Workbook

Sheet Microinformatica
F1: INFORMACION USUARIO EQUIPO ASIGNADO | O1: SOLO INFORMACION DEL EMPLEADO RESPONSABLE DE FEDERACION/ALMACAFE
A2: EMPRESA PROPIETARIO DEL EQUIPO | B2: DEPENDENCIA | C2: FUENTE DE RECURSO | D2: EMPRESA FUNCIONARIO | E2: EMPLEADO O CONTRATISTA | F2: CEDULA DEL FUNCIONARIO/CONTRATISTA | G2: SHORTNAME | H2: NOMBRES Y APELLIDOS | I2: DEPARTAMENTO | J2: CIUDAD | K2: CARGO | L2: ÁREA | M2: UBICACIÓN Y PISO | N2: TIPO DE RECURSO | O2: CEDULA | P2: NOMBRES Y APELLIDOS | Q2: CARGO | R2: CIUDAD | S2: AREA | T2: TIPO DE RECURSO | U2: TIPO | V2: SERIAL | W2: PLACA | X2: MARCA | Y2: MODELO | Z2: NOMBRE DE EQUIPO | AA2: ESTADO OPERATIVO | AB2: RAZÓN DEL ESTADO | AC2: ADMINISTRADO/CONTROLADO | AD2: PROCESADOR | AE2: MEMORIA RAM | AF2: TAMAÑO DISCO DURO | AG2: SISTEMA OPERATIVO | AH2: FECHA DE COMPRA | AI2: FIN DE GARANTIA | AJ2: TIEMPO USO (AÑOS) | AK2: TIPO DE PROPIEDAD | AL2: CHEKLIST (RESPONSABLE TI) | AM2: ORDEN DE REMISIÓN | AN2: OBSERVACIONES | AO2: TIPO DE PERFIL | AP2: TIPO DE EQUIPO | AQ2: TIPO DE RECURSO | AR2: CRUCE AV 23-12-2025 | AS2: Cruce Shortname | AT2: Resultado cruce AV
A3: FEDERACIÓN | B3: SUCURSAL IBAGUE | C3: FON1 | D3: FEDERACIÓN | E3: EMPLEADO | F3: 93370510 | G3: 93370510 | H3: ALEXANDER POLO PRIETO | I3: TOLIMA | J3: IBAGUE | K3: EXTENSIONISTA | L3: SECCIONAL IBAGUE | M3: 2 | N3: RECURSO PROPIO | O3: N/A | P3: N/A | Q3: N/A | R3: N/A | S3: N/A | U3: EQUIPO PORTATIL | V3: 9QH8SW3 | W3: F101875 | X3: DELL | Y3: Latitude 5450 | Z3: L11FETOLAPOL01 | AA3: EN OPERACION | AB3: ASIGNACION RESPONSABLE | AC3: CONTROLADO | AD3: Ultra 5 125u | AE3: 16GB | AF3: 500GB | AG3: WINDOWS 11 PRO | AH3: 45670 | AI3: 47497 | AJ3: =FLOOR(YEARFRAC(AH3, TODAY(), 1),1) -> 1 | AL3: JHONATHAN ARMANDO CAMARGO IZQUIERDO | AN3: N/A | AO3: N/A | AP3: N/A | AQ3: N/A | AR3: {=IFERROR(XLOOKUP(V3,'AV 23-12-2025'!A:A,'AV 23-12-2025'!D:D),"zz.No cruza con AV")} -> 19/12/25 5:24:37 COT | AS3: {=IFERROR(XLOOKUP(V3,'AV 23-12-2025'!A:A,'AV 23-12-2025'!C:C), "No cruza con AV")} -> ALEXANDER POLO | AT3: Si cruza con Antivirus
A4: FEDERACIÓN | B4: SUCURSAL IBAGUE | C4: FON1 | D4: FEDERACIÓN | E4: EMPLEADO | F4: 79912904 | H4: JAVIER LEONARDO MESA TRUJILLO | I4: TOLIMA | J4: IBAGUE | K4: ANALISTA | L4: PROYECTOS | M4: 2 | N4: RECURSO PROPIO | O4: N/A | P4: N/A | Q4: N/A | R4: N/A | S4: N/A | U4: EQUIPO ESCRITORIO | V4: 1NFPT64 | W4: 10105258 | X4: DELL | Y4: OPTIPLEX d15u MICRO 7020 | Z4: L11FETOLJMEZ01 | AA4: EN OPERACION | AB4: ASIGNACION RESPONSABLE | AC4: CONTROLADO | AD4: I7-14700t | AE4: 16GB | AF4: 500GB | AG4: WINDOWS 11 PRO | AH4: 45692 | AI4: 46882 | AJ4: =FLOOR(YEARFRAC(AH4, TODAY(), 1),1) -> 1 | AL4: JHONATHAN ARMANDO CAMARGO IZQUIERDO | AN4: N/A | AO4: N/A | AP4: N/A | AQ4: N/A | AR4: {=IFERROR(XLOOKUP(V4,'AV 23-12-2025'!A:A,'AV 23-12-2025'!D:D),"zz.No cruza con AV")} -> 23/12/25 7:38:03 COT | AS4: {=IFERROR(XLOOKUP(V4,'AV 23-12-2025'!A:A,'AV 23-12-2025'!C:C), "No cruza con AV")} -> JAVIER MEZA | AT4: Si cruza con Antivirus
A5: FEDERACIÓN | B5: SUCURSAL IBAGUE | C5: FON1 | D5: FEDERACIÓN | E5: EMPLEADO | F5: 1006118164 | H5: GISED CAMILA TOVAR ASCENCIO | I5: TOLIMA | J5: IBAGUE | K5: PROMOTOR DESARROLLO RURAL | L5: GOBERNACION DEL TOLIMA | M5: 2 | N5: RECURSO PROPIO | O5: N/A | P5: N/A | Q5: N/A | R5: N/A | S5: N/A | U5: EQUIPO PORTATIL | V5: BPLQ824 | W5: 10104244 | X5: DELL | Y5: Latitude 3440 | Z5: L11FETOLJDE3 | AA5: EN OPERACION | AB5: ASIGNACION RESPONSABLE | AC5: CONTROLADO | AD5: I5-1335u | AE5: 16GB | AF5: 500GB | AG5: WINDOWS 11 PRO | AH5: 45435 | AI5: 45946 | AJ5: =FLOOR(YEARFRAC(AH5, TODAY(), 1),1) -> 1 | AL5: JHONATHAN ARMANDO CAMARGO IZQUIERDO | AN5: N/A | AO5: N/A | AP5: N/A | AQ5: N/A | AR5: {=IFERROR(XLOOKUP(V5,'AV 23-12-2025'!A:A,'AV 23-12-2025'!D:D),"zz.No cruza con AV")} -> 19/12/25 12:26:35 COT | AS5: {=IFERROR(XLOOKUP(V5,'AV 23-12-2025'!A:A,'AV 23-12-2025'!C:C), "No cruza con AV")} -> JDE3 | AT5: Si cruza con Antivirus
A6: FEDERACIÓN | B6: SUCURSAL IBAGUE | C6: FON1 | D6: FEDERACIÓN | E6: EMPLEADO | F6: 5825253 | G6: 5825253 | H6: JORGE ELIECER CALDERON VILLAMIL | I6: TOLIMA | J6: IBAGUE | K6: COORDINADOR PROGRAMA | L6: PROGRAMA INVESTIGACION PARTICIPATIVA | M6: 2 | N6: RECURSO PROPIO | O6: N/A | P6: N/A | Q6: N/A | R6: N/A | S6: N/A | U6: EQUIPO PORTATIL | V6: B419SW3 | W6: F101887 | X6: DELL | Y6: Latitude 5450 | Z6: L11FETOLJCAL01 | AA6: EN OPERACION | AB6: ASIGNACION RESPONSABLE | AC6: CONTROLADO | AD6: Ultra 5 125u | AE6: 16GB | AF6: 500GB | AG6: WINDOWS 11 PRO | AH6: 45596 | AI6: 47497 | AJ6: =FLOOR(YEARFRAC(AH6, TODAY(), 1),1) -> 1 | AL6: JHONATHAN ARMANDO CAMARGO IZQUIERDO | AN6: N/A | AO6: N/A | AP6: N/A | AQ6: N/A | AR6: {=IFERROR(XLOOKUP(V6,'AV 23-12-2025'!A:A,'AV 23-12-2025'!D:D),"zz.No cruza con AV")} -> 23/12/25 12:37:17 COT | AS6: {=IFERROR(XLOOKUP(V6,'AV 23-12-2025'!A:A,'AV 23-12-2025'!C:C), "No cruza con AV")} -> JORGE CALDERON | AT6: Si cruza con Antivirus
A7: FEDERACIÓN | B7: SUCURSAL IBAGUE | C7: FON1 | D7: FEDERACIÓN | E7: EMPLEADO | F7: 1005692507 | G7: JVALENC507 | H7: JUANITA VALENCIA GARCIA | I7: TOLIMA | J7: IBAGUE | K7: AUXILIAR ADMINISTRATIVO | L7: ADMINISTRATIVOS | M7: 2 | N7: RECURSO PROPIO | O7: N/A | P7: N/A | Q7: N/A | R7: N/A | S7: N/A | U7: EQUIPO PORTATIL | V7: BW43B44 | W7: 10104274 | X7: DELL | Y7: Latitude 3440 | Z7: W11FETOL | AA7: EN OPERACION | AB7: ASIGNACION RESPONSABLE | AC7: CONTROLADO | AD7: I5-1235u | AE7: 16GB | AF7: 500GB | AG7: WINDOWS 11 PRO | AH7: 45537 | AI7: 45955 | AJ7: =FLOOR(YEARFRAC(AH7, TODAY(), 1),1) -> 1 | AL7: JHONATHAN ARMANDO CAMARGO IZQUIERDO | AN7: N/A | AO7: N/A | AP7: N/A | AQ7: N/A | AR7: {=IFERROR(XLOOKUP(V7,'AV 23-12-2025'!A:A,'AV 23-12-2025'!D:D),"zz.No cruza con AV")} -> zz.No cruza con AV | AS7: {=IFERROR(XLOOKUP(V7,'AV 23-12-2025'!A:A,'AV 23-12-2025'!C:C), "No cruza con AV")} -> No cruza con AV | AT7: No cruza con Antivirus
A8: FEDERACIÓN | B8: SUCURSAL IBAGUE | C8: FON1 | D8: FEDERACIÓN | E8: EMPLEADO | F8: 38210802 | G8: YBONILL802 | H8: YENNY PAOLA BONILLA ROJAS | I8: TOLIMA | J8: IBAGUE | K8: COORDINADOR ADMINISTRATIVO | L8: ADMINISTRATIVOS | M8: 2 | N8: RECURSO PROPIO | O8: N/A | P8: N/A | Q8: N/A | R8: N/A | S8: N/A | U8: EQUIPO ESCRITORIO | V8: 8QN0Y14 | W8: 10104277 | X8: DELL | Y8: OPTIPLEX Micro 7010 | Z8: D11FETOLYBON01 | AA8: EN OPERACION | AB8: ASIGNACION RESPONSABLE | AC8: CONTROLADO | AD8: I5-13500t | AE8: 16GB | AF8: 500GB | AG8: WINDOWS 11 PRO | AH8: 45405 | AI8: 46690 | AJ8: =FLOOR(YEARFRAC(AH8, TODAY(), 1),1) -> 1 | AL8: JHONATHAN ARMANDO CAMARGO IZQUIERDO | AN8: N/A | AO8: N/A | AP8: N/A | AQ8: N/A | AR8: {=IFERROR(XLOOKUP(V8,'AV 23-12-2025'!A:A,'AV 23-12-2025'!D:D),"zz.No cruza con AV")} -> 23/12/25 12:07:37 COT | AS8: {=IFERROR(XLOOKUP(V8,'AV 23-12-2025'!A:A,'AV 23-12-2025'!C:C), "No cruza con AV")} -> Paola Bonilla | AT8: Si cruza con Antivirus
A9: FEDERACIÓN | B9: SUCURSAL IBAGUE | C9: FON1 | D9: FEDERACIÓN | E9: EMPLEADO | F9: 65771971 | H9: JENNY TORRES ARANGO | I9: TOLIMA | J9: IBAGUE | K9: TESORERO AUXILIAR | L9: TESORERIA | M9: 2 | N9: RECURSO PROPIO | O9: N/A | P9: N/A | Q9: N/A | R9: N/A | S9: N/A | U9: EQUIPO ESCRITORIO | V9: 400SN40088 | W9: 10099137 | X9: COMPUMAX | Y9: 1052-900-0078 | Z9: W11FETOLJTOR | AA9: EN OPERACION | AB9: ASIGNACION RESPONSABLE | AC9: CONTROLADO | AD9: I5-11400 | AE9: 16GB | AF9: 500GB | AG9: WINDOWS 11 PRO | AH9: 45087 | AI9: NO REGISTRA | AJ9: =FLOOR(YEARFRAC(AH9, TODAY(), 1),1) -> 2 | AL9: JHONATHAN ARMANDO CAMARGO IZQUIERDO | AN9: N/A | AO9: N/A | AP9: N/A | AQ9: N/A | AR9: {=IFERROR(XLOOKUP(V9,'AV 23-12-2025'!A:A,'AV 23-12-2025'!D:D),"zz.No cruza con AV")} -> 23/12/25 12:15:23 COT | AS9: {=IFERROR(XLOOKUP(V9,'AV 23-12-2025'!A:A,'AV 23-12-2025'!C:C), "No cruza con AV")} -> Jenny Torres | AT9: Si cruza con Antivirus
A10: FEDERACIÓN | B10: SUCURSAL IBAGUE | C10: FON1 | D10: FEDERACIÓN | E10: EMPLEADO | F10: 1053767215 | G10: JHINCAP215 | H10: JULIAN DAVID HINCAPIE BETANCUR | I10: TOLIMA | J10: IBAGUE | K10: LIDER DEPARTAMENTAL EXTENSION RURAL | L10: EXTENSION RURAL | M10: 2 | N10: RECURSO PROPIO | O10: N/A | P10: N/A | Q10: N/A | R10: N/A | S10: N/A | U10: EQUIPO ESCRITORIO | V10: J517XV3 | W10: 10101123 | X10: DELL | Y10: OPTIPLEX 7010 d15u | Z10: L11FETOLJHIN01 | AA10: EN OPERACION | AB10: ASIGNACION RESPONSABLE | AC10: CONTROLADO | AD10: I5-13500t | AE10: 8GB | AF10: 500GB | AG10: WINDOWS 11 PRO | AH10: 45097 | AI10: 46343 | AJ10: =FLOOR(YEARFRAC(AH10, TODAY(), 1),1) -> 2 | AL10: JHONATHAN ARMANDO CAMARGO IZQUIERDO | AN10: N/A | AO10: N/A | AP10: N/A | AQ10: N/A | AR10: {=IFERROR(XLOOKUP(V10,'AV 23-12-2025'!A:A,'AV 23-12-2025'!D:D),"zz.No cruza con AV")} -> zz.No cruza con AV | AS10: {=IFERROR(XLOOKUP(V10,'AV 23-12-2025'!A:A,'AV 23-12-2025'!C:C), "No cruza con AV")} -> No cruza con AV | AT10: No cruza con Antivirus
A11: FEDERACIÓN | B11: SUCURSAL IBAGUE | C11: FON1 | D11: FEDERACIÓN | E11: EMPLEADO | F11: 28559149 | G11: FESGUE | H11: SVETLANY GUEPENDO ORTIZ | I11: TOLIMA | J11: IBAGUE | K11: ANALISTA | L11: EXTENSION RURAL | M11: 2 | N11: RECURSO PROPIO | O11: N/A | P11: N/A | Q11: N/A | R11: N/A | S11: N/A | U11: EQUIPO ESCRITORIO | V11: 1617XV3 | W11: 1010178 | X11: DELL | Y11: OPTIPLEX MICRO 7010 | Z11: D11FETOLSGUE01 | AA11: EN OPERACION | AB11: ASIGNACION RESPONSABLE | AC11: CONTROLADO | AD11: I3 | AE11: 8GB | AF11: 250GB | AG11: WINDOWS 11 PRO | AH11: 45097 | AI11: 46343 | AJ11: =FLOOR(YEARFRAC(AH11, TODAY(), 1),1) -> 2 | AL11: JHONATHAN ARMANDO CAMARGO IZQUIERDO | AN11: N/A | AO11: N/A | AP11: N/A | AQ11: N/A | AR11: {=IFERROR(XLOOKUP(V11,'AV 23-12-2025'!A:A,'AV 23-12-2025'!D:D),"zz.No cruza con AV")} -> 19/12/25 14:42:28 COT | AS11: {=IFERROR(XLOOKUP(V11,'AV 23-12-2025'!A:A,'AV 23-12-2025'!C:C), "No cruza con AV")} -> Svetlany Guependo | AT11: Si cruza con Antivirus
A12: FEDERACIÓN | B12: SUCURSAL IBAGUE | C12: FON1 | D12: FEDERACIÓN | E12: EMPLEADO | F12: 1007790166 | H12: YINA PAOLA OLAVE ANDRADE | I12: TOLIMA | J12: IBAGUE | K12: AUXILIAR ADMINISTRATIVO | L12: SECCIONAL IBAGUE | M12: 2 | N12: RECURSO PROPIO | O12: N/A | P12: N/A | Q12: N/A | R12: N/A | S12: N/A | U12: EQUIPO ESCRITORIO | V12: F717XV3 | W12: F717xv3CAMBIAR | X12: DELL | Y12: OPTIPLEX Micro 7010 | Z12: D11FETOLYOLA01 | AA12: EN OPERACION | AB12: ASIGNACION RESPONSABLE | AC12: CONTROLADO | AD12: I5-13500t | AE12: 16GB | AF12: 500GB | AG12: WINDOWS 11 PRO | AH12: 45097 | AI12: 46343 | AJ12: =FLOOR(YEARFRAC(AH12, TODAY(), 1),1) -> 2 | AL12: JHONATHAN ARMANDO CAMARGO IZQUIERDO | AN12: N/A | AO12: N/A | AP12: N/A | AQ12: N/A | AR12: {=IFERROR(XLOOKUP(V12,'AV 23-12-2025'!A:A,'AV 23-12-2025'!D:D),"zz.No cruza con AV")} -> 18/12/25 16:27:54 COT | AS12: {=IFERROR(XLOOKUP(V12,'AV 23-12-2025'!A:A,'AV 23-12-2025'!C:C), "No cruza con AV")} -> Yina Olave | AT12: Si cruza con Antivirus
A13: FEDERACIÓN | B13: SUCURSAL IBAGUE | C13: FON1 | D13: FEDERACIÓN | E13: EMPLEADO | F13: 1110541614 | G13: JCAMARG614 | H13: JHONATHAN ARMANDO CAMARGO IZQUIERDO | I13: TOLIMA | J13: IBAGUE | K13: ANALISTA TIC | L13: TIC | M13: 2 | N13: RECURSO PROPIO | O13: N/A | P13: N/A | Q13: N/A | R13: N/A | S13: N/A | U13: EQUIPO ESCRITORIO | V13: 8517XV3 | W13: 10101201 | X13: DELL | Y13: OPTIPLEX MICRO 7010 | Z13: No Aplica | AA13: ALMACENADO | AB13: ALISTAMIENTO/SOPORTE | AC13: CONTROLADO | AD13: Core i5 10 | AE13: 8GB | AF13: 512GB | AG13: No Aplica | AH13: 45097 | AI13: 46343 | AJ13: =FLOOR(YEARFRAC(AH13, TODAY(), 1),1) -> 2 | AL13: JHONATHAN ARMANDO CAMARGO IZQUIERDO | AN13: SIN USUARIO - PARA DESBLOQUEAR BIOS | AO13: N/A | AP13: N/A | AQ13: N/A | AR13: {=IFERROR(XLOOKUP(V13,'AV 23-12-2025'!A:A,'AV 23-12-2025'!D:D),"zz.No cruza con AV")} -> 10/05/25 11:49:29 COT | AS13: {=IFERROR(XLOOKUP(V13,'AV 23-12-2025'!A:A,'AV 23-12-2025'!C:C), "No cruza con AV")} -> Ingrid Segura | AT13: Si cruza con Antivirus
A14: FEDERACIÓN | B14: SUCURSAL IBAGUE | C14: FON1 | D14: FEDERACIÓN | E14: EMPLEADO | F14: 1105335001 | H14: JULIAN ANDRES LEITON CARDENAS | I14: TOLIMA | J14: IBAGUE | K14: PROFESIONAL DESARROLLO SOCIAL | L14: DESARROLLO SOCIAL | M14: 2 | N14: RECURSO PROPIO | O14: N/A | P14: N/A | Q14: N/A | R14: N/A | S14: N/A | U14: EQUIPO PORTATIL | V14: 1FBVYH3 | W14: 10095976 | X14: DELL | Y14: Vostro 3400 | Z14: L11FETOLJULIANLEITON | AA14: EN OPERACION | AB14: ASIGNACION RESPONSABLE | AC14: CONTROLADO | AD14: I5-1135g7 | AE14: 16GB | AF14: 500GB | AG14: WINDOWS 11 PRO | AH14: 44540 | AI14: 44959 | AJ14: =FLOOR(YEARFRAC(AH14, TODAY(), 1),1) -> 4 | AL14: JHONATHAN ARMANDO CAMARGO IZQUIERDO | AN14: N/A | AO14: N/A | AP14: N/A | AQ14: N/A | AR14: {=IFERROR(XLOOKUP(V14,'AV 23-12-2025'!A:A,'AV 23-12-2025'!D:D),"zz.No cruza con AV")} -> 1/10/25 16:34:19 COT | AS14: {=IFERROR(XLOOKUP(V14,'AV 23-12-2025'!A:A,'AV 23-12-2025'!C:C), "No cruza con AV")} -> Julian Leiton | AT14: Si cruza con Antivirus
A15: FEDERACIÓN | B15: SUCURSAL IBAGUE | C15: FON1 | D15: FEDERACIÓN | E15: CONTRATISTA | F15: 1110575083 | G15: ADIAZ083 | H15: ANGIE PAOLA DIAZ MORA | I15: TOLIMA | J15: IBAGUE | K15: AUXILIAR ADMINISTRATIVO | L15: BENEFICIO ECOLOGICO | M15: 2 | N15: RECURSO PROPIO | O15: 1110585547 | P15: GERMAN CAMILO ROMERO MOSQUERA | Q15: COORDINADOR BENEFICIO ECOLOGICO | R15: IBAGUE | S15: BENEFICIO ECOLOGICO | T15: RECURSO PROPIO | U15: EQUIPO PORTATIL | V15: 8VVJS93 | W15: 10105240 | X15: DELL | Y15: Latitude 3420 | Z15: L11FETOLCRED1 | AA15: EN OPERACION | AB15: ASIGNACION RESPONSABLE | AC15: CONTROLADO | AD15: I3-1115g4 | AE15: 4GB | AF15: 250GB | AG15: WINDOWS 11 PRO | AH15: 44351 | AI15: 44787 | AJ15: =FLOOR(YEARFRAC(AH15, TODAY(), 1),1) -> 4 | AL15: JHONATHAN ARMANDO CAMARGO IZQUIERDO | AN15: N/A | AO15: N/A | AP15: N/A | AQ15: N/A | AR15: {=IFERROR(XLOOKUP(V15,'AV 23-12-2025'!A:A,'AV 23-12-2025'!D:D),"zz.No cruza con AV")} -> zz.No cruza con AV | AS15: {=IFERROR(XLOOKUP(V15,'AV 23-12-2025'!A:A,'AV 23-12-2025'!C:C), "No cruza con AV")} -> No cruza con AV | AT15: No cruza con Antivirus
A16: FEDERACIÓN | B16: SUCURSAL IBAGUE | C16: FON1 | D16: FEDERACIÓN | E16: EMPLEADO | F16: 65719793 | G16: 65719793 | H16: BELLY LUZ DELGADO ARBOLEDA | I16: TOLIMA | J16: IBAGUE | K16: COORDINADOR SECCIONAL EXTENSION RURAL | L16: SECCIONAL RIOBLANCO | M16: 2 | N16: RECURSO PROPIO | O16: N/A | P16: N/A | Q16: N/A | R16: N/A | S16: N/A | U16: EQUIPO PORTATIL | V16: FVVJS93 | W16: 10105232 | X16: DELL | Y16: Latitude 3420 | Z16: L11FETOLRENOV2 | AA16: EN OPERACION | AB16: ASIGNACION RESPONSABLE | AC16: CONTROLADO | AD16: I3-1115g4 | AE16: 4GB | AF16: 250GB | AG16: WINDOWS 11 PRO | AH16: 44351 | AI16: 44787 | AJ16: =FLOOR(YEARFRAC(AH16, TODAY(), 1),1) -> 4 | AL16: JHONATHAN ARMANDO CAMARGO IZQUIERDO | AN16: N/A | AO16: N/A | AP16: N/A | AQ16: N/A | AR16: {=IFERROR(XLOOKUP(V16,'AV 23-12-2025'!A:A,'AV 23-12-2025'!D:D),"zz.No cruza con AV")} -> zz.No cruza con AV | AS16: {=IFERROR(XLOOKUP(V16,'AV 23-12-2025'!A:A,'AV 23-12-2025'!C:C), "No cruza con AV")} -> No cruza con AV | AT16: No cruza con Antivirus
A17: FEDERACIÓN | B17: SUCURSAL IBAGUE | C17: FON1 | D17: FEDERACIÓN | E17: EMPLEADO | F17: 1058274307 | H17: CARLOS ALFONSO TIBADUIZA VIANCHA | I17: TOLIMA | J17: IBAGUE | K17: COORDINADOR PROGRAMA | L17: PROGRAMA BENEFICIO Y CALIDAD | M17: 2 | N17: RECURSO PROPIO | O17: N/A | P17: N/A | Q17: N/A | R17: N/A | S17: N/A | U17: EQUIPO ESCRITORIO | V17: 207FMJ3 | W17: 10095983 | X17: DELL | Y17: OPTIPLEX 3080 | Z17: D10FETOLCTIB01 | AA17: EN OPERACION | AB17: ASIGNACION RESPONSABLE | AC17: CONTROLADO | AD17: I5-10500t | AE17: 16GB | AF17: 500GB | AG17: WINDOWS 10 PRO | AH17: 44525 | AI17: 45690 | AJ17: =FLOOR(YEARFRAC(AH17, TODAY(), 1),1) -> 4 | AL17: JHONATHAN ARMANDO CAMARGO IZQUIERDO | AN17: N/A | AO17: PERFIL 3 | AP17: DESKTOP TOWER/SFF DE ALTO RENDIMIENTO | AQ17: RECURSOS BOGOTA | AR17: {=IFERROR(XLOOKUP(V17,'AV 23-12-2025'!A:A,'AV 23-12-2025'!D:D),"zz.No cruza con AV")} -> 19/12/25 17:53:03 COT | AS17: {=IFERROR(XLOOKUP(V17,'AV 23-12-2025'!A:A,'AV 23-12-2025'!C:C), "No cruza con AV")} -> Carlos Tibaduiza | AT17: Si cruza con Antivirus
A18: FEDERACIÓN | B18: SUCURSAL IBAGUE | C18: FON1 | D18: FEDERACIÓN | E18: CONTRATISTA | F18: 1110552207 | G18: CGUERRA207 | H18: CRISTHIAN FELIPE GUERRA RODRIGUEZ | I18: TOLIMA | J18: IBAGUE | K18: AUXILIAR ADMINISTRATIVO | L18: BENEFICIO ECOLOGICO | M18: 2 | N18: RECURSO PROPIO | O18: 1110585547 | P18: GERMAN CAMILO ROMERO MOSQUERA | Q18: COORDINADOR BENEFICIO ECOLOGICO | R18: IBAGUE | S18: BENEFICIO ECOLOGICO | T18: RECURSO PROPIO | U18: EQUIPO PORTATIL | V18: 35WJS93 | W18: 10105229 | X18: DELL | Y18: Latitude 3420 | Z18: L11FETOLREN4 | AA18: EN OPERACION | AB18: ASIGNACION RESPONSABLE | AC18: CONTROLADO | AD18: I3-1115g4 | AE18: 4GB | AF18: 250GB | AG18: WINDOWS 11 PRO | AH18: 44351 | AI18: 44787 | AJ18: =FLOOR(YEARFRAC(AH18, TODAY(), 1),1) -> 4 | AL18: JHONATHAN ARMANDO CAMARGO IZQUIERDO | AN18: N/A | AO18: N/A | AP18: N/A | AQ18: N/A | AR18: {=IFERROR(XLOOKUP(V18,'AV 23-12-2025'!A:A,'AV 23-12-2025'!D:D),"zz.No cruza con AV")} -> 23/12/25 12:39:31 COT | AS18: {=IFERROR(XLOOKUP(V18,'AV 23-12-2025'!A:A,'AV 23-12-2025'!C:C), "No cruza con AV")} -> Renova4 | AT18: Si cruza con Antivirus
A19: FEDERACIÓN | B19: SUCURSAL IBAGUE | C19: FON1 | D19: FEDERACIÓN | E19: EMPLEADO | F19: 93387546 | G19: FEFEPER | H19: FERNANDO PEREZ MARTINEZ | I19: TOLIMA | J19: IBAGUE | K19: PROFESIONAL DESARROLLO SOCIAL | L19: DESARROLLO SOCIAL | M19: 2 | N19: RECURSO PROPIO | O19: N/A | P19: N/A | Q19: N/A | R19: N/A | S19: N/A | U19: EQUIPO PORTATIL | V19: 1ZDSGJ3 | W19: 10095969 | X19: DELL | Y19: Vostro 3400 | Z19: L10FETOLFPER | AA19: EN OPERACION | AB19: ASIGNACION RESPONSABLE | AC19: CONTROLADO | AD19: I5-1135g7 | AE19: 16GB | AF19: 500GB | AG19: WINDOWS 11 PRO | AH19: 44512 | AI19: 44947 | AJ19: =FLOOR(YEARFRAC(AH19, TODAY(), 1),1) -> 4 | AL19: JHONATHAN ARMANDO CAMARGO IZQUIERDO | AN19: N/A | AO19: N/A | AP19: N/A | AQ19: N/A | AR19: {=IFERROR(XLOOKUP(V19,'AV 23-12-2025'!A:A,'AV 23-12-2025'!D:D),"zz.No cruza con AV")} -> 23/12/25 12:01:10 COT | AS19: {=IFERROR(XLOOKUP(V19,'AV 23-12-2025'!A:A,'AV 23-12-2025'!C:C), "No cruza con AV")} -> DELL | AT19: Si cruza con Antivirus
A20: FEDERACIÓN | B20: SUCURSAL IBAGUE | C20: FON1 | D20: FEDERACIÓN | E20: EMPLEADO | F20: 93410091 | G20: HHINCAP091 | H20: HECTOR JAVIER HINCAPIE ARISTIZABAL | I20: TOLIMA | J20: IBAGUE | K20: COORDINADOR PROGRAMA | L20: PROGRAMA SICA | M20: 2 | N20: RECURSO PROPIO | O20: N/A | P20: N/A | Q20: N/A | R20: N/A | S20: N/A | U20: EQUIPO ESCRITORIO | V20: 507FMJ3 | W20: 1009582 | X20: DELL | Y20: OPTIPLEX 3080 | Z20: PENDIENTE SIN ROOT | AA20: EN OPERACION | AB20: ASIGNACION RESPONSABLE | AC20: CONTROLADO | AD20: I5-10500t | AE20: 8GB | AF20: 250GB | AG20: WINDOWS 11 PRO | AH20: 44525 | AI20: 45690 | AJ20: =FLOOR(YEARFRAC(AH20, TODAY(), 1),1) -> 4 | AL20: JHONATHAN ARMANDO CAMARGO IZQUIERDO | AN20: N/A | AO20: PERFIL 3 | AP20: DESKTOP TOWER/SFF DE ALTO RENDIMIENTO | AQ20: RECURSOS BOGOTA | AR20: {=IFERROR(XLOOKUP(V20,'AV 23-12-2025'!A:A,'AV 23-12-2025'!D:D),"zz.No cruza con AV")} -> 19/12/25 12:16:18 COT | AS20: {=IFERROR(XLOOKUP(V20,'AV 23-12-2025'!A:A,'AV 23-12-2025'!C:C), "No cruza con AV")} -> Javier Hincapie | AT20: Si cruza con Antivirus
A21: FEDERACIÓN | B21: SUCURSAL IBAGUE | C21: FON1 | D21: FEDERACIÓN | E21: EMPLEADO | F21: 38210802 | G21: YBONILL802 | H21: YENNY PAOLA BONILLA ROJAS | I21: TOLIMA | J21: IBAGUE | K21: COORDINADOR ADMINISTRATIVO | L21: ADMINISTRATIVOS | M21: 2 | N21: RECURSO PROPIO | O21: N/A | P21: N/A | Q21: N/A | R21: N/A | S21: N/A | U21: EQUIPO PORTATIL | V21: G4K54B3 | W21: 10095920 | X21: DELL | Y21: Latitude | Z21: L10FETOLAROM | AA21: EN OPERACION | AB21: ASIGNACION RESPONSABLE | AC21: CONTROLADO | AD21: I3-115g4 | AE21: 8GB | AF21: 250GB | AG21: WINDOWS 11 PRO | AH21: 44412 | AI21: 45540 | AJ21: =FLOOR(YEARFRAC(AH21, TODAY(), 1),1) -> 4 | AL21: JHONATHAN ARMANDO CAMARGO IZQUIERDO | AN21: N/A | AO21: N/A | AP21: N/A | AQ21: N/A | AR21: {=IFERROR(XLOOKUP(V21,'AV 23-12-2025'!A:A,'AV 23-12-2025'!D:D),"zz.No cruza con AV")} -> 22/12/25 13:29:04 COT | AS21: {=IFERROR(XLOOKUP(V21,'AV 23-12-2025'!A:A,'AV 23-12-2025'!C:C), "No cruza con AV")} -> Alejandra Romero | AT21: Si cruza con Antivirus
A22: FEDERACIÓN | B22: SUCURSAL IBAGUE | C22: FON1 | D22: FEDERACIÓN | E22: EMPLEADO | F22: 1104939227 | H22: MARIA JOSE AYA VARELA | I22: TOLIMA | J22: IBAGUE | K22: AUXILIAR ADMINISTRATIVO | L22: ADMINISTRATIVOS | M22: 2 | N22: RECURSO PROPIO | O22: N/A | P22: N/A | Q22: N/A | R22: N/A | S22: N/A | U22: EQUIPO ESCRITORIO | V22: D1DNH03 | W22: 10085705 | X22: DELL | Y22: OPTIPLEX 3070 | Z22: D11FETOLMAYA01 | AA22: EN OPERACION | AB22: ASIGNACION RESPONSABLE | AC22: CONTROLADO | AD22: I5-9500 | AE22: 16GB | AF22: 500GB | AG22: WINDOWS 11 PRO | AH22: 43805 | AI22: 44931 | AJ22: =FLOOR(YEARFRAC(AH22, TODAY(), 1),1) -> 6 | AL22: JHONATHAN ARMANDO CAMARGO IZQUIERDO | AN22: N/A | AO22: N/A | AP22: N/A | AQ22: N/A | AR22: {=IFERROR(XLOOKUP(V22,'AV 23-12-2025'!A:A,'AV 23-12-2025'!D:D),"zz.No cruza con AV")} -> 23/12/25 12:44:17 COT | AS22: {=IFERROR(XLOOKUP(V22,'AV 23-12-2025'!A:A,'AV 23-12-2025'!C:C), "No cruza con AV")} -> Valentina Vergara | AT22: Si cruza con Antivirus
A23: FEDERACIÓN | B23: SUCURSAL IBAGUE | C23: FON1 | D23: FEDERACIÓN | E23: EMPLEADO | F23: 38210802 | G23: YBONILL802 | H23: YENNY PAOLA BONILLA ROJAS | I23: TOLIMA | J23: IBAGUE | K23: COORDINADOR ADMINISTRATIVO | L23: ADMINISTRATIVOS | M23: 2 | N23: RECURSO PROPIO | O23: N/A | P23: N/A | Q23: N/A | R23: N/A | S23: N/A | U23: EQUIPO PORTATIL | V23: 5CG03799TD | W23: 10085754 | X23: HP | Y23: Hp 240 g7 | Z23: L10FETOLYBON2 | AA23: EN OPERACION | AB23: ASIGNACION RESPONSABLE | AC23: CONTROLADO | AD23: I5-1035g1 | AE23: 8GB | AF23: 250GB | AG23: WINDOWS 11 PRO | AH23: 44138 | AI23: 44502 | AJ23: =FLOOR(YEARFRAC(AH23, TODAY(), 1),1) -> 5 | AL23: JHONATHAN ARMANDO CAMARGO IZQUIERDO | AN23: N/A | AO23: N/A | AP23: N/A | AQ23: N/A | AR23: {=IFERROR(XLOOKUP(V23,'AV 23-12-2025'!A:A,'AV 23-12-2025'!D:D),"zz.No cruza con AV")} -> zz.No cruza con AV | AS23: {=IFERROR(XLOOKUP(V23,'AV 23-12-2025'!A:A,'AV 23-12-2025'!C:C), "No cruza con AV")} -> No cruza con AV | AT23: No cruza con Antivirus
A24: FEDERACIÓN | B24: SUCURSAL IBAGUE | C24: FON1 | D24: FEDERACIÓN | E24: EMPLEADO | F24: 28554485 | G24: FTEROJ | H24: EDNA MAGALLY ROJAS HERRERA | I24: TOLIMA | J24: IBAGUE | K24: COORDINADOR FINANCIERO | L24: FINANCIEROS | M24: 2 | N24: RECURSO PROPIO | O24: N/A | P24: N/A | Q24: N/A | R24: N/A | S24: N/A | U24: EQUIPO ESCRITORIO | V24: 4QVWHV2 | W24: 10081783 | X24: DELL | Y24: OPTIPLEX 3060 | Z24: W10FETOLEROJ | AA24: EN OPERACION | AB24: ASIGNACION RESPONSABLE | AC24: CONTROLADO | AD24: I5-8400 | AE24: 16GB | AF24: 500GB | AG24: WINDOWS 11 PRO | AH24: 43546 | AI24: 44672 | AJ24: =FLOOR(YEARFRAC(AH24, TODAY(), 1),1) -> 6 | AL24: JHONATHAN ARMANDO CAMARGO IZQUIERDO | AN24: N/A | AO24: N/A | AP24: N/A | AQ24: N/A | AR24: {=IFERROR(XLOOKUP(V24,'AV 23-12-2025'!A:A,'AV 23-12-2025'!D:D),"zz.No cruza con AV")} -> 23/12/25 12:46:03 COT | AS24: {=IFERROR(XLOOKUP(V24,'AV 23-12-2025'!A:A,'AV 23-12-2025'!C:C), "No cruza con AV")} -> Magally Rojas | AT24: Si cruza con Antivirus
A25: FEDERACIÓN | B25: SUCURSAL IBAGUE | C25: FON1 | D25: FEDERACIÓN | E25: EMPLEADO | F25: 1110584632 | G25: EDUQUE632 | H25: EDUARD DAVID DUQUE OTALVARO | I25: TOLIMA | J25: IBAGUE | K25: ANALISTA FINANCIERO | L25: FINANCIEROS | M25: 2 | N25: RECURSO PROPIO | O25: N/A | P25: N/A | Q25: N/A | R25: N/A | S25: N/A | U25: EQUIPO ESCRITORIO | V25: 9479778446 | W25: 10081782 | X25: DELL | Y25: OPTIPLEX 360 | Z25: D10FETOLEDUQ01 | AA25: EN OPERACION | AB25: ASIGNACION RESPONSABLE | AC25: CONTROLADO | AD25: I5-8400 | AE25: 8GB | AF25: 500GB | AG25: WINDOWS 10 PRO | AH25: 43546 | AI25: 44672 | AJ25: =FLOOR(YEARFRAC(AH25, TODAY(), 1),1) -> 6 | AL25: JHONATHAN ARMANDO CAMARGO IZQUIERDO | AN25: N/A | AO25: PERFIL 1 | AP25: DESKTOP | AQ25: PAC | AR25: {=IFERROR(XLOOKUP(V25,'AV 23-12-2025'!A:A,'AV 23-12-2025'!D:D),"zz.No cruza con AV")} -> zz.No cruza con AV | AS25: {=IFERROR(XLOOKUP(V25,'AV 23-12-2025'!A:A,'AV 23-12-2025'!C:C), "No cruza con AV")} -> No cruza con AV | AT25: No cruza con Antivirus
A26: FEDERACIÓN | B26: SUCURSAL IBAGUE | C26: FON1 | D26: FEDERACIÓN | E26: EMPLEADO | F26: 65748443 | G26: FEMHER | H26: MARIA VICTORIA HERRERA POLANIA | I26: TOLIMA | J26: IBAGUE | K26: COORDINADOR PROGRAMA | L26: PROGRAMA COMUNICACIONES | M26: 2 | N26: RECURSO PROPIO | O26: N/A | P26: N/A | Q26: N/A | R26: N/A | S26: N/A | U26: EQUIPO ESCRITORIO | V26: 7NP4FW2 | W26: 10085607 | X26: DELL | Y26: OPTIPLEX 3060 | Z26: W11FETOLMVHERRE | AA26: EN OPERACION | AB26: ASIGNACION RESPONSABLE | AC26: CONTROLADO | AD26: I5-8400 | AE26: 16GB | AF26: 250GB | AG26: WINDOWS 11 PRO | AH26: 43609 | AI26: 44892 | AJ26: =FLOOR(YEARFRAC(AH26, TODAY(), 1),1) -> 6 | AL26: JHONATHAN ARMANDO CAMARGO IZQUIERDO | AN26: N/A | AO26: PERFIL 3 | AP26: DESKTOP TOWER/SFF DE ALTO RENDIMIENTO | AQ26: RECURSOS BOGOTA | AR26: {=IFERROR(XLOOKUP(V26,'AV 23-12-2025'!A:A,'AV 23-12-2025'!D:D),"zz.No cruza con AV")} -> 19/12/25 17:39:58 COT | AS26: {=IFERROR(XLOOKUP(V26,'AV 23-12-2025'!A:A,'AV 23-12-2025'!C:C), "No cruza con AV")} -> Maria Herrera | AT26: Si cruza con Antivirus
A27: FEDERACIÓN | B27: SUCURSAL IBAGUE | C27: FON1 | D27: FEDERACIÓN | E27: EMPLEADO | F27: 1005720239 | G27: SCANO239 | H27: SARA VALENTINA CANO OSPINA | I27: TOLIMA | J27: IBAGUE | K27: AUXILIAR ADMINISTRATIVO | L27: ADMINISTRATIVOS | M27: 2 | N27: RECURSO PROPIO | O27: N/A | P27: N/A | Q27: N/A | R27: N/A | S27: N/A | U27: EQUIPO ESCRITORIO | V27: 4QRZHV2 | W27: 10081781 | X27: DELL | Y27: OPTIPLEX 3060 | Z27: D10FETOLSCAN01 | AA27: EN OPERACION | AB27: ASIGNACION RESPONSABLE | AC27: CONTROLADO | AD27: I5-8400 | AE27: 8GB | AF27: 500GB | AG27: WINDOWS 11 PRO | AH27: 43546 | AI27: 44672 | AJ27: =FLOOR(YEARFRAC(AH27, TODAY(), 1),1) -> 6 | AL27: JHONATHAN ARMANDO CAMARGO IZQUIERDO | AN27: N/A | AO27: N/A | AP27: N/A | AQ27: N/A | AR27: {=IFERROR(XLOOKUP(V27,'AV 23-12-2025'!A:A,'AV 23-12-2025'!D:D),"zz.No cruza con AV")} -> 23/12/25 10:58:55 COT | AS27: {=IFERROR(XLOOKUP(V27,'AV 23-12-2025'!A:A,'AV 23-12-2025'!C:C), "No cruza con AV")} -> Sara Cano | AT27: Si cruza con Antivirus
A28: FEDERACIÓN | B28: SUCURSAL IBAGUE | C28: FON1 | D28: FEDERACIÓN | E28: EMPLEADO | F28: 93362708 | G28: CO93362708 | H28: FERNANDO AUGUSTO VARGAS RIOS | I28: TOLIMA | J28: IBAGUE | K28: ANALISTA | L28: EXTENSION RURAL | M28: 2 | N28: RECURSO PROPIO | O28: N/A | P28: N/A | Q28: N/A | R28: N/A | S28: N/A | U28: EQUIPO ESCRITORIO | V28: 6XL41M2 | W28: 20008744 | X28: DELL | Y28: OPTIPLEX 3050 | Z28: D10FETOLFVAR01 | AA28: EN OPERACION | AB28: ASIGNACION RESPONSABLE | AC28: CONTROLADO | AD28: I5-7500 | AE28: 8GB | AF28: 500GB | AG28: WINDOWS 10 PRO | AH28: 43073 | AI28: 44199 | AJ28: =FLOOR(YEARFRAC(AH28, TODAY(), 1),1) -> 8 | AL28: JHONATHAN ARMANDO CAMARGO IZQUIERDO | AN28: N/A | AO28: PERFIL 1 | AP28: DESKTOP | AQ28: PAC | AR28: {=IFERROR(XLOOKUP(V28,'AV 23-12-2025'!A:A,'AV 23-12-2025'!D:D),"zz.No cruza con AV")} -> 23/12/25 12:22:25 COT | AS28: {=IFERROR(XLOOKUP(V28,'AV 23-12-2025'!A:A,'AV 23-12-2025'!C:C), "No cruza con AV")} -> Fernando Vargas | AT28: Si cruza con Antivirus
A29: FEDERACIÓN | B29: SUCURSAL IBAGUE | C29: FON1 | D29: FEDERACIÓN | E29: EMPLEADO | F29: 65553626 | G29: IRAMIRE626 | H29: ILSA RAMIREZ RAMIREZ | I29: TOLIMA | J29: IBAGUE | K29: ANALISTA FINANCIERO | L29: FINANCIEROS | M29: 2 | N29: RECURSO PROPIO | O29: N/A | P29: N/A | Q29: N/A | R29: N/A | S29: N/A | U29: EQUIPO ESCRITORIO | V29: 74VZ0M2 | W29: 20008877 | X29: DELL | Y29: OPTIPLEX 3050 | Z29: W11FETOLIRAM | AA29: EN OPERACION | AB29: ASIGNACION RESPONSABLE | AC29: CONTROLADO | AD29: I5-7500 | AE29: 8GB | AF29: 500GB | AG29: WINDOWS 11 PRO | AH29: 43073 | AI29: 44199 | AJ29: =FLOOR(YEARFRAC(AH29, TODAY(), 1),1) -> 8 | AL29: JHONATHAN ARMANDO CAMARGO IZQUIERDO | AN29: N/A | AO29: N/A | AP29: N/A | AQ29: N/A | AR29: {=IFERROR(XLOOKUP(V29,'AV 23-12-2025'!A:A,'AV 23-12-2025'!D:D),"zz.No cruza con AV")} -> zz.No cruza con AV | AS29: {=IFERROR(XLOOKUP(V29,'AV 23-12-2025'!A:A,'AV 23-12-2025'!C:C), "No cruza con AV")} -> No cruza con AV | AT29: No cruza con Antivirus
A30: FEDERACIÓN | B30: SUCURSAL IBAGUE | C30: FON1 | D30: FEDERACIÓN | E30: EMPLEADO | F30: 39580689 | G30: FEBMAR | H30: BIBIANA MARCELA MARTINEZ BARRERO | I30: TOLIMA | J30: IBAGUE | K30: AUXILIAR ADMINISTRATIVO | L30: ADMINISTRATIVOS | M30: 2 | N30: RECURSO PROPIO | O30: N/A | P30: N/A | Q30: N/A | R30: N/A | S30: N/A | U30: EQUIPO ESCRITORIO | V30: 1FYTSD2 | W30: 10078204 | X30: DELL | Y30: OPTIPLEX 3040 | Z30: W11FETOLBIMA | AA30: EN OPERACION | AB30: ASIGNACION RESPONSABLE | AC30: CONTROLADO | AD30: I5-6500 | AE30: 8GB | AF30: 500GB | AG30: WINDOWS 11 PRO | AH30: 42697 | AI30: 43823 | AJ30: =FLOOR(YEARFRAC(AH30, TODAY(), 1),1) -> 9 | AL30: JHONATHAN ARMANDO CAMARGO IZQUIERDO | AN30: N/A | AO30: N/A | AP30: N/A | AQ30: N/A | AR30: {=IFERROR(XLOOKUP(V30,'AV 23-12-2025'!A:A,'AV 23-12-2025'!D:D),"zz.No cruza con AV")} -> 23/12/25 12:55:16 COT | AS30: {=IFERROR(XLOOKUP(V30,'AV 23-12-2025'!A:A,'AV 23-12-2025'!C:C), "No cruza con AV")} -> Bibiana Martinez | AT30: Si cruza con Antivirus
A31: FEDERACIÓN | B31: SUCURSAL IBAGUE | C31: FON1 | D31: FEDERACIÓN | E31: EMPLEADO | F31: 28548604 | G31: FELPLOP | H31: LINA PASTORA LOPERA MORENO | I31: TOLIMA | J31: IBAGUE | K31: ANALISTA | L31: PROGRAMA SICA | M31: 2 | N31: RECURSO PROPIO | O31: N/A | P31: N/A | Q31: N/A | R31: N/A | S31: N/A | U31: EQUIPO ESCRITORIO | V31: 1FYMSD2 | W31: 10078203 | X31: DELL | Y31: OPTIPLEX 3040 | Z31: W11FETOLLLOP | AA31: EN OPERACION | AB31: ASIGNACION RESPONSABLE | AC31: CONTROLADO | AD31: I5-6500 | AE31: 8GB | AF31: 250GB | AG31: WINDOWS 11 PRO | AH31: 42697 | AI31: 43793 | AJ31: =FLOOR(YEARFRAC(AH31, TODAY(), 1),1) -> 9 | AL31: JHONATHAN ARMANDO CAMARGO IZQUIERDO | AN31: N/A | AO31: N/A | AP31: N/A | AQ31: N/A | AR31: {=IFERROR(XLOOKUP(V31,'AV 23-12-2025'!A:A,'AV 23-12-2025'!D:D),"zz.No cruza con AV")} -> 19/12/25 15:54:57 COT | AS31: {=IFERROR(XLOOKUP(V31,'AV 23-12-2025'!A:A,'AV 23-12-2025'!C:C), "No cruza con AV")} -> Lina Lopera | AT31: Si cruza con Antivirus
A32: FEDERACIÓN | B32: SUCURSAL IBAGUE | C32: FON1 | D32: FEDERACIÓN | E32: EMPLEADO | F32: 1110541614 | H32: JHONATHAN ARMANDO CAMARGO IZQUIERDO | I32: TOLIMA | J32: IBAGUE | K32: ANALISTA TIC | L32: TIC | M32: 2 | N32: RECURSO PROPIO | O32: N/A | P32: N/A | Q32: N/A | R32: N/A | S32: N/A | U32: EQUIPO PORTATIL | V32: C2YF5C2 | W32: 10070724 | X32: DELL | Y32: LATITUD 3560 | Z32: No Aplica | AA32: ALMACENADO | AB32: RETORNO | AC32: CONTROLADO | AD32: i5-5200U | AE32: 8GB | AF32: No Aplica | AG32: No Aplica | AH32: 42696 | AI32: 43822 | AJ32: =FLOOR(YEARFRAC(AH32, TODAY(), 1),1) -> 9 | AL32: JHONATHAN ARMANDO CAMARGO IZQUIERDO | AN32: OBSOLETO | AO32: N/A | AP32: N/A | AQ32: N/A | AR32: {=IFERROR(XLOOKUP(V32,'AV 23-12-2025'!A:A,'AV 23-12-2025'!D:D),"zz.No cruza con AV")} -> 9/10/25 9:52:04 COT | AS32: {=IFERROR(XLOOKUP(V32,'AV 23-12-2025'!A:A,'AV 23-12-2025'!C:C), "No cruza con AV")} -> MariaP Patiño | AT32: Si cruza con Antivirus
A33: FEDERACIÓN | B33: SUCURSAL IBAGUE | C33: FON1 | D33: FEDERACIÓN | E33: EMPLEADO | F33: 1110541614 | H33: JHONATHAN ARMANDO CAMARGO IZQUIERDO | I33: TOLIMA | J33: IBAGUE | K33: ANALISTA TIC | L33: TIC | M33: 2 | N33: RECURSO PROPIO | O33: N/A | P33: N/A | Q33: N/A | R33: N/A | S33: N/A | U33: EQUIPO TODO EN UNO | V33: P9017H90 | X33: LENOVO | Y33: IDEA CENTRE AiO 700-24ISH | Z33: No Aplica | AA33: ALMACENADO | AB33: ALISTAMIENTO/SOPORTE | AC33: CONTROLADO | AD33: Core i7 6700 | AE33: 12GB | AF33: No Aplica | AG33: No Aplica | AH33: 42430 | AI33: 42491 | AJ33: =FLOOR(YEARFRAC(AH33, TODAY(), 1),1) -> 9 | AL33: JHONATHAN ARMANDO CAMARGO IZQUIERDO | AN33: FALLA EN PANTALLA - SIN SO | AO33: N/A | AP33: N/A | AQ33: N/A | AR33: {=IFERROR(XLOOKUP(V33,'AV 23-12-2025'!A:A,'AV 23-12-2025'!D:D),"zz.No cruza con AV")} -> zz.No cruza con AV | AS33: {=IFERROR(XLOOKUP(V33,'AV 23-12-2025'!A:A,'AV 23-12-2025'!C:C), "No cruza con AV")} -> No cruza con AV | AT33: No cruza con Antivirus
A34: FEDERACIÓN | B34: SUCURSAL IBAGUE | C34: FON1 | D34: FEDERACIÓN | E34: EMPLEADO | F34: 1005701133 | G34: GECHEVE133 | H34: GABRIELA ECHEVERRY ESCOBAR | I34: TOLIMA | J34: IBAGUE | K34: ANALISTA COMPRAS | L34: BIENES Y SERVICIOS | M34: 2 | N34: RECURSO PROPIO | O34: N/A | P34: N/A | Q34: N/A | R34: N/A | S34: N/A | U34: EQUIPO ESCRITORIO | V34: G2P7S22 | W34: 10065509 | X34: DELL | Y34: OPTIPLEX 9020 | Z34: D10FETOLGECH01 | AA34: EN OPERACION | AB34: ASIGNACION RESPONSABLE | AC34: CONTROLADO | AD34: I5-4590 | AE34: 12GB | AF34: 500GB | AG34: WINDOWS 10 PRO | AH34: 42012 | AI34: 43139 | AJ34: =FLOOR(YEARFRAC(AH34, TODAY(), 1),1) -> 11 | AL34: JHONATHAN ARMANDO CAMARGO IZQUIERDO | AN34: N/A | AO34: PERFIL 2 | AP34: LAPTOP | AQ34: RECURSOS PROPIOS | AR34: {=IFERROR(XLOOKUP(V34,'AV 23-12-2025'!A:A,'AV 23-12-2025'!D:D),"zz.No cruza con AV")} -> 22/12/25 16:22:44 COT | AS34: {=IFERROR(XLOOKUP(V34,'AV 23-12-2025'!A:A,'AV 23-12-2025'!C:C), "No cruza con AV")} -> Gabriela Echeverry | AT34: Si cruza con Antivirus
A35: FEDERACIÓN | B35: SUCURSAL IBAGUE | C35: FON1 | D35: FEDERACIÓN | E35: EMPLEADO | F35: 1109419709 | H35: KELLY MARCELA GARZON ESPINOSA | I35: TOLIMA | J35: IBAGUE | K35: AUXILIAR ADMINISTRATIVO | L35: ADMINISTRATIVOS | M35: 2 | N35: RECURSO PROPIO | O35: N/A | P35: N/A | Q35: N/A | R35: N/A | S35: N/A | U35: EQUIPO ESCRITORIO | V35: G2MXR22 | W35: 10065508 | X35: DELL | Y35: OPTIPLEX 9020 | Z35: D10FETOLKGAR01 | AA35: EN OPERACION | AB35: ASIGNACION RESPONSABLE | AC35: CONTROLADO | AD35: I5-4590 | AE35: 16GB | AF35: 250GB | AG35: WINDOWS 10 PRO | AH35: 42012 | AI35: 43139 | AJ35: =FLOOR(YEARFRAC(AH35, TODAY(), 1),1) -> 11 | AL35: JHONATHAN ARMANDO CAMARGO IZQUIERDO | AN35: N/A | AO35: PERFIL 1 | AP35: DESKTOP | AQ35: PAC | AR35: {=IFERROR(XLOOKUP(V35,'AV 23-12-2025'!A:A,'AV 23-12-2025'!D:D),"zz.No cruza con AV")} -> 23/12/25 12:14:14 COT | AS35: {=IFERROR(XLOOKUP(V35,'AV 23-12-2025'!A:A,'AV 23-12-2025'!C:C), "No cruza con AV")} -> KELLY GARZON | AT35: Si cruza con Antivirus
A36: FEDERACIÓN | B36: SUCURSAL IBAGUE | C36: FON1 | D36: FEDERACIÓN | E36: EMPLEADO | F36: 1110541614 | H36: JHONATHAN ARMANDO CAMARGO IZQUIERDO | I36: TOLIMA | J36: IBAGUE | K36: ANALISTA TIC | L36: TIC | M36: 2 | N36: RECURSO PROPIO | O36: N/A | P36: N/A | Q36: N/A | R36: N/A | S36: N/A | U36: EQUIPO PORTATIL | V36: 96TKL32 | W36: 10065498 | X36: DELL | Y36: LATITUDE E5440 | Z36: No Aplica | AA36: ALMACENADO | AB36: ALISTAMIENTO/SOPORTE | AC36: CONTROLADO | AD36: Core i5-3230M | AE36: N/A | AF36: No Aplica | AG36: No Aplica | AH36: 42074 | AI36: 43200 | AJ36: =FLOOR(YEARFRAC(AH36, TODAY(), 1),1) -> 10 | AL36: JHONATHAN ARMANDO CAMARGO IZQUIERDO | AN36: SIN HDD - SIN RAM - CORTO BOARD | AO36: N/A | AP36: N/A | AQ36: N/A | AR36: {=IFERROR(XLOOKUP(V36,'AV 23-12-2025'!A:A,'AV 23-12-2025'!D:D),"zz.No cruza con AV")} -> zz.No cruza con AV | AS36: {=IFERROR(XLOOKUP(V36,'AV 23-12-2025'!A:A,'AV 23-12-2025'!C:C), "No cruza con AV")} -> No cruza con AV | AT36: No cruza con Antivirus
A37: FEDERACIÓN | B37: SUCURSAL IBAGUE | C37: FON1 | D37: FEDERACIÓN | E37: EMPLEADO | F37: 1110541614 | H37: JHONATHAN ARMANDO CAMARGO IZQUIERDO | I37: TOLIMA | J37: IBAGUE | K37: ANALISTA TIC | L37: TIC | M37: 2 | N37: RECURSO PROPIO | O37: N/A | P37: N/A | Q37: N/A | R37: N/A | S37: N/A | U37: EQUIPO PORTATIL | V37: 92TKL32 | W37: 10065492 | X37: DELL | Y37: LATITUDE E5440 | Z37: No Aplica | AA37: ALMACENADO | AB37: ALISTAMIENTO/SOPORTE | AC37: CONTROLADO | AD37: Core i5-3230M | AE37: EXTRAIDA | AF37: No Aplica | AG37: No Aplica | AH37: 42074 | AI37: 43200 | AJ37: =FLOOR(YEARFRAC(AH37, TODAY(), 1),1) -> 10 | AL37: JHONATHAN ARMANDO CAMARGO IZQUIERDO | AN37: WIFI - USB - ETHERNET - PANTALLA | AO37: N/A | AP37: N/A | AQ37: N/A | AR37: {=IFERROR(XLOOKUP(V37,'AV 23-12-2025'!A:A,'AV 23-12-2025'!D:D),"zz.No cruza con AV")} -> zz.No cruza con AV | AS37: {=IFERROR(XLOOKUP(V37,'AV 23-12-2025'!A:A,'AV 23-12-2025'!C:C), "No cruza con AV")} -> No cruza con AV | AT37: No cruza con Antivirus
A38: FEDERACIÓN | B38: SUCURSAL IBAGUE | C38: FON1 | D38: FEDERACIÓN | E38: EMPLEADO | F38: 1110541614 | H38: JHONATHAN ARMANDO CAMARGO IZQUIERDO | I38: TOLIMA | J38: IBAGUE | K38: ANALISTA TIC | L38: TIC | M38: 2 | N38: RECURSO PROPIO | O38: N/A | P38: N/A | Q38: N/A | R38: N/A | S38: N/A | U38: EQUIPO PORTATIL | V38: 12TKL32 | W38: 10065493 | X38: DELL | Y38: LATITUDE E5440 | Z38: No Aplica | AA38: ALMACENADO | AB38: ALISTAMIENTO/SOPORTE | AC38: CONTROLADO | AD38: Core i5-4310U | AE38: 4GB | AF38: No Aplica | AG38: No Aplica | AH38: 42074 | AI38: 43200 | AJ38: =FLOOR(YEARFRAC(AH38, TODAY(), 1),1) -> 10 | AL38: JHONATHAN ARMANDO CAMARGO IZQUIERDO | AN38: BATERIA NO CARGA - SIN ADAPTADOR ENERGIA - NO ENCIENDE | AO38: N/A | AP38: N/A | AQ38: N/A | AR38: {=IFERROR(XLOOKUP(V38,'AV 23-12-2025'!A:A,'AV 23-12-2025'!D:D),"zz.No cruza con AV")} -> 9/10/25 15:29:43 COT | AS38: {=IFERROR(XLOOKUP(V38,'AV 23-12-2025'!A:A,'AV 23-12-2025'!C:C), "No cruza con AV")} -> Administrador | AT38: Si cruza con Antivirus
A39: FEDERACIÓN | B39: SUCURSAL IBAGUE | C39: FON1 | D39: FEDERACIÓN | E39: EMPLEADO | F39: 1110515041 | G39: JSANDOV041 | H39: JUAN CAMILO SANDOVAL GUZMAN | I39: TOLIMA | J39: IBAGUE | K39: ANALISTA BIENES Y SERVICIOS | L39: BIENES Y SERVICIOS | M39: 2 | N39: RECURSO PROPIO | O39: N/A | P39: N/A | Q39: N/A | R39: N/A | S39: N/A | U39: EQUIPO ESCRITORIO | V39: 21599474330 | W39: 10069362 | X39: DELL | Y39: OPTIPLEX 3020 | Z39: W10FETOLJSAND | AA39: EN OPERACION | AB39: ASIGNACION RESPONSABLE | AC39: CONTROLADO | AD39: I5-4590 | AE39: 12GB | AF39: 250GB | AG39: WINDOWS 10 PRO | AH39: 41947 | AI39: 43074 | AJ39: =FLOOR(YEARFRAC(AH39, TODAY(), 1),1) -> 11 | AL39: JHONATHAN ARMANDO CAMARGO IZQUIERDO | AN39: N/A | AO39: PERFIL 2 | AP39: LAPTOP | AQ39: RECURSOS PROPIOS | AR39: {=IFERROR(XLOOKUP(V39,'AV 23-12-2025'!A:A,'AV 23-12-2025'!D:D),"zz.No cruza con AV")} -> zz.No cruza con AV | AS39: {=IFERROR(XLOOKUP(V39,'AV 23-12-2025'!A:A,'AV 23-12-2025'!C:C), "No cruza con AV")} -> No cruza con AV | AT39: No cruza con Antivirus
A40: FEDERACIÓN | B40: SUCURSAL IBAGUE | C40: FON1 | D40: FEDERACIÓN | E40: EMPLEADO | F40: 65758694 | G40: FEMREY | H40: MARIA DEL CARMEN REYES BONILLA | I40: TOLIMA | J40: IBAGUE | K40: ANALISTA PLANEACION FINANCIERA Y PRESUPU | L40: PLANEACION FINANCIERA Y PRESUPUESTO | M40: 2 | N40: RECURSO PROPIO | O40: N/A | P40: N/A | Q40: N/A | R40: N/A | S40: N/A | U40: EQUIPO ESCRITORIO | V40: C6RVK02 | W40: 10069152 | X40: DELL | Y40: OPTIPLEX 7010 | Z40: W10FETOLMDCREY | AA40: EN OPERACION | AB40: ASIGNACION RESPONSABLE | AC40: CONTROLADO | AD40: i5-3570 | AE40: 4GB | AF40: 500GB | AG40: WINDOWS 10 PRO | AH40: 41743 | AI40: 42870 | AJ40: =FLOOR(YEARFRAC(AH40, TODAY(), 1),1) -> 11 | AL40: JHONATHAN ARMANDO CAMARGO IZQUIERDO | AN40: N/A | AO40: PERFIL 3 | AP40: DESKTOP TOWER/SFF DE ALTO RENDIMIENTO | AQ40: RECURSOS BOGOTA | AR40: {=IFERROR(XLOOKUP(V40,'AV 23-12-2025'!A:A,'AV 23-12-2025'!D:D),"zz.No cruza con AV")} -> 23/12/25 12:42:26 COT | AS40: {=IFERROR(XLOOKUP(V40,'AV 23-12-2025'!A:A,'AV 23-12-2025'!C:C), "No cruza con AV")} -> Maria Reyes | AT40: Si cruza con Antivirus
A41: FEDERACIÓN | B41: SUCURSAL IBAGUE | C41: FON1 | D41: FEDERACIÓN | E41: EMPLEADO | F41: 1006128400 | H41: MARIA FERNANDA MANRIQUE BLANDON | I41: TOLIMA | J41: IBAGUE | K41: AUXILIAR GESTION HUMANA | L41: TALENTO HUMANO | M41: 2 | N41: RECURSO PROPIO | O41: N/A | P41: N/A | Q41: N/A | R41: N/A | S41: N/A | U41: EQUIPO ESCRITORIO | V41: 6CRYK02 | W41: 10069209 | X41: DELL | Y41: OPTIPLEX 7010 | Z41: L10FETOLMMAN01 | AA41: EN OPERACION | AB41: ASIGNACION RESPONSABLE | AC41: CONTROLADO | AD41: I5-3570 | AE41: 12GB | AF41: 500GB | AG41: WINDOWS 10 PRO | AH41: 41740 | AI41: 42837 | AJ41: =FLOOR(YEARFRAC(AH41, TODAY(), 1),1) -> 11 | AL41: JHONATHAN ARMANDO CAMARGO IZQUIERDO | AN41: N/A | AO41: PERFIL 2 | AP41: LAPTOP | AQ41: RECURSOS PROPIOS | AR41: {=IFERROR(XLOOKUP(V41,'AV 23-12-2025'!A:A,'AV 23-12-2025'!D:D),"zz.No cruza con AV")} -> zz.No cruza con AV | AS41: {=IFERROR(XLOOKUP(V41,'AV 23-12-2025'!A:A,'AV 23-12-2025'!C:C), "No cruza con AV")} -> No cruza con AV | AT41: No cruza con Antivirus
A42: FEDERACIÓN | B42: SUCURSAL IBAGUE | C42: FON1 | D42: FEDERACIÓN | E42: EMPLEADO | F42: 1110462834 | G42: MGONZAL834 | H42: MAYRA ALEJANDRA GONZALEZ APONTE | I42: TOLIMA | J42: IBAGUE | K42: ANALISTA FINANCIERO | L42: FINANCIEROS | M42: 2 | N42: RECURSO PROPIO | O42: N/A | P42: N/A | Q42: N/A | R42: N/A | S42: N/A | U42: EQUIPO ESCRITORIO | V42: C6RTK02 | W42: 10069210 | X42: DELL | Y42: OPTIPLEX 7010 | Z42: W10FETOLMAGONZ | AA42: EN OPERACION | AB42: ASIGNACION RESPONSABLE | AC42: CONTROLADO | AD42: I5-3570 | AE42: 12GB | AF42: 250GB | AG42: WINDOWS 10 PRO | AH42: 41743 | AI42: 42870 | AJ42: =FLOOR(YEARFRAC(AH42, TODAY(), 1),1) -> 11 | AL42: JHONATHAN ARMANDO CAMARGO IZQUIERDO | AN42: N/A | AO42: PERFIL 1 | AP42: DESKTOP | AQ42: PAC | AR42: {=IFERROR(XLOOKUP(V42,'AV 23-12-2025'!A:A,'AV 23-12-2025'!D:D),"zz.No cruza con AV")} -> 23/12/25 12:43:46 COT | AS42: {=IFERROR(XLOOKUP(V42,'AV 23-12-2025'!A:A,'AV 23-12-2025'!C:C), "No cruza con AV")} -> Alejandra Gonzalez | AT42: Si cruza con Antivirus
A43: FEDERACIÓN | B43: SUCURSAL IBAGUE | C43: FON1 | D43: FEDERACIÓN | E43: EMPLEADO | F43: 52079779 | H43: NAYIBE MONTAÑA RIVERA | I43: TOLIMA | J43: IBAGUE | K43: ANALISTA GESTION HUMANA | L43: TALENTO HUMANO | M43: 2 | N43: RECURSO PROPIO | O43: N/A | P43: N/A | Q43: N/A | R43: N/A | S43: N/A | U43: EQUIPO ESCRITORIO | V43: 1DL0Z12 | W43: 10065632 | X43: DELL | Y43: OPTIPLEX 7010 | Z43: W10FETOLGHTOL | AA43: EN OPERACION | AB43: ASIGNACION RESPONSABLE | AC43: CONTROLADO | AD43: I5-3570 | AE43: 24GB | AF43: 500GB | AG43: WINDOWS 10 PRO | AH43: 41869 | AI43: 42996 | AJ43: =FLOOR(YEARFRAC(AH43, TODAY(), 1),1) -> 11 | AL43: JHONATHAN ARMANDO CAMARGO IZQUIERDO | AN43: N/A | AO43: PERFIL 2 | AP43: LAPTOP | AQ43: RECURSOS PROPIOS | AR43: {=IFERROR(XLOOKUP(V43,'AV 23-12-2025'!A:A,'AV 23-12-2025'!D:D),"zz.No cruza con AV")} -> 23/12/25 12:41:43 COT | AS43: {=IFERROR(XLOOKUP(V43,'AV 23-12-2025'!A:A,'AV 23-12-2025'!C:C), "No cruza con AV")} -> GH Tolima | AT43: Si cruza con Antivirus
A44: FEDERACIÓN | B44: SUCURSAL IBAGUE | C44: FON1 | D44: FEDERACIÓN | E44: EMPLEADO | F44: NO APLICA | H44: NO APLICA | I44: TOLIMA | J44: IBAGUE | K44: NO APLICA | L44: FINANCIEROS | M44: 2 | N44: RECURSO PROPIO | O44: N/A | P44: N/A | Q44: N/A | R44: N/A | S44: N/A | U44: EQUIPO PORTATIL | V44: JYXSVY1 | W44: 10066953 | X44: DELL | Y44: Latitude e5430 | Z44: L10FETOLMAFE | AA44: EN OPERACION | AB44: ASIGNACION RESPONSABLE | AC44: CONTROLADO | AD44: I5-3340m | AE44: 4GB | AF44: 500GB | AG44: WINDOWS 10 PRO | AH44: 41609 | AI44: 42706 | AJ44: =FLOOR(YEARFRAC(AH44, TODAY(), 1),1) -> 12 | AL44: JHONATHAN ARMANDO CAMARGO IZQUIERDO | AN44: N/A | AO44: N/A | AP44: N/A | AQ44: N/A | AR44: {=IFERROR(XLOOKUP(V44,'AV 23-12-2025'!A:A,'AV 23-12-2025'!D:D),"zz.No cruza con AV")} -> 20/10/25 7:46:19 COT | AS44: {=IFERROR(XLOOKUP(V44,'AV 23-12-2025'!A:A,'AV 23-12-2025'!C:C), "No cruza con AV")} -> Maria Fernanda | AT44: Si cruza con Antivirus
A45: FEDERACIÓN | B45: SUCURSAL IBAGUE | C45: FON1 | D45: FEDERACIÓN | E45: EMPLEADO | F45: 1110541614 | H45: JHONATHAN ARMANDO CAMARGO IZQUIERDO | I45: TOLIMA | J45: IBAGUE | K45: ANALISTA TIC | L45: TIC | M45: 2 | N45: RECURSO PROPIO | O45: N/A | P45: N/A | Q45: N/A | R45: N/A | S45: N/A | U45: EQUIPO PORTATIL | V45: J6PSG12 | W45: 10069135 | X45: DELL | Y45: LATITUDE E5440 | Z45: No Aplica | AA45: ALMACENADO | AB45: ALISTAMIENTO/SOPORTE | AC45: CONTROLADO | AD45: Core i5-3230M | AE45: N/A | AF45: No Aplica | AG45: No Aplica | AH45: 41833 | AI45: 42960 | AJ45: =FLOOR(YEARFRAC(AH45, TODAY(), 1),1) -> 11 | AL45: JHONATHAN ARMANDO CAMARGO IZQUIERDO | AN45: CORTO BOARD | AO45: N/A | AP45: N/A | AQ45: N/A | AR45: {=IFERROR(XLOOKUP(V45,'AV 23-12-2025'!A:A,'AV 23-12-2025'!D:D),"zz.No cruza con AV")} -> zz.No cruza con AV | AS45: {=IFERROR(XLOOKUP(V45,'AV 23-12-2025'!A:A,'AV 23-12-2025'!C:C), "No cruza con AV")} -> No cruza con AV | AT45: No cruza con Antivirus
A46: FEDERACIÓN | B46: SUCURSAL IBAGUE | C46: FON1 | D46: FEDERACIÓN | E46: EMPLEADO | F46: 1110541614 | H46: JHONATHAN ARMANDO CAMARGO IZQUIERDO | I46: TOLIMA | J46: IBAGUE | K46: ANALISTA TIC | L46: TIC | M46: 2 | N46: RECURSO PROPIO | O46: N/A | P46: N/A | Q46: N/A | R46: N/A | S46: N/A | U46: EQUIPO PORTATIL | V46: 2T5TG12 | W46: 10069148 | X46: DELL | Y46: LATITUDE E5440 | Z46: No Aplica | AA46: ALMACENADO | AB46: RETORNO | AC46: CONTROLADO | AD46: Core i5-4300U | AE46: 4GB | AF46: No Aplica | AG46: No Aplica | AH46: 41833 | AI46: 42960 | AJ46: =FLOOR(YEARFRAC(AH46, TODAY(), 1),1) -> 11 | AL46: JHONATHAN ARMANDO CAMARGO IZQUIERDO | AN46: SIN DISCO - SIN CARGADOR ASIGNADO ZIMA | AO46: N/A | AP46: N/A | AQ46: N/A | AR46: {=IFERROR(XLOOKUP(V46,'AV 23-12-2025'!A:A,'AV 23-12-2025'!D:D),"zz.No cruza con AV")} -> 9/10/25 11:30:36 COT | AS46: {=IFERROR(XLOOKUP(V46,'AV 23-12-2025'!A:A,'AV 23-12-2025'!C:C), "No cruza con AV")} -> Sergio Ruiz | AT46: Si cruza con Antivirus
A47: FEDERACIÓN | B47: SUCURSAL IBAGUE | C47: FON1 | D47: FEDERACIÓN | E47: EMPLEADO | F47: 1105335425 | G47: AMARIN425 | H47: ADRIANA VALENTINA MARIN GRISALES | I47: TOLIMA | J47: IBAGUE | K47: ANALISTA FINANCIERO | L47: FINANCIEROS | M47: 2 | N47: RECURSO PROPIO | O47: N/A | P47: N/A | Q47: N/A | R47: N/A | S47: N/A | U47: EQUIPO ESCRITORIO | V47: 9JN5DX1 | W47: 10062150 | X47: DELL | Y47: OPTIPLEX 7010 | Z47: W10FETOLAMARIN | AA47: EN OPERACIÓN | AB47: ASIGNACIÓN RESPONSABLE | AC47: CONTROLADO | AD47: INTEL(R) CORE(TM) I5-3470 CPU @ 3.20GHZ | AE47: 4GB | AF47: 250GB | AG47: WINDOWS 10 PRO | AH47: 41393 | AI47: 42490 | AJ47: =FLOOR(YEARFRAC(AH47, TODAY(), 1),1) -> 12 | AL47: JHONATHAN ARMANDO CAMARGO IZQUIERDO | AN47: N/A | AO47: PERFIL 1 | AP47: DESKTOP | AQ47: PAC | AR47: {=IFERROR(XLOOKUP(V47,'AV 23-12-2025'!A:A,'AV 23-12-2025'!D:D),"zz.No cruza con AV")} -> 23/12/25 12:44:04 COT | AS47: {=IFERROR(XLOOKUP(V47,'AV 23-12-2025'!A:A,'AV 23-12-2025'!C:C), "No cruza con AV")} -> Adriana Marin | AT47: Si cruza con Antivirus
A48: FEDERACIÓN | B48: SUCURSAL IBAGUE | C48: FON1 | D48: FEDERACIÓN | E48: EMPLEADO | F48: 14229778 | G48: 14229778 | H48: AURELIO GOMEZ BELTRAN | I48: TOLIMA | J48: IBAGUE | K48: EXTENSIONISTA | L48: SECCIONAL PLANADAS | M48: 2 | N48: RECURSO PROPIO | O48: N/A | P48: N/A | Q48: N/A | R48: N/A | S48: N/A | U48: EQUIPO ESCRITORIO | V48: 9JL6DX1 | W48: 10062156 | X48: DELL | Y48: OPTIPLEX 7010 | Z48: L10FETOLAGOM01 | AA48: EN OPERACION | AB48: ASIGNACION RESPONSABLE | AC48: CONTROLADO | AD48: I5-3470 | AE48: 8GB | AF48: 250GB | AG48: WINDOWS 10 PRO | AH48: 41393 | AI48: 42490 | AJ48: =FLOOR(YEARFRAC(AH48, TODAY(), 1),1) -> 12 | AL48: JHONATHAN ARMANDO CAMARGO IZQUIERDO | AN48: N/A | AO48: PERFIL 1 | AP48: DESKTOP | AQ48: RECURSOS BOGOTA | AR48: {=IFERROR(XLOOKUP(V48,'AV 23-12-2025'!A:A,'AV 23-12-2025'!D:D),"zz.No cruza con AV")} -> 23/12/25 11:35:19 COT | AS48: {=IFERROR(XLOOKUP(V48,'AV 23-12-2025'!A:A,'AV 23-12-2025'!C:C), "No cruza con AV")} -> Aurelio Gomez | AT48: Si cruza con Antivirus
A49: FEDERACIÓN | B49: SUCURSAL IBAGUE | C49: FON1 | D49: FEDERACIÓN | E49: EMPLEADO | F49: NO APLICA | H49: AUXILIAR DE OFICINA JURIDICA | I49: TOLIMA | J49: IBAGUE | K49: AUXILIAR ADMINISTRATIVO | L49: BENEFICIO ECOLOGICO | M49: 2 | N49: RECURSO PROPIO | O49: N/A | P49: N/A | Q49: N/A | R49: N/A | S49: N/A | U49: EQUIPO ESCRITORIO | V49: 9JM5DX1 | W49: 10062153 | X49: DELL | Y49: OPTIPLEX 7010 | Z49: W10FETOLAUXJUR | AA49: EN OPERACION | AB49: ASIGNACION RESPONSABLE | AC49: CONTROLADO | AD49: I5-3470 | AE49: 8GB | AF49: 500GB | AG49: WINDOWS 10 PRO | AH49: 41393 | AI49: 42490 | AJ49: =FLOOR(YEARFRAC(AH49, TODAY(), 1),1) -> 12 | AL49: JHONATHAN ARMANDO CAMARGO IZQUIERDO | AN49: N/A | AO49: N/A | AP49: N/A | AQ49: N/A | AR49: {=IFERROR(XLOOKUP(V49,'AV 23-12-2025'!A:A,'AV 23-12-2025'!D:D),"zz.No cruza con AV")} -> 22/12/25 14:48:52 COT | AS49: {=IFERROR(XLOOKUP(V49,'AV 23-12-2025'!A:A,'AV 23-12-2025'!C:C), "No cruza con AV")} -> Auxiliar Juridica | AT49: Si cruza con Antivirus
A50: FEDERACIÓN | B50: SUCURSAL IBAGUE | C50: FON1 | D50: FEDERACIÓN | E50: EMPLEADO | F50: 1110489898 | H50: CRISTY MARIAM RAMIREZ PERALTA | I50: TOLIMA | J50: IBAGUE | K50: AUXILIAR ADMINISTRATIVO | L50: ADMINISTRATIVOS | M50: 2 | N50: RECURSO PROPIO | O50: N/A | P50: N/A | Q50: N/A | R50: N/A | S50: N/A | U50: EQUIPO ESCRITORIO | V50: 9JM7DX1 | W50: 10062155 | X50: DELL | Y50: OPTIPLEX 7010 | Z50: W10FETOLCMRAMI | AA50: EN OPERACION | AB50: ASIGNACION RESPONSABLE | AC50: CONTROLADO | AD50: I5-3470 | AE50: 16GB | AF50: 500GB | AG50: WINDOWS 10 PRO | AH50: 41393 | AI50: 42490 | AJ50: =FLOOR(YEARFRAC(AH50, TODAY(), 1),1) -> 12 | AL50: JHONATHAN ARMANDO CAMARGO IZQUIERDO | AN50: N/A | AO50: PERFIL 2 | AP50: LAPTOP | AQ50: PAC | AR50: {=IFERROR(XLOOKUP(V50,'AV 23-12-2025'!A:A,'AV 23-12-2025'!D:D),"zz.No cruza con AV")} -> 23/12/25 12:48:17 COT | AS50: {=IFERROR(XLOOKUP(V50,'AV 23-12-2025'!A:A,'AV 23-12-2025'!C:C), "No cruza con AV")} -> Cristy Ramirez | AT50: Si cruza con Antivirus
A51: FEDERACIÓN | B51: SUCURSAL IBAGUE | C51: FON1 | D51: FEDERACIÓN | E51: EMPLEADO | F51: 93451618 | G51: EGUAYAR618 | H51: EDWIN ODAIR GUAYARA GUZMAN | I51: TOLIMA | J51: IBAGUE | K51: EXTENSIONISTA | L51: SECCIONAL CHAPARRAL | M51: 2 | N51: RECURSO PROPIO | O51: N/A | P51: N/A | Q51: N/A | R51: N/A | S51: N/A | U51: EQUIPO ESCRITORIO | V51: 43YYDX1 | W51: 10062147 | X51: DELL | Y51: OPTIPLEX 7010 | Z51: W10FETOLEGUAYA | AA51: EN OPERACION | AB51: ASIGNACION RESPONSABLE | AC51: CONTROLADO | AD51: I5-3470 | AE51: 4GB | AF51: 500GB | AG51: WINDOWS 10 PRO | AH51: 41403 | AI51: 42500 | AJ51: =FLOOR(YEARFRAC(AH51, TODAY(), 1),1) -> 12 | AL51: JHONATHAN ARMANDO CAMARGO IZQUIERDO | AN51: N/A | AO51: PERFIL 1 | AP51: DESKTOP | AQ51: RECURSOS BOGOTA | AR51: {=IFERROR(XLOOKUP(V51,'AV 23-12-2025'!A:A,'AV 23-12-2025'!D:D),"zz.No cruza con AV")} -> zz.No cruza con AV | AS51: {=IFERROR(XLOOKUP(V51,'AV 23-12-2025'!A:A,'AV 23-12-2025'!C:C), "No cruza con AV")} -> No cruza con AV | AT51: No cruza con Antivirus
A52: FEDERACIÓN | B52: SUCURSAL IBAGUE | C52: FON1 | D52: FEDERACIÓN | E52: EMPLEADO | F52: 5824733 | G52: GGARAVI733 | H52: GABRIEL ESTEBAN GARAVITO CARREÑO | I52: TOLIMA | J52: IBAGUE | K52: ANALISTA GESTION HUMANA | L52: TALENTO HUMANO | M52: 2 | N52: RECURSO PROPIO | O52: N/A | P52: N/A | Q52: N/A | R52: N/A | S52: N/A | U52: EQUIPO ESCRITORIO | V52: FOXZMS1 | W52: 10058656 | X52: DELL | Y52: OPTIPLEX 790 | Z52: W10FETOLSSTTOL | AA52: EN OPERACION | AB52: ASIGNACION RESPONSABLE | AC52: CONTROLADO | AD52: I5-2400 | AE52: 16GB | AF52: 500GB | AG52: WINDOWS 10 PRO | AH52: 41248 | AI52: NO REGISTRA | AJ52: =FLOOR(YEARFRAC(AH52, TODAY(), 1),1) -> 13 | AL52: JHONATHAN ARMANDO CAMARGO IZQUIERDO | AN52: N/A | AO52: PERFIL 2 | AP52: LAPTOP | AQ52: RECURSOS PROPIOS | AR52: {=IFERROR(XLOOKUP(V52,'AV 23-12-2025'!A:A,'AV 23-12-2025'!D:D),"zz.No cruza con AV")} -> zz.No cruza con AV | AS52: {=IFERROR(XLOOKUP(V52,'AV 23-12-2025'!A:A,'AV 23-12-2025'!C:C), "No cruza con AV")} -> No cruza con AV | AT52: No cruza con Antivirus
A53: FEDERACIÓN | B53: SUCURSAL IBAGUE | C53: FON1 | D53: FEDERACIÓN | E53: EMPLEADO | F53: 1110585547 | H53: GERMAN CAMILO ROMERO MOSQUERA | I53: TOLIMA | J53: IBAGUE | K53: COORDINADOR GRUPO BENEFICIO ECOLOGICO | L53: EXTENSION RURAL | M53: 2 | N53: RECURSO PROPIO | O53: N/A | P53: N/A | Q53: N/A | R53: N/A | S53: N/A | U53: EQUIPO ESCRITORIO | V53: 9JM6DX1 | W53: 10062154 | X53: DELL | Y53: OPTIPLEX 7010 | Z53: D10FETOLGROM01 | AA53: EN OPERACION | AB53: ASIGNACION RESPONSABLE | AC53: CONTROLADO | AD53: I5-3470 | AE53: 12GB | AF53: 500GB | AG53: WINDOWS 10 PRO | AH53: 41393 | AI53: 46142 | AJ53: =FLOOR(YEARFRAC(AH53, TODAY(), 1),1) -> 12 | AL53: JHONATHAN ARMANDO CAMARGO IZQUIERDO | AN53: N/A | AO53: PERFIL 1 | AP53: DESKTOP | AQ53: RECURSOS BOGOTA | AR53: {=IFERROR(XLOOKUP(V53,'AV 23-12-2025'!A:A,'AV 23-12-2025'!D:D),"zz.No cruza con AV")} -> 23/12/25 12:20:09 COT | AS53: {=IFERROR(XLOOKUP(V53,'AV 23-12-2025'!A:A,'AV 23-12-2025'!C:C), "No cruza con AV")} -> German Romero | AT53: Si cruza con Antivirus
A54: FEDERACIÓN | B54: SUCURSAL IBAGUE | C54: FON1 | D54: FEDERACIÓN | E54: EMPLEADO | F54: 1105335340 | G54: IGUTIER340 | H54: IVETH DANIELA GUTIERREZ SUAREZ | I54: TOLIMA | J54: IBAGUE | K54: ANALISTA PROYECTOS | L54: PROYECTOS | M54: 2 | N54: RECURSO PROPIO | O54: N/A | P54: N/A | Q54: N/A | R54: N/A | S54: N/A | U54: EQUIPO ESCRITORIO | V54: 9JL7DX1 | W54: 10062157 | X54: DELL | Y54: OPTIPLEX 7010 | Z54: W10FETOLIDGUT | AA54: EN OPERACION | AB54: ASIGNACION RESPONSABLE | AC54: CONTROLADO | AD54: I5-3470 | AE54: 12GB | AF54: 250GB | AG54: WINDOWS 10 PRO | AH54: 41393 | AI54: 42490 | AJ54: =FLOOR(YEARFRAC(AH54, TODAY(), 1),1) -> 12 | AL54: JHONATHAN ARMANDO CAMARGO IZQUIERDO | AN54: N/A | AO54: PERFIL 1 | AP54: DESKTOP | AQ54: PAC | AR54: {=IFERROR(XLOOKUP(V54,'AV 23-12-2025'!A:A,'AV 23-12-2025'!D:D),"zz.No cruza con AV")} -> 23/12/25 12:21:48 COT | AS54: {=IFERROR(XLOOKUP(V54,'AV 23-12-2025'!A:A,'AV 23-12-2025'!C:C), "No cruza con AV")} -> Daniela Gutierrez | AT54: Si cruza con Antivirus
A55: FEDERACIÓN | B55: SUCURSAL IBAGUE | C55: FON1 | D55: FEDERACIÓN | E55: EMPLEADO | F55: 1020776044 | H55: LAURA DANIELA VASQUEZ GALLEGO | I55: TOLIMA | J55: IBAGUE | K55: COORDINADOR PROGRAMA | L55: PROGRAMA GESTION EMPRESARIAL | M55: 2 | N55: RECURSO PROPIO | O55: N/A | P55: N/A | Q55: N/A | R55: N/A | S55: N/A | U55: EQUIPO ESCRITORIO | V55: FZKV6Y1 | W55: 10066876 | X55: DELL | Y55: OPTIPLEX 7010 | Z55: W11FETOLLVASQ | AA55: EN OPERACION | AB55: ASIGNACION RESPONSABLE | AC55: CONTROLADO | AD55: I5-3570 | AE55: 14GB | AF55: 250GB | AG55: WINDOWS 10 PRO | AH55: 41470 | AI55: 42567 | AJ55: =FLOOR(YEARFRAC(AH55, TODAY(), 1),1) -> 12 | AL55: JHONATHAN ARMANDO CAMARGO IZQUIERDO | AN55: N/A | AO55: PERFIL 2 | AP55: LAPTOP | AQ55: PAC | AR55: {=IFERROR(XLOOKUP(V55,'AV 23-12-2025'!A:A,'AV 23-12-2025'!D:D),"zz.No cruza con AV")} -> 22/12/25 16:51:56 COT | AS55: {=IFERROR(XLOOKUP(V55,'AV 23-12-2025'!A:A,'AV 23-12-2025'!C:C), "No cruza con AV")} -> Laura Vasquez | AT55: Si cruza con Antivirus
A56: FEDERACIÓN | B56: SUCURSAL IBAGUE | C56: FON1 | D56: FEDERACIÓN | E56: EMPLEADO | F56: 65752678 | G56: FELCOM | H56: LEYDA LILIANA COMBITA ZAMBRANO | I56: TOLIMA | J56: IBAGUE | K56: AUXILIAR ADMINISTRATIVO | L56: PROGRAMA MEDIO AMBIENTE | M56: 2 | N56: RECURSO PROPIO | O56: N/A | P56: N/A | Q56: N/A | R56: N/A | S56: N/A | U56: EQUIPO ESCRITORIO | V56: 43WZDX1 | W56: 10062149 | X56: DELL | Y56: OPTIPLEX 7010 | Z56: W10FETOLLCOMB | AA56: EN OPERACION | AB56: ASIGNACION RESPONSABLE | AC56: CONTROLADO | AD56: I5-3470 | AE56: 12GB | AF56: 250GB | AG56: WINDOWS 10 PRO | AH56: 41403 | AI56: 42500 | AJ56: =FLOOR(YEARFRAC(AH56, TODAY(), 1),1) -> 12 | AL56: JHONATHAN ARMANDO CAMARGO IZQUIERDO | AN56: N/A | AO56: PERFIL 1 | AP56: DESKTOP | AQ56: PAC | AR56: {=IFERROR(XLOOKUP(V56,'AV 23-12-2025'!A:A,'AV 23-12-2025'!D:D),"zz.No cruza con AV")} -> 19/12/25 17:53:31 COT | AS56: {=IFERROR(XLOOKUP(V56,'AV 23-12-2025'!A:A,'AV 23-12-2025'!C:C), "No cruza con AV")} -> Liliana Combita | AT56: Si cruza con Antivirus
A57: FEDERACIÓN | B57: SUCURSAL IBAGUE | C57: FON1 | D57: FEDERACIÓN | E57: EMPLEADO | F57: 93359471 | G57: FTLSAE | H57: LUISA FERNANDA CASTAÑEDA LONDOÑO | I57: TOLIMA | J57: IBAGUE | K57: AUXILIAR ADMINISTRATIVO | L57: PROGRAMA COMUNICACIONES | M57: 2 | N57: RECURSO PROPIO | O57: N/A | P57: N/A | Q57: N/A | R57: N/A | S57: N/A | U57: EQUIPO ESCRITORIO | V57: 1YNLHX1 | W57: 10066848 | X57: DELL | Y57: OPTIPLEX 7010 | Z57: W10FETOLKSAENZ | AA57: EN OPERACION | AB57: ASIGNACION RESPONSABLE | AC57: CONTROLADO | AD57: I5-3470 | AE57: 4GB | AF57: 500GB | AG57: WINDOWS 10 PRO | AH57: 41451 | AI57: 42548 | AJ57: =FLOOR(YEARFRAC(AH57, TODAY(), 1),1) -> 12 | AL57: JHONATHAN ARMANDO CAMARGO IZQUIERDO | AN57: N/A | AO57: PERFIL 1 | AP57: DESKTOP | AQ57: RECURSOS BOGOTA | AR57: {=IFERROR(XLOOKUP(V57,'AV 23-12-2025'!A:A,'AV 23-12-2025'!D:D),"zz.No cruza con AV")} -> 19/12/25 13:34:59 COT | AS57: {=IFERROR(XLOOKUP(V57,'AV 23-12-2025'!A:A,'AV 23-12-2025'!C:C), "No cruza con AV")} -> Luis Saenz | AT57: Si cruza con Antivirus
A58: FEDERACIÓN | B58: SUCURSAL IBAGUE | C58: FON1 | D58: FEDERACIÓN | E58: EMPLEADO | F58: 1110489085 | H58: ANGI LORENA CAPERA SOTO | I58: TOLIMA | J58: IBAGUE | K58: AUXILIAR ADMINISTRATIVO | L58: ADMINISTRATIVOS | M58: 2 | N58: RECURSO PROPIO | O58: N/A | P58: N/A | Q58: N/A | R58: N/A | S58: N/A | U58: EQUIPO ESCRITORIO | V58: 20773835317 | W58: 10062151 | X58: DELL | Y58: OPTIPLEX 7010 | Z58: W11FETOLLFCASTA | AA58: EN OPERACION | AB58: ASIGNACION RESPONSABLE | AC58: CONTROLADO | AD58: I5-3470 | AE58: 8GB | AF58: 250GB | AG58: WINDOWS 10 PRO | AH58: 41393 | AI58: 42490 | AJ58: =FLOOR(YEARFRAC(AH58, TODAY(), 1),1) -> 12 | AL58: JHONATHAN ARMANDO CAMARGO IZQUIERDO | AN58: N/A | AO58: PERFIL 2 | AP58: LAPTOP | AQ58: RECURSOS BOGOTA | AR58: {=IFERROR(XLOOKUP(V58,'AV 23-12-2025'!A:A,'AV 23-12-2025'!D:D),"zz.No cruza con AV")} -> zz.No cruza con AV | AS58: {=IFERROR(XLOOKUP(V58,'AV 23-12-2025'!A:A,'AV 23-12-2025'!C:C), "No cruza con AV")} -> No cruza con AV | AT58: No cruza con Antivirus
A59: FEDERACIÓN | B59: SUCURSAL IBAGUE | C59: FON1 | D59: FEDERACIÓN | E59: EMPLEADO | F59: 1110590598 | G59: MCABRER598 | H59: MARIA ALEJANDRA CABRERA RIOS | I59: TOLIMA | J59: IBAGUE | K59: AUXILIAR ADMINISTRATIVO | L59: ADMINISTRATIVOS | M59: 2 | N59: RECURSO PROPIO | O59: N/A | P59: N/A | Q59: N/A | R59: N/A | S59: N/A | U59: EQUIPO ESCRITORIO | V59: 9JK6DX1 | W59: 10062152 | X59: DELL | Y59: OPTIPLEX 7010 | Z59: W10FTOYPOLAVE | AA59: EN OPERACION | AB59: ASIGNACION RESPONSABLE | AC59: CONTROLADO | AD59: I5-3470 | AE59: 12GB | AF59: 250GB | AG59: WINDOWS 10 PRO | AH59: 41393 | AI59: 42463 | AJ59: =FLOOR(YEARFRAC(AH59, TODAY(), 1),1) -> 12 | AL59: JHONATHAN ARMANDO CAMARGO IZQUIERDO | AN59: N/A | AO59: PERFIL 2 | AP59: LAPTOP | AQ59: PAC | AR59: {=IFERROR(XLOOKUP(V59,'AV 23-12-2025'!A:A,'AV 23-12-2025'!D:D),"zz.No cruza con AV")} -> 19/12/25 18:07:26 COT | AS59: {=IFERROR(XLOOKUP(V59,'AV 23-12-2025'!A:A,'AV 23-12-2025'!C:C), "No cruza con AV")} -> Paola Olave | AT59: Si cruza con Antivirus
A60: FEDERACIÓN | B60: SUCURSAL IBAGUE | C60: FON1 | D60: FEDERACIÓN | E60: EMPLEADO | F60: 28968290 | H60: MARICELA GARCIA CARDOZO | I60: TOLIMA | J60: IBAGUE | K60: AUXILIAR BIENES Y SERVICIOS | L60: BIENES Y SERVICIOS | M60: 2 | N60: RECURSO PROPIO | O60: N/A | P60: N/A | Q60: N/A | R60: N/A | S60: N/A | U60: EQUIPO ESCRITORIO | V60: 2STCCY1 | W60: 10066949 | X60: DELL | Y60: OPTIPLEX 3010 | Z60: D10FETOLMGAR01 | AA60: EN OPERACION | AB60: ASIGNACION RESPONSABLE | AC60: CONTROLADO | AD60: I5-3470 | AE60: 12GB | AF60: 250GB | AG60: WINDOWS 10 PRO | AH60: 41558 | AI60: 42746 | AJ60: =FLOOR(YEARFRAC(AH60, TODAY(), 1),1) -> 12 | AL60: JHONATHAN ARMANDO CAMARGO IZQUIERDO | AN60: N/A | AO60: PERFIL 2 | AP60: LAPTOP | AQ60: RECURSOS BOGOTA | AR60: {=IFERROR(XLOOKUP(V60,'AV 23-12-2025'!A:A,'AV 23-12-2025'!D:D),"zz.No cruza con AV")} -> 19/12/25 12:37:39 COT | AS60: {=IFERROR(XLOOKUP(V60,'AV 23-12-2025'!A:A,'AV 23-12-2025'!C:C), "No cruza con AV")} -> Maricela Garcia | AT60: Si cruza con Antivirus
A61: FEDERACIÓN | B61: SUCURSAL IBAGUE | C61: FON1 | D61: FEDERACIÓN | E61: EMPLEADO | F61: 65815394 | G61: MGONZALEZ394 | H61: MARTHA LUCIA GONZALEZ TRUJILLO | I61: TOLIMA | J61: IBAGUE | K61: ANALISTA | L61: PROGRAMA CREDITO CAFETERO | M61: 2 | N61: RECURSO PROPIO | O61: N/A | P61: N/A | Q61: N/A | R61: N/A | S61: N/A | U61: EQUIPO ESCRITORIO | V61: 1YNKHX1 | W61: 10066847 | X61: DELL | Y61: OPTIPLEX 7010 | Z61: W10FETOLJNMONCA | AA61: EN OPERACION | AB61: ASIGNACION RESPONSABLE | AC61: CONTROLADO | AD61: I5-3470 | AE61: 12GB | AF61: 250GB | AG61: WINDOWS 10 PRO | AH61: 41451 | AI61: 42548 | AJ61: =FLOOR(YEARFRAC(AH61, TODAY(), 1),1) -> 12 | AL61: JHONATHAN ARMANDO CAMARGO IZQUIERDO | AN61: N/A | AO61: PERFIL 1 | AP61: DESKTOP | AQ61: PAC | AR61: {=IFERROR(XLOOKUP(V61,'AV 23-12-2025'!A:A,'AV 23-12-2025'!D:D),"zz.No cruza con AV")} -> 23/12/25 12:45:14 COT | AS61: {=IFERROR(XLOOKUP(V61,'AV 23-12-2025'!A:A,'AV 23-12-2025'!C:C), "No cruza con AV")} -> Jessica Moncaleano | AT61: Si cruza con Antivirus
A62: FEDERACIÓN | B62: SUCURSAL IBAGUE | C62: FON1 | D62: FEDERACIÓN | E62: EMPLEADO | F62: 1005715189 | H62: DANIEL FELIPE ROJAS MENDEZ | I62: TOLIMA | J62: IBAGUE | K62: PASANTE | L62: EXTENSION RURAL | M62: 2 | N62: RECURSO PROPIO | O62: N/A | P62: N/A | Q62: N/A | R62: N/A | S62: N/A | U62: EQUIPO TODO EN UNO | V62: BB1CBY1 | W62: 10063520 | X62: DELL | Y62: OPTIPLEX 9020 AiO | Z62: W10FETOLKFWTOL | AA62: EN OPERACION | AB62: ASIGNACION RESPONSABLE | AC62: CONTROLADO | AD62: I5-4570s | AE62: 4GB | AF62: 500GB | AG62: WINDOWS 10 PRO | AH62: 41541 | AI62: 42638 | AJ62: =FLOOR(YEARFRAC(AH62, TODAY(), 1),1) -> 12 | AL62: JHONATHAN ARMANDO CAMARGO IZQUIERDO | AN62: N/A | AO62: N/A | AP62: N/A | AQ62: N/A | AR62: {=IFERROR(XLOOKUP(V62,'AV 23-12-2025'!A:A,'AV 23-12-2025'!D:D),"zz.No cruza con AV")} -> zz.No cruza con AV | AS62: {=IFERROR(XLOOKUP(V62,'AV 23-12-2025'!A:A,'AV 23-12-2025'!C:C), "No cruza con AV")} -> No cruza con AV | AT62: No cruza con Antivirus
A63: FEDERACIÓN | B63: SUCURSAL IBAGUE | C63: FON1 | D63: FEDERACIÓN | E63: EMPLEADO | F63: 28541956 | G63: 28541956 | H63: JEIMMY ROCIO ARCINIEGAS PEREZ | I63: TOLIMA | J63: IBAGUE | K63: ANALISTA | L63: EXTENSION RURAL | M63: 2 | N63: RECURSO PROPIO | O63: N/A | P63: N/A | Q63: N/A | R63: N/A | S63: N/A | U63: EQUIPO ESCRITORIO | V63: 89SQBY1 | W63: 10066898 | X63: DELL | Y63: OPTIPLEX 7010 | Z63: W10FETOLJARC | AA63: EN OPERACION | AB63: ASIGNACION RESPONSABLE | AC63: CONTROLADO | AD63: I5-3470 | AE63: 16GB | AF63: 250GB | AG63: WINDOWS 10 PRO | AH63: 41544 | AI63: 42631 | AJ63: =FLOOR(YEARFRAC(AH63, TODAY(), 1),1) -> 12 | AL63: JHONATHAN ARMANDO CAMARGO IZQUIERDO | AN63: N/A | AO63: PERFIL 1 | AP63: DESKTOP | AQ63: PAC | AR63: {=IFERROR(XLOOKUP(V63,'AV 23-12-2025'!A:A,'AV 23-12-2025'!D:D),"zz.No cruza con AV")} -> 23/12/25 12:29:17 COT | AS63: {=IFERROR(XLOOKUP(V63,'AV 23-12-2025'!A:A,'AV 23-12-2025'!C:C), "No cruza con AV")} -> Nidia Moreno | AT63: Si cruza con Antivirus
A64: FEDERACIÓN | B64: SUCURSAL IBAGUE | C64: FON1 | D64: FEDERACIÓN | E64: EMPLEADO | F64: 1110541614 | H64: JHONATHAN ARMANDO CAMARGO IZQUIERDO | I64: TOLIMA | J64: IBAGUE | K64: ANALISTA TIC | L64: TIC | M64: 2 | N64: RECURSO PROPIO | O64: N/A | P64: N/A | Q64: N/A | R64: N/A | S64: N/A | U64: EQUIPO PORTATIL | V64: CL3T3X1 | W64: 10062127 | X64: DELL | Y64: LATITUDE E5430 | Z64: No Aplica | AA64: ALMACENADO | AB64: RETORNO | AC64: CONTROLADO | AD64: Core i5-3320M | AE64: EXTRAIDA | AF64: No Aplica | AG64: No Aplica | AH64: 41395 | AI64: 42492 | AJ64: =FLOOR(YEARFRAC(AH64, TODAY(), 1),1) -> 12 | AL64: JHONATHAN ARMANDO CAMARGO IZQUIERDO | AN64: ACTUALIZAR BIOS - DAÑO PANTALLA Y CARCASA EXTERNA | AO64: N/A | AP64: N/A | AQ64: N/A | AR64: {=IFERROR(XLOOKUP(V64,'AV 23-12-2025'!A:A,'AV 23-12-2025'!D:D),"zz.No cruza con AV")} -> 12/05/25 13:57:18 COT | AS64: {=IFERROR(XLOOKUP(V64,'AV 23-12-2025'!A:A,'AV 23-12-2025'!C:C), "No cruza con AV")} -> Jhon Gomez | AT64: Si cruza con Antivirus
A65: FEDERACIÓN | B65: SUCURSAL IBAGUE | C65: FON1 | D65: FEDERACIÓN | E65: EMPLEADO | F65: 1110541614 | H65: JHONATHAN ARMANDO CAMARGO IZQUIERDO | I65: TOLIMA | J65: IBAGUE | K65: ANALISTA TIC | L65: TIC | M65: 2 | N65: RECURSO PROPIO | O65: N/A | P65: N/A | Q65: N/A | R65: N/A | S65: N/A | U65: EQUIPO PORTATIL | V65: 816T3X1 | W65: 10062121 | X65: DELL | Y65: LATITUDE E5430 | Z65: No Aplica | AA65: ALMACENADO | AB65: ALISTAMIENTO/SOPORTE | AC65: CONTROLADO | AD65: Core i5-3230M | AE65: N/A | AF65: No Aplica | AG65: No Aplica | AH65: 41395 | AI65: 42492 | AJ65: =FLOOR(YEARFRAC(AH65, TODAY(), 1),1) -> 12 | AL65: JHONATHAN ARMANDO CAMARGO IZQUIERDO | AN65: SIN RAM - NO ENCIENDE - CORTO BOARD | AO65: N/A | AP65: N/A | AQ65: N/A | AR65: {=IFERROR(XLOOKUP(V65,'AV 23-12-2025'!A:A,'AV 23-12-2025'!D:D),"zz.No cruza con AV")} -> 31/07/25 5:33:46 COT | AS65: {=IFERROR(XLOOKUP(V65,'AV 23-12-2025'!A:A,'AV 23-12-2025'!C:C), "No cruza con AV")} -> Jeyiluz Ramirez | AT65: Si cruza con Antivirus
A66: FEDERACIÓN | B66: SUCURSAL IBAGUE | C66: FON1 | D66: FEDERACIÓN | E66: EMPLEADO | F66: 1075310355 | G66: NGUZMAN355 | H66: NATALIA GUZMAN QUINTERO | I66: TOLIMA | J66: IBAGUE | K66: AUXILIAR ADMINISTRATIVO | L66: PROGRAMA SICA | M66: 2 | N66: RECURSO PROPIO | O66: N/A | P66: N/A | Q66: N/A | R66: N/A | S66: N/A | U66: EQUIPO ESCRITORIO | V66: 5YL06V1 | W66: 10062050 | X66: DELL | Y66: OPTIPLEX 7010 | Z66: DESKTOP-4I5VMEK | AA66: EN OPERACION | AB66: ASIGNACION RESPONSABLE | AC66: CONTROLADO | AD66: I5-3550 | AE66: 4GB | AF66: 500GB | AG66: WINDOWS 10 PRO | AH66: 41227 | AI66: 42323 | AJ66: =FLOOR(YEARFRAC(AH66, TODAY(), 1),1) -> 13 | AL66: JHONATHAN ARMANDO CAMARGO IZQUIERDO | AN66: N/A | AO66: PERFIL 1 | AP66: DESKTOP | AQ66: PAC | AR66: {=IFERROR(XLOOKUP(V66,'AV 23-12-2025'!A:A,'AV 23-12-2025'!D:D),"zz.No cruza con AV")} -> 23/12/25 12:44:43 COT | AS66: {=IFERROR(XLOOKUP(V66,'AV 23-12-2025'!A:A,'AV 23-12-2025'!C:C), "No cruza con AV")} -> Natalia Guzman | AT66: Si cruza con Antivirus
A67: FEDERACIÓN | B67: SUCURSAL IBAGUE | C67: FON1 | D67: FEDERACIÓN | E67: EMPLEADO | F67: 1110541614 | H67: JHONATHAN ARMANDO CAMARGO IZQUIERDO | I67: TOLIMA | J67: IBAGUE | K67: ANALISTA TIC | L67: TIC | M67: 2 | N67: RECURSO PROPIO | O67: N/A | P67: N/A | Q67: N/A | R67: N/A | S67: N/A | U67: EQUIPO ESCRITORIO | V67: F0YZMS1 | W67: 10058675 | X67: DELL | Y67: D05D | Z67: No Aplica | AA67: ALMACENADO | AB67: RETORNO | AC67: CONTROLADO | AD67: Core i5 2400 | AE67: 8GB | AF67: No Aplica | AG67: No Aplica | AH67: 41017 | AI67: 42113 | AJ67: =FLOOR(YEARFRAC(AH67, TODAY(), 1),1) -> 13 | AL67: JHONATHAN ARMANDO CAMARGO IZQUIERDO | AN67: SIN HDD | AO67: N/A | AP67: N/A | AQ67: N/A | AR67: {=IFERROR(XLOOKUP(V67,'AV 23-12-2025'!A:A,'AV 23-12-2025'!D:D),"zz.No cruza con AV")} -> zz.No cruza con AV | AS67: {=IFERROR(XLOOKUP(V67,'AV 23-12-2025'!A:A,'AV 23-12-2025'!C:C), "No cruza con AV")} -> No cruza con AV | AT67: No cruza con Antivirus
A68: FEDERACIÓN | B68: SUCURSAL IBAGUE | C68: FON1 | D68: FEDERACIÓN | E68: EMPLEADO | F68: 1110494320 | G68: JCABEZA320 | H68: JESSICA ALEXANDRA CABEZAS PATIÑO | I68: TOLIMA | J68: IBAGUE | K68: COORDINADOR FORTALECIMIENTO GREMIAL | L68: FORTALECIMIENTO GREMIAL | M68: 2 | N68: RECURSO PROPIO | O68: N/A | P68: N/A | Q68: N/A | R68: N/A | S68: N/A | U68: EQUIPO ESCRITORIO | V68: 3KW7PN1 | W68: 10052445 | X68: DELL | Y68: OPTIPLEX 980 | Z68: W10FETOLJCAB | AA68: EN OPERACION | AB68: ASIGNACION RESPONSABLE | AC68: CONTROLADO | AD68: I3-540 | AE68: 6GB | AF68: 250GB | AG68: WINDOWS 10 PRO | AH68: 40513 | AI68: 41610 | AJ68: =FLOOR(YEARFRAC(AH68, TODAY(), 1),1) -> 15 | AL68: JHONATHAN ARMANDO CAMARGO IZQUIERDO | AN68: N/A | AO68: PERFIL 2 | AP68: LAPTOP | AQ68: RECURSOS BOGOTA | AR68: {=IFERROR(XLOOKUP(V68,'AV 23-12-2025'!A:A,'AV 23-12-2025'!D:D),"zz.No cruza con AV")} -> 19/12/25 14:25:34 COT | AS68: {=IFERROR(XLOOKUP(V68,'AV 23-12-2025'!A:A,'AV 23-12-2025'!C:C), "No cruza con AV")} -> Jessica Cabezas | AT68: Si cruza con Antivirus
A69: FEDERACIÓN | B69: SUCURSAL IBAGUE | C69: FON1 | D69: FEDERACIÓN | E69: EMPLEADO | F69: 14242690 | G69: FEJGOM | H69: JOSE CELESTINO GOMEZ ACOSTA | I69: TOLIMA | J69: IBAGUE | K69: PROFESIONAL DESARROLLO SOCIAL | L69: DESARROLLO SOCIAL | M69: 2 | N69: RECURSO PROPIO | O69: N/A | P69: N/A | Q69: N/A | R69: N/A | S69: N/A | U69: EQUIPO ESCRITORIO | V69: 3KX5PN1 | W69: 10052440 | X69: DELL | Y69: OPTIPLEX 980 | Z69: W10FETOLJCGOMEZ | AA69: EN OPERACION | AB69: ASIGNACION RESPONSABLE | AC69: CONTROLADO | AD69: I3-540 | AE69: 4GB | AF69: 250GB | AG69: WINDOWS 10 PRO | AH69: 40513 | AI69: 41610 | AJ69: =FLOOR(YEARFRAC(AH69, TODAY(), 1),1) -> 15 | AL69: JHONATHAN ARMANDO CAMARGO IZQUIERDO | AN69: N/A | AO69: PERFIL 2 | AP69: LAPTOP | AQ69: PAC | AR69: {=IFERROR(XLOOKUP(V69,'AV 23-12-2025'!A:A,'AV 23-12-2025'!D:D),"zz.No cruza con AV")} -> 19/12/25 12:18:46 COT | AS69: {=IFERROR(XLOOKUP(V69,'AV 23-12-2025'!A:A,'AV 23-12-2025'!C:C), "No cruza con AV")} -> Celestino Gomez | AT69: Si cruza con Antivirus
A70: FEDERACIÓN | B70: SUCURSAL IBAGUE | C70: FON1 | D70: FEDERACIÓN | E70: EMPLEADO | F70: 1110557986 | G70: 1110557986 | H70: JULIAN DAVID QUINTERO HERRERA | I70: TOLIMA | J70: IBAGUE | K70: AUXILIAR SERVICIOS | L70: ADMINISTRATIVOS | M70: 2 | N70: RECURSO PROPIO | O70: N/A | P70: N/A | Q70: N/A | R70: N/A | S70: N/A | U70: EQUIPO ESCRITORIO | V70: 3KW6PN1 | W70: 10052442 | X70: DELL | Y70: OPTIPLEX 980 | Z70: W10FETOLCONTAB | AA70: EN OPERACION | AB70: ASIGNACION RESPONSABLE | AC70: CONTROLADO | AD70: I3-540 | AE70: 4GB | AF70: 250GB | AG70: WINDOWS 10 PRO | AH70: 40513 | AI70: 41610 | AJ70: =FLOOR(YEARFRAC(AH70, TODAY(), 1),1) -> 15 | AL70: JHONATHAN ARMANDO CAMARGO IZQUIERDO | AN70: N/A | AO70: PERFIL 2 | AP70: LAPTOP | AQ70: RECURSOS BOGOTA | AR70: {=IFERROR(XLOOKUP(V70,'AV 23-12-2025'!A:A,'AV 23-12-2025'!D:D),"zz.No cruza con AV")} -> 23/12/25 11:47:50 COT | AS70: {=IFERROR(XLOOKUP(V70,'AV 23-12-2025'!A:A,'AV 23-12-2025'!C:C), "No cruza con AV")} -> Contabilidad | AT70: Si cruza con Antivirus
A71: FEDERACIÓN | B71: SUCURSAL IBAGUE | C71: FON1 | D71: FEDERACIÓN | E71: EMPLEADO | F71: 28936342 | G71: LSALAS342 | H71: LILIANA JHOANA SALAS | I71: TOLIMA | J71: IBAGUE | K71: AUXILIAR ADMINISTRATIVO | L71: ARCHIVO | M71: ARCHIVO | N71: RECURSO PROPIO | O71: N/A | P71: N/A | Q71: N/A | R71: N/A | S71: N/A | U71: EQUIPO ESCRITORIO | V71: 3KW8PN1 | W71: 10052448 | X71: DELL | Y71: OPTIPLEX 980 | Z71: W10FETOLACHITOL | AA71: EN OPERACION | AB71: ASIGNACION RESPONSABLE | AC71: CONTROLADO | AD71: I3-540 | AE71: 8GB | AF71: 250GB | AG71: WINDOWS 10 PRO | AH71: 40513 | AI71: 41610 | AJ71: =FLOOR(YEARFRAC(AH71, TODAY(), 1),1) -> 15 | AL71: JHONATHAN ARMANDO CAMARGO IZQUIERDO | AN71: N/A | AO71: PERFIL 1 | AP71: DESKTOP | AQ71: RECURSOS BOGOTA | AR71: {=IFERROR(XLOOKUP(V71,'AV 23-12-2025'!A:A,'AV 23-12-2025'!D:D),"zz.No cruza con AV")} -> 19/12/25 19:22:02 COT | AS71: {=IFERROR(XLOOKUP(V71,'AV 23-12-2025'!A:A,'AV 23-12-2025'!C:C), "No cruza con AV")} -> Archivo Tolima | AT71: Si cruza con Antivirus
A72: FEDERACIÓN | B72: SUCURSAL IBAGUE | C72: FON1 | D72: FEDERACIÓN | E72: EMPLEADO | H72: GISET CAMILA TOVAR ASCENCIO | I72: TOLIMA | J72: IBAGUE | K72: PROMOTOR DESARROLLO RURAL | L72: DESARROLLO SOCIAL | M72: 2 | N72: RECURSO PROPIO | O72: N/A | P72: N/A | Q72: N/A | R72: N/A | S72: N/A | U72: EQUIPO PORTATIL | V72: BPLQ824 | W72: 10104244 | X72: DELL | Y72: Latitude 3440 | Z72: L11FETOLJDE3 | AA72: EN OPERACION | AB72: ASIGNACION RESPONSABLE | AC72: CONTROLADO | AD72: I5-1335u | AE72: 16GB | AF72: 500GB | AG72: WINDOWS 11 PRO | AH72: 45069 | AI72: 45946 | AJ72: =FLOOR(YEARFRAC(AH72, TODAY(), 1),1) -> 2 | AL72: JHONATHAN ARMANDO CAMARGO IZQUIERDO | AN72: N/A | AO72: N/A | AP72: N/A | AQ72: N/A | AR72: {=IFERROR(XLOOKUP(V72,'AV 23-12-2025'!A:A,'AV 23-12-2025'!D:D),"zz.No cruza con AV")} -> 19/12/25 12:26:35 COT | AS72: {=IFERROR(XLOOKUP(V72,'AV 23-12-2025'!A:A,'AV 23-12-2025'!C:C), "No cruza con AV")} -> JDE3 | AT72: Si cruza con Antivirus
A73: FEDERACIÓN | B73: SUCURSAL IBAGUE | C73: FON1 | D73: FEDERACIÓN | E73: EMPLEADO | G73: KAGONZA679 | H73: ANDREA GONZALEZ PEREZ | I73: TOLIMA | J73: IBAGUE | K73: RECEPCION | L73: RECEPCION | M73: RECEPCION | N73: RECURSO PROPIO | O73: N/A | P73: N/A | Q73: N/A | R73: N/A | S73: N/A | U73: EQUIPO ESCRITORIO | V73: 1G0QSD2 | W73: 10078205 | X73: DELL | Y73: OPTIPLEX 3040 | Z73: L10FETOLAGON01 | AA73: EN OPERACION | AB73: ASIGNACION RESPONSABLE | AC73: CONTROLADO | AD73: I5-6500 | AE73: 8GB | AF73: 250GB | AG73: WINDOWS 10 PRO | AH73: 42697 | AI73: 43823 | AJ73: =FLOOR(YEARFRAC(AH73, TODAY(), 1),1) -> 9 | AL73: JHONATHAN ARMANDO CAMARGO IZQUIERDO | AN73: N/A | AO73: PERFIL 1 | AP73: DESKTOP | AQ73: RECURSOS BOGOTA | AR73: {=IFERROR(XLOOKUP(V73,'AV 23-12-2025'!A:A,'AV 23-12-2025'!D:D),"zz.No cruza con AV")} -> 8/05/25 19:22:28 COT | AS73: {=IFERROR(XLOOKUP(V73,'AV 23-12-2025'!A:A,'AV 23-12-2025'!C:C), "No cruza con AV")} -> Jorge Triana | AT73: Si cruza con Antivirus
A74: FEDERACIÓN | B74: SUCURSAL IBAGUE | C74: FON1 | D74: FEDERACIÓN | E74: EMPLEADO | H74: CARLOS JONNATHAN HERNANDEZ PARRA | I74: TOLIMA | J74: IBAGUE | K74: ANALISTA PROGRAMA DE COMUNICACIONES | L74: COMUNICACIONES | M74: 2 | N74: RECURSO PROPIO | O74: N/A | P74: N/A | Q74: N/A | R74: N/A | S74: N/A | U74: EQUIPO ESCRITORIO | V74: GVY4H32K33 | W74: 10103257 | X74: APPLE | Y74: iMac 24 pulgadas 2023 | Z74: iMac de COMUNITOL | AA74: EN OPERACION | AB74: ASIGNACION RESPONSABLE | AC74: CONTROLADO | AD74: Apple M3 | AE74: 16GB | AF74: 500GB | AG74: macOS Sonoma 14.6.1 | AH74: 45525 | AI74: 45890 | AJ74: =FLOOR(YEARFRAC(AH74, TODAY(), 1),1) -> 1 | AL74: JHONATHAN ARMANDO CAMARGO IZQUIERDO | AN74: N/A | AO74: N/A | AP74: N/A | AQ74: N/A | AR74: {=IFERROR(XLOOKUP(V74,'AV 23-12-2025'!A:A,'AV 23-12-2025'!D:D),"zz.No cruza con AV")} -> zz.No cruza con AV | AS74: {=IFERROR(XLOOKUP(V74,'AV 23-12-2025'!A:A,'AV 23-12-2025'!C:C), "No cruza con AV")} -> No cruza con AV | AT74: No cruza con Antivirus
A75: FEDERACIÓN | B75: SUCURSAL IBAGUE | C75: FON1 | D75: FEDERACIÓN | E75: EMPLEADO | G75: FEDVER | H75: DIANA VALENTINA VERGARA GONZALEZ | I75: TOLIMA | J75: IBAGUE | K75: COORDINADOR CONTABLE | L75: FINANCIEROS | M75: 2 | N75: RECURSO PROPIO | O75: N/A | P75: N/A | Q75: N/A | R75: N/A | S75: N/A | U75: EQUIPO ESCRITORIO | V75: 7WT9MH3 | W75: 10095935 | X75: DELL | Y75: OPTIPLEX 3080 | Z75: W11FETOLDVER | AA75: EN OPERACION | AB75: ASIGNACION RESPONSABLE | AC75: CONTROLADO | AD75: Corte i5-10500t | AE75: 16GB | AF75: 500GB | AG75: WINDOWS 11 PRO | AH75: 44448 | AI75: 45574 | AJ75: =FLOOR(YEARFRAC(AH75, TODAY(), 1),1) -> 4 | AL75: JHONATHAN ARMANDO CAMARGO IZQUIERDO | AN75: N/A | AO75: N/A | AP75: N/A | AQ75: N/A | AR75: {=IFERROR(XLOOKUP(V75,'AV 23-12-2025'!A:A,'AV 23-12-2025'!D:D),"zz.No cruza con AV")} -> 23/12/25 12:46:47 COT | AS75: {=IFERROR(XLOOKUP(V75,'AV 23-12-2025'!A:A,'AV 23-12-2025'!C:C), "No cruza con AV")} -> Valentina Vergara | AT75: Si cruza con Antivirus
A76: FEDERACIÓN | B76: SUCURSAL IBAGUE | C76: FON1 | D76: FEDERACIÓN | E76: EMPLEADO | G76: FEGIMO | H76: GILDARDO MONROY GUERRERO | I76: TOLIMA | J76: IBAGUE | K76: DIRECTOR EJECUTIVO | L76: DIRECCION | M76: 2 | N76: RECURSO PROPIO | O76: N/A | P76: N/A | Q76: N/A | R76: N/A | S76: N/A | U76: EQUIPO PORTATIL | V76: DSNX2C4 | W76: 10105304 | X76: DELL | Y76: Dell Pro 14 P193G | Z76: L11FNCTOLGMON01 | AA76: EN OPERACION | AB76: ASIGNACION RESPONSABLE | AC76: CONTROLADO | AD76: Core Ultra 7 255U | AE76: 16GB | AF76: 500GB | AG76: WINDOWS 11 PRO | AH76: 45877 | AI76: 47004 | AJ76: =FLOOR(YEARFRAC(AH76, TODAY(), 1),1) -> 0 | AL76: JHONATHAN ARMANDO CAMARGO IZQUIERDO | AN76: N/A | AO76: N/A | AP76: N/A | AQ76: N/A | AR76: {=IFERROR(XLOOKUP(V76,'AV 23-12-2025'!A:A,'AV 23-12-2025'!D:D),"zz.No cruza con AV")} -> zz.No cruza con AV | AS76: {=IFERROR(XLOOKUP(V76,'AV 23-12-2025'!A:A,'AV 23-12-2025'!C:C), "No cruza con AV")} -> No cruza con AV | AT76: No cruza con Antivirus
A77: FEDERACIÓN | B77: SUCURSAL IBAGUE | C77: FON1 | D77: FEDERACIÓN | E77: CONTRATISTA | G77: N/A | H77: CONTRATISTA | I77: TOLIMA | J77: IBAGUE | K77: AUXILIAR ADMINISTRATIVO | L77: BENEFICIO ECOLOGICO | M77: 2 | N77: RECURSO PROPIO | O77: 1110585547 | P77: GERMAN CAMILO ROMERO MOSQUERA | Q77: COORDINADOR BENEFICIO ECOLOGICO | R77: IBAGUE | S77: BENEFICIO ECOLOGICO | T77: RECURSO PROPIO | U77: EQUIPO PORTATIL | V77: 96WJS93 | W77: 10105231 | X77: DELL | Y77: Latitude 3420 | Z77: L11FETOLRENOV3 | AA77: EN OPERACION | AB77: ASIGNACION RESPONSABLE | AC77: CONTROLADO | AD77: Core i3-1115G4 | AE77: 4GB | AF77: 500GB | AG77: WINDOWS 11 PRO | AH77: 44351 | AI77: 44787 | AJ77: =FLOOR(YEARFRAC(AH77, TODAY(), 1),1) -> 4 | AL77: JHONATHAN ARMANDO CAMARGO IZQUIERDO | AN77: N/A | AO77: N/A | AP77: N/A | AQ77: N/A | AR77: {=IFERROR(XLOOKUP(V77,'AV 23-12-2025'!A:A,'AV 23-12-2025'!D:D),"zz.No cruza con AV")} -> zz.No cruza con AV | AS77: {=IFERROR(XLOOKUP(V77,'AV 23-12-2025'!A:A,'AV 23-12-2025'!C:C), "No cruza con AV")} -> No cruza con AV | AT77: No cruza con Antivirus
A78: FEDERACIÓN | B78: SUCURSAL IBAGUE | C78: FON1 | D78: FEDERACIÓN | E78: EMPLEADO | G78: FEDCES | H78: DIANA CAROLINA CESPEDES DIAZ | I78: TOLIMA | J78: IBAGUE | K78: ANALISTA | L78: EXTENSION RURAL | M78: 2 | N78: RECURSO PROPIO | O78: N/A | P78: N/A | Q78: N/A | R78: N/A | S78: N/A | U78: EQUIPO ESCRITORIO | V78: G2VVR22 | W78: 10065506 | X78: DELL | Y78: OPTIPLEX 9020 | Z78: W10FETOLDCESP | AA78: EN OPERACION | AB78: ASIGNACION RESPONSABLE | AC78: CONTROLADO | AD78: Core i5-4590 | AE78: 22GB | AF78: 500GB | AG78: WINDOWS 10 PRO | AH78: 42012 | AI78: 43139 | AJ78: =FLOOR(YEARFRAC(AH78, TODAY(), 1),1) -> 11 | AN78: N/A | AO78: PERFIL 1 | AP78: DESKTOP | AQ78: RECURSOS BOGOTA | AR78: {=IFERROR(XLOOKUP(V78,'AV 23-12-2025'!A:A,'AV 23-12-2025'!D:D),"zz.No cruza con AV")} -> 19/12/25 11:35:42 COT | AS78: {=IFERROR(XLOOKUP(V78,'AV 23-12-2025'!A:A,'AV 23-12-2025'!C:C), "No cruza con AV")} -> Diana Cespedes | AT78: Si cruza con Antivirus
A79: FEDERACIÓN | B79: SUCURSAL IBAGUE | C79: FON1 | D79: FEDERACIÓN | E79: EMPLEADO | F79: 1110541614 | H79: JHONATHAN ARMANDO CAMARGO IZQUIERDO | I79: TOLIMA | J79: IBAGUE | K79: ANALISTA TIC | L79: TIC | M79: 2 | N79: RECURSO PROPIO | O79: N/A | P79: N/A | Q79: N/A | R79: N/A | S79: N/A | U79: EQUIPO ESCRITORIO | V79: G2T7S22 | W79: 10065507 | X79: DELL | Y79: D07S | Z79: No Aplica | AA79: ALMACENADO | AB79: BAJA | AC79: CONTROLADO | AD79: Core i5 4590 | AE79: No Aplica | AF79: No Aplica | AG79: No Aplica | AH79: 40513 | AI79: 41610 | AJ79: =FLOOR(YEARFRAC(AH79, TODAY(), 1),1) -> 15 | AL79: JHONATHAN ARMANDO CAMARGO IZQUIERDO | AN79: SIN RAM - SIN HDD - NO DETECTA DISCOS | AO79: N/A | AP79: N/A | AQ79: N/A | AR79: {=IFERROR(XLOOKUP(V79,'AV 23-12-2025'!A:A,'AV 23-12-2025'!D:D),"zz.No cruza con AV")} -> zz.No cruza con AV | AS79: {=IFERROR(XLOOKUP(V79,'AV 23-12-2025'!A:A,'AV 23-12-2025'!C:C), "No cruza con AV")} -> No cruza con AV | AT79: No cruza con Antivirus
A80: FEDERACIÓN | B80: SUCURSAL IBAGUE | C80: FON1 | D80: FEDERACIÓN | E80: EMPLEADO | F80: 1110541614 | H80: JHONATHAN ARMANDO CAMARGO IZQUIERDO | I80: TOLIMA | J80: IBAGUE | K80: ANALISTA TIC | L80: TIC | M80: 2 | N80: RECURSO PROPIO | O80: N/A | P80: N/A | Q80: N/A | R80: N/A | S80: N/A | U80: EQUIPO ESCRITORIO | V80: 3KY5PN1 | W80: 10052441 | X80: DELL | Y80: DCNE1F | Z80: No Aplica | AA80: ALMACENADO | AB80: BAJA | AC80: CONTROLADO | AD80: Core i3 3 | AE80: No Aplica | AF80: No Aplica | AG80: No Aplica | AH80: 40513 | AI80: 41610 | AJ80: =FLOOR(YEARFRAC(AH80, TODAY(), 1),1) -> 15 | AL80: JHONATHAN ARMANDO CAMARGO IZQUIERDO | AN80: SIN RAM - SIN HDD - SONIDO BOARD | AO80: N/A | AP80: N/A | AQ80: N/A | AR80: {=IFERROR(XLOOKUP(V80,'AV 23-12-2025'!A:A,'AV 23-12-2025'!D:D),"zz.No cruza con AV")} -> zz.No cruza con AV | AS80: {=IFERROR(XLOOKUP(V80,'AV 23-12-2025'!A:A,'AV 23-12-2025'!C:C), "No cruza con AV")} -> No cruza con AV | AT80: No cruza con Antivirus
A81: FEDERACIÓN | B81: SUCURSAL IBAGUE | C81: FON1 | D81: FEDERACIÓN | E81: EMPLEADO | F81: 1110541614 | H81: JHONATHAN ARMANDO CAMARGO IZQUIERDO | I81: TOLIMA | J81: IBAGUE | K81: ANALISTA TIC | L81: TIC | M81: 2 | N81: RECURSO PROPIO | O81: N/A | P81: N/A | Q81: N/A | R81: N/A | S81: N/A | U81: EQUIPO ESCRITORIO | V81: 3KX7PN1 | W81: 10052446 | X81: DELL | Y81: DCNE1F0 | Z81: No Aplica | AA81: ALMACENADO | AB81: RETORNO | AC81: CONTROLADO | AD81: Core i3 3 | AE81: No Aplica | AF81: No Aplica | AG81: No Aplica | AH81: 40513 | AI81: 41610 | AJ81: =FLOOR(YEARFRAC(AH81, TODAY(), 1),1) -> 15 | AL81: JHONATHAN ARMANDO CAMARGO IZQUIERDO | AN81: SIN RAM - SIN SO | AO81: N/A | AP81: N/A | AQ81: N/A | AR81: {=IFERROR(XLOOKUP(V81,'AV 23-12-2025'!A:A,'AV 23-12-2025'!D:D),"zz.No cruza con AV")} -> zz.No cruza con AV | AS81: {=IFERROR(XLOOKUP(V81,'AV 23-12-2025'!A:A,'AV 23-12-2025'!C:C), "No cruza con AV")} -> No cruza con AV | AT81: No cruza con Antivirus
A82: FEDERACIÓN | B82: SUCURSAL IBAGUE | C82: FON1 | D82: FEDERACIÓN | E82: EMPLEADO | F82: 1110541614 | H82: JHONATHAN ARMANDO CAMARGO IZQUIERDO | I82: TOLIMA | J82: IBAGUE | K82: ANALISTA TIC | L82: TIC | M82: 2 | N82: RECURSO PROPIO | O82: N/A | P82: N/A | Q82: N/A | R82: N/A | S82: N/A | U82: EQUIPO ESCRITORIO | V82: 3KX6PN1 | W82: 10052443 | X82: DELL | Y82: DCNE1F | Z82: No Aplica | AA82: ALMACENADO | AB82: BAJA | AC82: CONTROLADO | AD82: Core i3 3 | AE82: No Aplica | AF82: No Aplica | AG82: No Aplica | AH82: 40513 | AI82: 41610 | AJ82: =FLOOR(YEARFRAC(AH82, TODAY(), 1),1) -> 15 | AL82: JHONATHAN ARMANDO CAMARGO IZQUIERDO | AN82: SIN RAM - SIN HDD - DAÑO BOARD | AO82: N/A | AP82: N/A | AQ82: N/A | AR82: {=IFERROR(XLOOKUP(V82,'AV 23-12-2025'!A:A,'AV 23-12-2025'!D:D),"zz.No cruza con AV")} -> zz.No cruza con AV | AS82: {=IFERROR(XLOOKUP(V82,'AV 23-12-2025'!A:A,'AV 23-12-2025'!C:C), "No cruza con AV")} -> No cruza con AV | AT82: No cruza con Antivirus
A83: FEDERACIÓN | B83: SUCURSAL IBAGUE | C83: FON1 | D83: FEDERACIÓN | E83: EMPLEADO | F83: 1110541614 | H83: JHONATHAN ARMANDO CAMARGO IZQUIERDO | I83: TOLIMA | J83: IBAGUE | K83: ANALISTA TIC | L83: TIC | M83: 2 | N83: RECURSO PROPIO | O83: N/A | P83: N/A | Q83: N/A | R83: N/A | S83: N/A | U83: EQUIPO PORTATIL | V83: 9N0RNP1 | W83: 10056800 | X83: DELL | Y83: VOSTRO 3550 | Z83: No Aplica | AA83: ALMACENADO | AB83: ALISTAMIENTO/SOPORTE | AC83: CONTROLADO | AD83: N/A | AE83: N/A | AF83: No Aplica | AG83: No Aplica | AH83: 40806 | AI83: 41538 | AJ83: =FLOOR(YEARFRAC(AH83, TODAY(), 1),1) -> 14 | AL83: JHONATHAN ARMANDO CAMARGO IZQUIERDO | AN83: DAÑO BOARD - SE EXTRAE HDD - SIN RAM | AO83: N/A | AP83: N/A | AQ83: N/A | AR83: {=IFERROR(XLOOKUP(V83,'AV 23-12-2025'!A:A,'AV 23-12-2025'!D:D),"zz.No cruza con AV")} -> 19/05/25 8:34:35 COT | AS83: {=IFERROR(XLOOKUP(V83,'AV 23-12-2025'!A:A,'AV 23-12-2025'!C:C), "No cruza con AV")} -> Xiomara Alape | AT83: Si cruza con Antivirus
A84: FEDERACIÓN | B84: SUCURSAL IBAGUE | C84: FON1 | D84: FEDERACIÓN | E84: EMPLEADO | F84: 1110541614 | H84: JHONATHAN ARMANDO CAMARGO IZQUIERDO | I84: TOLIMA | J84: IBAGUE | K84: ANALISTA TIC | L84: TIC | M84: 2 | N84: RECURSO PROPIO | O84: N/A | P84: N/A | Q84: N/A | R84: N/A | S84: N/A | U84: EQUIPO PORTATIL | V84: CH442Q1 | W84: N/A | X84: DELL | Y84: INSPIRON MINI 1018 | Z84: No Aplica | AA84: ALMACENADO | AB84: RETORNO | AC84: CONTROLADO | AD84: ATOM | AE84: N/A | AF84: No Aplica | AG84: No Aplica | AH84: 40714 | AI84: 41081 | AJ84: =FLOOR(YEARFRAC(AH84, TODAY(), 1),1) -> 14 | AL84: JHONATHAN ARMANDO CAMARGO IZQUIERDO | AN84: SIN CARGADOR - NO SE VALIDA ESTADO | AO84: N/A | AP84: N/A | AQ84: N/A | AR84: {=IFERROR(XLOOKUP(V84,'AV 23-12-2025'!A:A,'AV 23-12-2025'!D:D),"zz.No cruza con AV")} -> zz.No cruza con AV | AS84: {=IFERROR(XLOOKUP(V84,'AV 23-12-2025'!A:A,'AV 23-12-2025'!C:C), "No cruza con AV")} -> No cruza con AV | AT84: No cruza con Antivirus
A85: FEDERACIÓN | B85: SUCURSAL IBAGUE | C85: FON1 | D85: FEDERACIÓN | E85: EMPLEADO | F85: 1110541614 | H85: JHONATHAN ARMANDO CAMARGO IZQUIERDO | I85: TOLIMA | J85: IBAGUE | K85: ANALISTA TIC | L85: TIC | M85: 2 | N85: RECURSO PROPIO | O85: N/A | P85: N/A | Q85: N/A | R85: N/A | S85: N/A | U85: EQUIPO TODO EN UNO | V85: 1NJS9Q1 | W85: 10058594 | X85: DELL | Y85: VOSTRO 360 W03C | Z85: No Aplica | AA85: ALMACENADO | AB85: RETORNO | AC85: CONTROLADO | AD85: Core i3 3ra | AE85: N/A | AF85: No Aplica | AG85: No Aplica | AH85: 40831 | AI85: 41928 | AJ85: =FLOOR(YEARFRAC(AH85, TODAY(), 1),1) -> 14 | AL85: JHONATHAN ARMANDO CAMARGO IZQUIERDO | AN85: BAJA 2024 MARIA V HERN | AO85: N/A | AP85: N/A | AQ85: N/A | AR85: {=IFERROR(XLOOKUP(V85,'AV 23-12-2025'!A:A,'AV 23-12-2025'!D:D),"zz.No cruza con AV")} -> zz.No cruza con AV | AS85: {=IFERROR(XLOOKUP(V85,'AV 23-12-2025'!A:A,'AV 23-12-2025'!C:C), "No cruza con AV")} -> No cruza con AV | AT85: No cruza con Antivirus
A86: FEDERACIÓN | B86: SUCURSAL IBAGUE | C86: FON1 | D86: FEDERACIÓN | E86: EMPLEADO | F86: 1110541614 | H86: JHONATHAN ARMANDO CAMARGO IZQUIERDO | I86: TOLIMA | J86: IBAGUE | K86: ANALISTA TIC | L86: TIC | M86: 2 | N86: RECURSO PROPIO | O86: N/A | P86: N/A | Q86: N/A | R86: N/A | S86: N/A | U86: EQUIPO PORTATIL | V86: N/A | W86: 20006117 | X86: DELL | Y86: VOSTRO 1320 | Z86: No Aplica | AA86: ALMACENADO | AB86: RETORNO | AC86: CONTROLADO | AD86: Core 2 Duo | AE86: N/A | AF86: No Aplica | AG86: No Aplica | AH86: NO APLICA | AI86: NO APLICA | AJ86: NO APLICA | AL86: JHONATHAN ARMANDO CAMARGO IZQUIERDO | AN86: SIN DISCO - SIN RAM - SIN TECLA M | AO86: N/A | AP86: N/A | AQ86: N/A | AR86: {=IFERROR(XLOOKUP(V86,'AV 23-12-2025'!A:A,'AV 23-12-2025'!D:D),"zz.No cruza con AV")} -> zz.No cruza con AV | AS86: {=IFERROR(XLOOKUP(V86,'AV 23-12-2025'!A:A,'AV 23-12-2025'!C:C), "No cruza con AV")} -> No cruza con AV | AT86: No cruza con Antivirus
A87: FEDERACIÓN | B87: SUCURSAL IBAGUE | C87: FON1 | D87: FEDERACIÓN | F87: NO APLICA | H87: APRENDIZ | I87: TOLIMA | J87: IBAGUE | K87: APRENDIZ | L87: APRENDIZ | M87: 2 | N87: RECURSO PROPIO | O87: N/A | P87: N/A | Q87: N/A | R87: N/A | S87: N/A | U87: EQUIPO ESCRITORIO | V87: CRVBJV2 | W87: NO APLICA | X87: DELL | Y87: OPTIPLEX 3060 | Z87: W11FETOLAPSENA1 | AA87: EN OPERACION | AB87: ASIGNACION RESPONSABLE | AC87: CONTROLADO | AD87: I5-8400t | AE87: 8GB | AF87: 250GB | AG87: WINDOWS 11 PRO | AH87: PROBLEMA CON GARANTIA | AI87: PROBLEMA CON GARANTIA | AJ87: PENDIENTE | AL87: JHONATHAN ARMANDO CAMARGO IZQUIERDO | AN87: N/A | AO87: N/A | AP87: N/A | AQ87: N/A | AR87: {=IFERROR(XLOOKUP(V87,'AV 23-12-2025'!A:A,'AV 23-12-2025'!D:D),"zz.No cruza con AV")} -> zz.No cruza con AV | AS87: {=IFERROR(XLOOKUP(V87,'AV 23-12-2025'!A:A,'AV 23-12-2025'!C:C), "No cruza con AV")} -> No cruza con AV | AT87: No cruza con Antivirus
A88: FEDERACIÓN | B88: SUCURSAL IBAGUE | C88: FON1 | D88: FEDERACIÓN | E88: EMPLEADO | F88: 1110541614 | H88: JHONATHAN ARMANDO CAMARGO IZQUIERDO | I88: TOLIMA | J88: IBAGUE | K88: ANALISTA TIC | L88: TIC | M88: 2 | N88: RECURSO PROPIO | O88: N/A | P88: N/A | Q88: N/A | R88: N/A | S88: N/A | U88: EQUIPO ESCRITORIO | V88: 400SN40090 | W88: 10099135 | X88: COMPUMAX | Y88: 1052-900-0078 | Z88: No Aplica | AA88: ALMACENADO | AB88: BAJA | AC88: CONTROLADO | AD88: Core i5 11400 | AE88: No Aplica | AF88: No Aplica | AG88: No Aplica | AH88: PENDIENTE | AI88: SIN REGISTRO | AJ88: PENDIENTE | AL88: JHONATHAN ARMANDO CAMARGO IZQUIERDO | AN88: SIN RAM - CORTO EN BOARD | AO88: N/A | AP88: N/A | AQ88: N/A | AR88: {=IFERROR(XLOOKUP(V88,'AV 23-12-2025'!A:A,'AV 23-12-2025'!D:D),"zz.No cruza con AV")} -> zz.No cruza con AV | AS88: {=IFERROR(XLOOKUP(V88,'AV 23-12-2025'!A:A,'AV 23-12-2025'!C:C), "No cruza con AV")} -> No cruza con AV | AT88: No cruza con Antivirus
A89: FEDERACIÓN | B89: SUCURSAL IBAGUE | C89: FON1 | D89: FEDERACIÓN | E89: EMPLEADO | F89: 1110541614 | H89: JHONATHAN ARMANDO CAMARGO IZQUIERDO | I89: TOLIMA | J89: IBAGUE | K89: ANALISTA TIC | L89: TIC | M89: 2 | N89: RECURSO PROPIO | O89: N/A | P89: N/A | Q89: N/A | R89: N/A | S89: N/A | U89: EQUIPO PORTATIL | V89: 5GV3PY1 | W89: 10066950 | X89: DELL | Y89: VOSTRO 3460 | Z89: No Aplica | AA89: ALMACENADO | AB89: RETORNO | AC89: CONTROLADO | AD89: Core i5-3230M | AE89: 2X4GB | AF89: No Aplica | AG89: No Aplica | AH89: SIN REGISTRO | AI89: SIN REGISTRO | AJ89: PENDIENTE | AL89: JHONATHAN ARMANDO CAMARGO IZQUIERDO | AN89: CARCASA DESGASTADA - ACTUALIZAR A SSD | AO89: N/A | AP89: N/A | AQ89: N/A | AR89: {=IFERROR(XLOOKUP(V89,'AV 23-12-2025'!A:A,'AV 23-12-2025'!D:D),"zz.No cruza con AV")} -> zz.No cruza con AV | AS89: {=IFERROR(XLOOKUP(V89,'AV 23-12-2025'!A:A,'AV 23-12-2025'!C:C), "No cruza con AV")} -> No cruza con AV | AT89: No cruza con Antivirus
A90: FEDERACIÓN | B90: SUCURSAL IBAGUE | C90: FON1 | D90: FEDERACIÓN | E90: EMPLEADO | F90: 1110541614 | H90: JHONATHAN ARMANDO CAMARGO IZQUIERDO | I90: TOLIMA | J90: IBAGUE | K90: ANALISTA TIC | L90: TIC | M90: 2 | N90: RECURSO PROPIO | O90: N/A | P90: N/A | Q90: N/A | R90: N/A | S90: N/A | U90: EQUIPO PORTATIL | V90: CJNUV2 | W90: 10066967 | X90: DELL | Y90: LATITUDE E5440 | Z90: No Aplica | AA90: ALMACENADO | AB90: ALISTAMIENTO/SOPORTE | AC90: CONTROLADO | AD90: Core i5-3230M | AE90: N/A | AF90: No Aplica | AG90: No Aplica | AH90: SIN REGISTRO | AI90: SIN REGISTRO | AJ90: PENDIENTE | AL90: JHONATHAN ARMANDO CAMARGO IZQUIERDO | AN90: CORTO BOARD | AO90: N/A | AP90: N/A | AQ90: N/A | AR90: {=IFERROR(XLOOKUP(V90,'AV 23-12-2025'!A:A,'AV 23-12-2025'!D:D),"zz.No cruza con AV")} -> zz.No cruza con AV | AS90: {=IFERROR(XLOOKUP(V90,'AV 23-12-2025'!A:A,'AV 23-12-2025'!C:C), "No cruza con AV")} -> No cruza con AV | AT90: No cruza con Antivirus
A91: FEDERACIÓN | B91: SUCURSAL IBAGUE | C91: FON1 | D91: FEDERACIÓN | E91: EMPLEADO | F91: 1110541614 | H91: JHONATHAN ARMANDO CAMARGO IZQUIERDO | I91: TOLIMA | J91: IBAGUE | K91: ANALISTA TIC | L91: TIC | M91: RICOH MP 501 DSOCIAL | N91: RECURSO PROPIO | O91: N/A | P91: N/A | Q91: N/A | R91: N/A | S91: N/A | U91: IMPRESORA | V91: RNP58387915921B | W91: 10085568 | X91: RICOH | Y91: MP 501 | Z91: No Aplica | AA91: EN OPERACIÓN | AB91: ASIGNACION RESPONSABLE | AC91: CONTROLADO | AD91: No Aplica | AE91: No Aplica | AF91: No Aplica | AG91: No Aplica | AH91: SIN REGISTRO | AI91: SIN REGISTRO | AJ91: SIN REGISTRO | AL91: JHONATHAN ARMANDO CAMARGO IZQUIERDO | AN91: N/A | AO91: N/A | AP91: N/A | AQ91: N/A | AS91: {=IFERROR(XLOOKUP(V91,'AV 23-12-2025'!A:A,'AV 23-12-2025'!C:C), "No cruza con AV")} -> No cruza con AV
A92: FEDERACIÓN | B92: SUCURSAL IBAGUE | C92: FON1 | D92: FEDERACIÓN | E92: EMPLEADO | F92: 1110541614 | H92: JHONATHAN ARMANDO CAMARGO IZQUIERDO | I92: TOLIMA | J92: IBAGUE | K92: ANALISTA TIC | L92: TIC | M92: EXTENSION | N92: RECURSO PROPIO | O92: N/A | P92: N/A | Q92: N/A | R92: N/A | S92: N/A | U92: IMPRESORA | V92: RNP583879597B09 | W92: 10105230 | X92: RICOH | Y92: IM 430 | Z92: No Aplica | AA92: EN OPERACIÓN | AB92: ASIGNACION RESPONSABLE | AC92: CONTROLADO | AD92: No Aplica | AE92: No Aplica | AF92: No Aplica | AG92: No Aplica | AH92: SIN REGISTRO | AI92: SIN REGISTRO | AJ92: SIN REGISTRO | AL92: JHONATHAN ARMANDO CAMARGO IZQUIERDO | AN92: N/A | AO92: N/A | AP92: N/A | AQ92: N/A | AS92: {=IFERROR(XLOOKUP(V92,'AV 23-12-2025'!A:A,'AV 23-12-2025'!C:C), "No cruza con AV")} -> No cruza con AV
A93: FEDERACIÓN | B93: SUCURSAL IBAGUE | C93: FON1 | D93: FEDERACIÓN | E93: EMPLEADO | F93: 1110541614 | H93: JHONATHAN ARMANDO CAMARGO IZQUIERDO | I93: TOLIMA | J93: IBAGUE | K93: ANALISTA TIC | L93: TIC | M93: BENEFICIO ECOLOGICO | N93: RECURSO PROPIO | O93: N/A | P93: N/A | Q93: N/A | R93: N/A | S93: N/A | U93: IMPRESORA | V93: RNP58387966C2A3 | W93: SIN PLACA | X93: RICOH | Y93: IM 550 | Z93: No Aplica | AA93: EN OPERACIÓN | AB93: ASIGNACION RESPONSABLE | AC93: CONTROLADO | AD93: No Aplica | AE93: No Aplica | AF93: No Aplica | AG93: No Aplica | AH93: SIN REGISTRO | AI93: SIN REGISTRO | AJ93: SIN REGISTRO | AL93: JHONATHAN ARMANDO CAMARGO IZQUIERDO | AN93: N/A | AO93: N/A | AP93: N/A | AQ93: N/A | AS93: {=IFERROR(XLOOKUP(V93,'AV 23-12-2025'!A:A,'AV 23-12-2025'!C:C), "No cruza con AV")} -> No cruza con AV
A94: FEDERACIÓN | B94: SUCURSAL IBAGUE | C94: FON1 | D94: FEDERACIÓN | E94: EMPLEADO | F94: 1110541614 | H94: JHONATHAN ARMANDO CAMARGO IZQUIERDO | I94: TOLIMA | J94: IBAGUE | K94: ANALISTA TIC | L94: TIC | M94: PROYECTOS | N94: RECURSO PROPIO | O94: N/A | P94: N/A | Q94: N/A | R94: N/A | S94: N/A | U94: IMPRESORA | V94: VE83625947 | W94: 10104273 | X94: KYOCERA | Y94: ECOSYS M5526cdw | Z94: No Aplica | AA94: EN OPERACIÓN | AB94: ASIGNACION RESPONSABLE | AC94: CONTROLADO | AD94: No Aplica | AE94: No Aplica | AF94: No Aplica | AG94: No Aplica | AH94: SIN REGISTRO | AI94: SIN REGISTRO | AJ94: SIN REGISTRO | AL94: JHONATHAN ARMANDO CAMARGO IZQUIERDO | AN94: N/A | AO94: N/A | AP94: N/A | AQ94: N/A | AS94: {=IFERROR(XLOOKUP(V94,'AV 23-12-2025'!A:A,'AV 23-12-2025'!C:C), "No cruza con AV")} -> No cruza con AV
A95: FEDERACIÓN | B95: SUCURSAL IBAGUE | C95: FON1 | D95: FEDERACIÓN | E95: EMPLEADO | F95: 1110541614 | H95: JHONATHAN ARMANDO CAMARGO IZQUIERDO | I95: TOLIMA | J95: IBAGUE | K95: ANALISTA TIC | L95: TIC | M95: SICA | N95: RECURSO PROPIO | O95: N/A | P95: N/A | Q95: N/A | R95: N/A | S95: N/A | U95: IMPRESORA | V95: CND8F8C87R | W95: 10066940 | X95: HP | Y95: HP LaserJet 400 MFP M425dn | Z95: No Aplica | AA95: EN OPERACIÓN | AB95: ASIGNACION RESPONSABLE | AC95: CONTROLADO | AD95: No Aplica | AE95: No Aplica | AF95: No Aplica | AG95: No Aplica | AH95: SIN REGISTRO | AI95: SIN REGISTRO | AJ95: SIN REGISTRO | AL95: JHONATHAN ARMANDO CAMARGO IZQUIERDO | AN95: N/A | AO95: N/A | AP95: N/A | AQ95: N/A | AS95: {=IFERROR(XLOOKUP(V95,'AV 23-12-2025'!A:A,'AV 23-12-2025'!C:C), "No cruza con AV")} -> No cruza con AV
A96: FEDERACIÓN | B96: SUCURSAL IBAGUE | C96: FON1 | D96: FEDERACIÓN | E96: EMPLEADO | F96: 1110541614 | H96: JHONATHAN ARMANDO CAMARGO IZQUIERDO | I96: TOLIMA | J96: IBAGUE | K96: ANALISTA TIC | L96: TIC | M96: FORTALECIMIENTO GREMIAL | N96: RECURSO PROPIO | O96: N/A | P96: N/A | Q96: N/A | R96: N/A | S96: N/A | U96: IMPRESORA | V96: CND8F1K04C | W96: 10065470 | X96: HP | Y96: HP LaserJet 400 MFP M425dn | Z96: No Aplica | AA96: EN OPERACIÓN | AB96: ASIGNACION RESPONSABLE | AC96: CONTROLADO | AD96: No Aplica | AE96: No Aplica | AF96: No Aplica | AG96: No Aplica | AH96: SIN REGISTRO | AI96: SIN REGISTRO | AJ96: SIN REGISTRO | AL96: JHONATHAN ARMANDO CAMARGO IZQUIERDO | AN96: N/A | AO96: N/A | AP96: N/A | AQ96: N/A | AS96: {=IFERROR(XLOOKUP(V96,'AV 23-12-2025'!A:A,'AV 23-12-2025'!C:C), "No cruza con AV")} -> No cruza con AV
A97: FEDERACIÓN | B97: SUCURSAL IBAGUE | C97: FON1 | D97: FEDERACIÓN | E97: EMPLEADO | F97: 1110541614 | H97: JHONATHAN ARMANDO CAMARGO IZQUIERDO | I97: TOLIMA | J97: IBAGUE | K97: ANALISTA TIC | L97: TIC | M97: FORTALECIMIENTO GREMIAL | N97: RECURSO PROPIO | O97: N/A | P97: N/A | Q97: N/A | R97: N/A | S97: N/A | U97: IMPRESORA | V97: NPIB8C4B8 | W97: 10065471 | X97: HP | Y97: HP LaserJet 400 MFP M425dn | Z97: No Aplica | AA97: EN OPERACIÓN | AB97: ASIGNACION RESPONSABLE | AC97: CONTROLADO | AD97: No Aplica | AE97: No Aplica | AF97: No Aplica | AG97: No Aplica | AH97: SIN REGISTRO | AI97: SIN REGISTRO | AJ97: SIN REGISTRO | AL97: JHONATHAN ARMANDO CAMARGO IZQUIERDO | AN97: N/A | AO97: N/A | AP97: N/A | AQ97: N/A | AS97: {=IFERROR(XLOOKUP(V97,'AV 23-12-2025'!A:A,'AV 23-12-2025'!C:C), "No cruza con AV")} -> No cruza con AV
A98: FEDERACIÓN | B98: SUCURSAL IBAGUE | C98: FON1 | D98: FEDERACIÓN | E98: EMPLEADO | F98: 1110516526 | H98: JENNY DANIELA REYES OTALORA | I98: TOLIMA | J98: ABECHUCOS | K98: EXTENSIONISTA | L98: EXTENSION RURAL | M98: ABECHUCOS | N98: PAC | O98: N/A | P98: N/A | Q98: N/A | R98: N/A | S98: N/A | U98: TABLETA | V98: 24358524702446 | W98: CR46800 | X98: ZEBRA TECHNOLOGIES | Y98: ET45 | AA98: EN OPERACIÓN | AB98: ASIGNACION RESPONSABLE | AC98: CONTROLADO | AD98: Qualcomm Snapdragon™ SM6375 | AE98: 4GB | AF98: 64GB | AG98: Android | AH98: SIN REGISTRO | AI98: SIN REGISTRO | AJ98: SIN REGISTRO | AL98: JHONATHAN ARMANDO CAMARGO IZQUIERDO | AN98: SIN MONITOR | AO98: N/A | AP98: N/A | AQ98: N/A | AR98: {=IFERROR(XLOOKUP(V98,'AV 23-12-2025'!A:A,'AV 23-12-2025'!D:D),"zz.No cruza con AV")} -> zz.No cruza con AV | AS98: {=IFERROR(XLOOKUP(V98,'AV 23-12-2025'!A:A,'AV 23-12-2025'!C:C), "No cruza con AV")} -> No cruza con AV | AT98: No cruza con Antivirus
A99: FEDERACIÓN | B99: SUCURSAL IBAGUE | C99: FON1 | D99: FEDERACIÓN | E99: EMPLEADO | F99: 1016050789 | H99: SOLTMER ANDRES SANCHEZ CERQUERA | I99: TOLIMA | J99: AMBEIMA | K99: EXTENSIONISTA | L99: EXTENSION RURAL | M99: AMBEIMA | N99: PAC | O99: N/A | P99: N/A | Q99: N/A | R99: N/A | S99: N/A | U99: TABLETA | V99: R52WA02SJ3F | W99: 20009432 | X99: SAMSUNG | Y99: SM-T575 | Z99: TOL26 | AA99: EN OPERACIÓN | AB99: ASIGNACION RESPONSABLE | AC99: CONTROLADO | AD99: EXYNOS 9810 | AE99: 4GB | AF99: 64GB | AG99: Android | AH99: SIN REGISTRO | AI99: SIN REGISTRO | AJ99: SIN REGISTRO | AL99: JHONATHAN ARMANDO CAMARGO IZQUIERDO | AN99: SIN MONITOR | AO99: N/A | AP99: N/A | AQ99: N/A | AR99: {=IFERROR(XLOOKUP(V99,'AV 23-12-2025'!A:A,'AV 23-12-2025'!D:D),"zz.No cruza con AV")} -> zz.No cruza con AV | AS99: {=IFERROR(XLOOKUP(V99,'AV 23-12-2025'!A:A,'AV 23-12-2025'!C:C), "No cruza con AV")} -> No cruza con AV | AT99: No cruza con Antivirus
A100: FEDERACIÓN | B100: SUCURSAL IBAGUE | C100: FON1 | D100: FEDERACIÓN | E100: EMPLEADO | F100: 1005815055 | G100: BGIRALDO55 | H100: BRAYAN STEVEN GIRALDO ROMERO | I100: TOLIMA | J100: EL CEDRO | K100: EXTENSIONISTA | L100: EXTENSION RURAL | M100: EL CEDRO | N100: PAC | O100: N/A | P100: N/A | Q100: N/A | R100: N/A | S100: N/A | U100: TABLETA | V100: R52WA02SRQF | W100: 20009441 | X100: SAMSUNG | Y100: SM-T575 | Z100: TOL104 | AA100: EN OPERACIÓN | AB100: ASIGNACION RESPONSABLE | AC100: CONTROLADO | AD100: EXYNOS 9810 | AE100: 4GB | AF100: 64GB | AG100: Android | AH100: SIN REGISTRO | AI100: SIN REGISTRO | AJ100: SIN REGISTRO | AL100: JHONATHAN ARMANDO CAMARGO IZQUIERDO | AN100: SIN MONITOR | AO100: N/A | AP100: N/A | AQ100: N/A | AR100: {=IFERROR(XLOOKUP(V100,'AV 23-12-2025'!A:A,'AV 23-12-2025'!D:D),"zz.No cruza con AV")} -> zz.No cruza con AV | AS100: {=IFERROR(XLOOKUP(V100,'AV 23-12-2025'!A:A,'AV 23-12-2025'!C:C), "No cruza con AV")} -> No cruza con AV | AT100: No cruza con Antivirus
...

Sheet Tabla dinámica 2

Sheet AV 23-12-2025
A1: Número de serie del sistema | B1: Nombre de sistema | C1: Nombre de usuario | D1: Última comunicación | E1: Dirección IP | F1: Fabricante del sistema | G1: Sistema operativo | H1: Espacio total en disco | I1: Tipo de CPU | J1: Modelo del sistema | K1: Memoria física total | L1: ID de plataforma | M1: Plataforma de SO | N1: Nombre de grupo | O1: Versión de producto (Trellix DLP Endpoint) | P1: Dirección MAC | Q1: Clasificación del Árbol de sistemas
A2: 8CN30905BJ | B2: 022WXPFEQUIPA | C2: ALMACEN ARMENIA | D2: 23/12/25 12:54:42 COT | E2: 192.168.122.59 | F2: HP | G2: Tipo de SO:Windows 10,Plataforma de SO:Workstation,Versión de SO:10.0 | H2: 487207 MB | I2: 12th Gen Intel(R) Core(TM) i5-12500 | J2: HP ProOne 440 23.8 inch G9 All-in-One Desktop PC | K2: 16.053,58 MB | L2: Windows 10:10:0:0 | M2: Estación de trabajo | N2: Comite Quindio | O2: 11.11.2.1172 | P2: 7C4D8FF30953 | Q2: Desactivado
A3: 8CC1022Z6V | B3: 041WXPFEQUIPA | C3: ALMACEN CALARCA | D3: 23/12/25 11:58:06 COT | E3: 192.168.1.14 | F3: HP | G3: Tipo de SO:Windows 10,Plataforma de SO:Workstation,Versión de SO:10.0 | H3: 952018 MB | I3: Intel(R) Core(TM) i5-10210U CPU @ 1.60GHz | J3: HP 200 G4 22 All-in-One PC | K3: 8.016,82 MB | L3: Windows 10:10:0:0 | M3: Estación de trabajo | N3: Comite Quindio | O3: 11.11.2.1172 | P3: 6C02E07110F7 | Q3: Desactivado
A4: 8CTC8F3 | B4: 8CTC8F3-FNC-CUC | C4: CARMEN LUCIA VALLEJO | D4: 23/12/25 10:14:45 COT | E4: 192.168.1.7 | F4: Dell Inc. | G4: Tipo de SO:Windows 10,Plataforma de SO:Workstation,Versión de SO:10.0 | H4: 472477 MB | I4: 11th Gen Intel(R) Core(TM) i5-1135G7 @ 2.40GHz | J4: Inspiron 3501 | K4: 7.918,79 MB | L4: Windows 10:10:0:0 | M4: Estación de trabajo | N4: Comite Municipal Norte Santander | O4: 11.11.2.1172 | P4: C6DDC8150EB7 | Q4: Desactivado
A5: FL17XV3 | B5: ACORREDORG | C5: JMORENOCUN | D5: 23/12/25 12:55:53 COT | E5: ########## | F5: Dell Inc. | G5: Tipo de SO:Windows 11,Plataforma de SO:Workstation,Versión de SO:10.0 | H5: 485371 MB | I5: 13th Gen Intel(R) Core(TM) i5-13500T | J5: OptiPlex Micro 7010 | K5: 16.072,73 MB | L5: Windows 11:10:0:0 | M5: Estación de trabajo | N5: Comite Cundinamarca | O5: 11.11.2.1172 | P5: 7497797FC821 | Q5: Desactivado
A6: PF20P5RJ | B6: ADMI03 | C6: thoy | D6: 23/12/25 12:37:26 COT | E6: 192.168.40.67 | F6: LENOVO | G6: Tipo de SO:Windows 11,Plataforma de SO:Workstation,Versión de SO:10.0 | H6: 486878 MB | I6: Intel(R) Core(TM) i7-10510U CPU @ 1.80GHz | J6: 20UAS1TF00 | K6: 16.134,84 MB | L6: Windows 11:10:0:0 | M6: Estación de trabajo | N6: Buencafe_Fabrica | O6: 11.9.100.182 | P6: FCB3BC927FED | Q6: Desactivado
A7: PF3WLFF6 | B7: ADMI04 | C7: JGONZAL937 | D7: 23/12/25 12:39:43 COT | E7: 192.168.207.19 | F7: LENOVO | G7: Tipo de SO:Windows 11,Plataforma de SO:Workstation,Versión de SO:10.0 | H7: 486108 MB | I7: 11th Gen Intel(R) Core(TM) i7-1165G7 @ 2.80GHz | J7: 20TBS1PG00 | K7: 16.082,11 MB | L7: Windows 11:10:0:0 | M7: Estación de trabajo | N7: Buencafe_Fabrica | O7: 11.9.100.182 | P7: 88A4C2A218CD | Q7: Desactivado
A8: MP26TL4T | B8: ADMI05 | C8: SVALDER808,DTOBAR704 | D8: 23/12/25 12:43:03 COT | E8: 192.168.207.57 | F8: LENOVO | G8: Tipo de SO:Windows 11,Plataforma de SO:Workstation,Versión de SO:10.0 | H8: 487497 MB | I8: Intel(R) Core(TM) i7-10700T CPU @ 2.00GHz | J8: 11FJ00FWLS | K8: 16.195,00 MB | L8: Windows 11:10:0:0 | M8: Estación de trabajo | N8: Buencafe_Fabrica | O8: 11.9.100.182 | P8: E4A8DFA0BCC4 | Q8: Desactivado
A9: MJ0DNZ8P | B9: ADMI06 | C9: pgon | D9: 23/12/25 12:36:54 COT | E9: ########## | F9: LENOVO | G9: Tipo de SO:Windows 11,Plataforma de SO:Workstation,Versión de SO:10.0 | H9: 486991 MB | I9: Intel(R) Core(TM) i5-10600 CPU @ 3.30GHz | J9: 30DJS3A100 | K9: 16.091,41 MB | L9: Windows 11:10:0:0 | M9: Estación de trabajo | N9: Buencafe_Fabrica | O9: 11.9.100.182 | P9: 2CF05D51272D | Q9: Desactivado
A10: PF3WLLT5 | B10: ADMI07 | C10: LMZULUA473 | D10: 23/12/25 12:07:38 COT | E10: 192.168.40.94 | F10: LENOVO | G10: Tipo de SO:Windows 11,Plataforma de SO:Workstation,Versión de SO:10.0 | H10: 241920 MB | I10: 11th Gen Intel(R) Core(TM) i7-1165G7 @ 2.80GHz | J10: 20TBS10800 | K10: 16.082,11 MB | L10: Windows 11:10:0:0 | M10: Estación de trabajo | N10: Buencafe_Fabrica | O10: 11.9.100.182 | P10: C475ABC992B2 | Q10: Desactivado
A11: 7426BMO | B11: ADMI08 | C11: pinsdep | D11: 23/12/25 12:24:14 COT | E11: 192.168.41.59 | F11: LENOVO | G11: Tipo de SO:Windows 10,Plataforma de SO:Workstation,Versión de SO:10.0 | H11: 224126 MB | I11: Intel(R) Core(TM) i7-3667U CPU @ 2.00GHz | J11: 04Y1988 | K11: 8.010,84 MB | L11: Windows 10:10:0:0 | M11: Estación de trabajo | N11: Buencafe_Fabrica | O11: 11.9.100.182 | P11: 00B56D011CDB | Q11: Desactivado
A12: R90L7HJP | B12: ADMI09 | C12: SOLAYA948 | D12: 19/12/25 12:32:28 COT | E12: 192.168.40.63 | F12: LENOVO | G12: Tipo de SO:Windows 10,Plataforma de SO:Workstation,Versión de SO:10.0 | H12: 242920 MB | I12: Intel(R) Core(TM) i7-6500U CPU @ 2.50GHz | J12: 20FCS0P100 | K12: 8.063,61 MB | L12: Windows 10:10:0:0 | M12: Estación de trabajo | N12: Buencafe_Fabrica | O12: 11.9.100.182 | P12: 52FBA0888247 | Q12: Desactivado
... A39: NXHN2AL00S1160D7EE7600 | B39: ADMIN | C39: casan | D39: 16/10/25 10:39:43 COT | E39: 192.168.91.22 | F39: Acer | G39: Tipo de SO:Windows 11,Plataforma de SO:Workstation,Versión de SO:10.0 | H39: 243056 MB | I39: Intel(R) Core(TM) i3-10110U CPU @ 2.10GHz | J39: Aspire A515-54 | K39: 20.302,99 MB | L39: Windows 11:10:0:0 | M39: Estación de trabajo | N39: Comite Santander | O39: 11.11.2.1172 | P39: E02BE97DDA2A | Q39: Activada
A40: MP2ABAF | B40: ADMINISTRATIVOS | C40: Administrativo | D40: 22/12/25 13:21:19 COT | E40: 192.168.1.103 | F40: LENOVO | G40: Tipo de SO:Windows 7,Plataforma de SO:Workstation,Versión de SO:6.1 | H40: 114370 MB | I40: Intel(R) Core(TM) i5-3210M CPU @ 2.50GHz | J40: 32543XS | K40: 3.186,86 MB | L40: Windows 7:6:1:0 | M40: Estación de trabajo | N40: Comite Cundinamarca | P40: B888E3E76477 | Q40: Desactivado
A41: PF4F354Q | B41: ADMINOMINA | C41: auxnom2 | D41: 23/12/25 12:27:17 COT | E41: 192.168.207.55 | F41: LENOVO | G41: Tipo de SO:Windows 11,Plataforma de SO:Workstation,Versión de SO:10.0 | H41: 486108 MB | I41: 12th Gen Intel(R) Core(TM) i7-1255U | J41: 21E40023LM | K41: 16.059,65 MB | L41: Windows 11:10:0:0 | M41: Estación de trabajo | N41: Buencafe_Fabrica | O41: 11.9.100.182 | P41: 745D22118C92 | Q41: Desactivado
A42: 3872JS3 | B42: AGROFORESTERIA0 | C42: Dolly Garcia | D42: 21/12/25 12:55:59 COT | E42: 192.168.101.13 | F42: Dell Inc. | G42: Tipo de SO:Windows 11,Plataforma de SO:Workstation,Versión de SO:10.0 | H42: 952979 MB | I42: 13th Gen Intel(R) Core(TM) i5-1335U | J42: Latitude 3440 | K42: 7.876,70 MB | L42: Windows 11:10:0:0 | M42: Estación de trabajo | N42: Comite Nariño | O42: 11.11.2.1172 | P42: 10F60A8D4960 | Q42: Desactivado
A43: 2PH8793 | B43: AGROKMORENO | C43: N/A | D43: 18/12/25 14:38:48 COT | E43: 192.168.20.141 | F43: Dell Inc. | G43: Tipo de SO:Windows 11,Plataforma de SO:Workstation,Versión de SO:10.0 | H43: 2393052 MB | I43: Intel(R) Core(TM) i7-10750H CPU @ 2.60GHz | J43: Precision 3551 | K43: 16.017,86 MB | L43: Windows 11:10:0:0 | M43: Estación de trabajo | N43: Comite Valle | O43: 11.11.2.1172 | P43: 18473DE9C155 | Q43: Desactivado
A44: MJ0M0CLL | B44: AGUADAS01 | C44: Alm. Cafe Aguadas01 | D44: 23/12/25 12:14:14 COT | E44: ########## | F44: LENOVO | G44: Tipo de SO:Windows 11,Plataforma de SO:Workstation,Versión de SO:10.0 | H44: 486107 MB | I44: 13th Gen Intel(R) Core(TM) i5-13400T | J44: 12E4S8PL00 | K44: 16.023,16 MB | L44: Windows 11:10:0:0 | M44: Estación de trabajo | N44: Comite Caldas | O44: 11.11.2.1172 | P44: 250410000000000 | Q44: Desactivado
A45: MP15GMRC | B45: AGUADAS02 | C45: Alm.Cafe Aguadas2 | D45: 23/12/25 12:20:46 COT | E45: 10.11.1.14 | F45: LENOVO | G45: Tipo de SO:Windows 10,Plataforma de SO:Workstation,Versión de SO:10.0 | H45: 921258 MB | I45: Intel(R) Core(TM) i5-7400T CPU @ 2.40GHz | J45: F0CD00GNLD | K45: 8.103,46 MB | L45: Windows 10:10:0:0 | M45: Estación de trabajo | N45: Comite Caldas | O45: 11.11.2.1172 | P45: FC45967BE51B | Q45: Desactivado
A46: BRC4064EPF | B46: alarmlnx | C46: N/A | D46: 28/07/25 11:08:21 COT | E46: 192.168.140.64 | F46: HP | G46: Tipo de SO:Linux,Plataforma de SO:Workstation,Versión de SO:2.6,Versión de Service Pack de SO:32-504.el6.x86_64 | H46: 4500801 MB | I46: Intel(R) Xeon(R) CPU E3-1240 v3 @ 3.40GHz | J46: ProLiant ML310e Gen8 v2 | K46: 7.703,11 MB | L46: LINUX | M46: Estación de trabajo | N46: SERVIDORES | P46: C4346B2111AC | Q46: Desactivado
A47: BRC4064ELW | B47: alboglnx | C47: N/A | D47: 17/09/25 16:26:02 COT | E47: 192.168.24.215 | F47: HP | G47: Tipo de SO:Linux,Plataforma de SO:Workstation,Versión de SO:2.6,Versión de Service Pack de SO:32-504.el6.x86_64 | H47: 1881159 MB | I47: Intel(R) Xeon(R) CPU E3-1240 v3 @ 3.40GHz | J47: ProLiant ML310e Gen8 v2 | K47: 7.956,11 MB | L47: LINUX | M47: Estación de trabajo | N47: Almacafe Bogota-Soacha | P47: E0071B1B7FEC | Q47: Desactivado
A48: BRC4064ELN | B48: albuclnx | C48: N/A | D48: 1/07/25 10:27:45 COT | E48: 192.168.161.64 | F48: HP | G48: Tipo de SO:Linux,Plataforma de SO:Workstation,Versión de SO:2.6,Versión de Service Pack de SO:32-504.el6.x86_64 | H48: 4027072 MB | I48: Intel(R) Xeon(R) CPU E3-1240 v3 @ 3.40GHz | J48: ProLiant ML310e Gen8 v2 | K48: 7.703,11 MB | L48: LINUX | M48: Estación de trabajo | N48: Linux Almacafe | P48: A01D4897061C | Q48: Desactivado
A49: BRC4064EN5 | B49: albuelnx | C49: root | D49: 3/09/25 7:18:40 COT | E49: 192.168.30.64 | F49: HP | G49: Tipo de SO:Linux,Plataforma de SO:Workstation,Versión de SO:2.6,Versión de Service Pack de SO:32-754.el6.x86_64 | H49: 4867689 MB | I49: Intel(R) Xeon(R) CPU E3-1240 v3 @ 3.40GHz | J49: ProLiant ML310e Gen8 v2 | K49: 7.702,31 MB | L49: LINUX | M49: Estación de trabajo | N49: Almacafe Buenaventura | P49: A01D489704BC | Q49: Desactivado
A50: BRC4064EP9 | B50: albuglnx | C50: N/A | D50: 8/08/25 13:31:18 COT | E50: 192.168.155.64 | F50: HP | G50: Tipo de SO:Linux,Plataforma de SO:Workstation,Versión de SO:2.6,Versión de Service Pack de SO:32-504.el6.x86_64 | H50: 4178262 MB | I50: Intel(R) Xeon(R) CPU E3-1240 v3 @ 3.40GHz | J50: ProLiant ML310e Gen8 v2 | K50: 7.703,11 MB | L50: LINUX | M50: Estación de trabajo | N50: Almacafe Buga | P50: A01D489705B4 | Q50: Desactivado
A51: BRC4064ERC | B51: alcarlnx | C51: N/A | D51: 29/08/25 14:17:45 COT | E51: 192.168.35.64 | F51: HP | G51: Tipo de SO:Linux,Plataforma de SO:Workstation,Versión de SO:2.6,Versión de Service Pack de SO:32-754.el6.x86_64 | H51: 4546162 MB | I51: Intel(R) Xeon(R) CPU E3-1240 v3 @ 3.40GHz | J51: ProLiant ML310e Gen8 v2 | K51: 7.702,31 MB | L51: LINUX | M51: Estación de trabajo | N51: Almacafe Cartagena | P51: A01D48970294 | Q51: Desactivado
A52: BRC4064EMH | B52: alcuclnx | C52: N/A | D52: 23/07/25 14:25:02 COT | E52: 192.168.165.64 | F52: HP | G52: Tipo de SO:Linux,Plataforma de SO:Workstation,Versión de SO:2.6,Versión de Service Pack de SO:32-754.el6.x86_64 | H52: 3978691 MB | I52: Intel(R) Xeon(R) CPU E3-1240 v3 @ 3.40GHz | J52: ProLiant ML310e Gen8 v2 | K52: 7.702,31 MB | L52: LINUX | M52: Estación de trabajo | N52: Almacafe Cucuta | P52: A01D48971600 | Q52: Desactivado
A53: PF3YE3E6 | B53: ALEXANDERRANGEL | C53: Alexander Rangel | D53: 23/12/25 12:42:57 COT | E53: 192.168.90.15 | F53: LENOVO | G53: Tipo de SO:Windows 11,Plataforma de SO:Workstation,Versión de SO:10.0 | H53: 974483 MB | I53: 11th Gen Intel(R) Core(TM) i7-11800H @ 2.30GHz | J53: 21AAS06E00 | K53: 16.103,05 MB | L53: Windows 11:10:0:0 | M53: Estación de trabajo | N53: Directory | P53: 6C2408E193D5 | Q53: Desactivado
A54: 5L27XV3 | B54: ALEXBTENAPAYACA | C54: MMARCHCUN | D54: 18/12/25 16:33:27 COT | E54: ########## | F54: Dell Inc. | G54: Tipo de SO:Windows 11,Plataforma de SO:Workstation,Versión de SO:10.0 | H54: 485371 MB | I54: 13th Gen Intel(R) Core(TM) i5-13500T | J54: OptiPlex Micro 7010 | K54: 16.072,73 MB | L54: Windows 11:10:0:0 | M54: Estación de trabajo | N54: Comite Cundinamarca | O54: 11.11.2.1172 | P54: 7497797FBB97 | Q54: Desactivado
A55: BRC4064ELP | B55: alibalnx | C55: N/A | D55: 5/08/25 14:19:22 COT | E55: 192.168.145.64 | F55: HP | G55: Tipo de SO:Linux,Plataforma de SO:Workstation,Versión de SO:2.6,Versión de Service Pack de SO:32-504.el6.x86_64 | H55: 4480642 MB | I55: Intel(R) Xeon(R) CPU E3-1240 v3 @ 3.40GHz | J55: ProLiant ML310e Gen8 v2 | K55: 7.703,11 MB | L55: LINUX | M55: Estación de trabajo | N55: SERVIDORES | P55: A0481CD6F3C4 | Q55: Desactivado
A56: BRC4064EN4 | B56: almedlnx | C56: N/A | D56: 4/09/25 9:28:13 COT | E56: 192.168.126.64 | F56: HP | G56: Tipo de SO:Linux,Plataforma de SO:Workstation,Versión de SO:2.6,Versión de Service Pack de SO:32-754.el6.x86_64 | H56: 4752783 MB | I56: Intel(R) Xeon(R) CPU E3-1240 v3 @ 3.40GHz | J56: ProLiant ML310e Gen8 v2 | K56: 7.702,31 MB | L56: LINUX | M56: Estación de trabajo | N56: Linux Almacafe | P56: A01D48971778 | Q56: Desactivado
A57: BRC4064ERB | B57: almmanizaleslnx | C57: N/A | D57: 23/07/25 14:45:36 COT | E57: 192.168.130.11 | F57: HP | G57: Tipo de SO:Linux,Plataforma de SO:Workstation,Versión de SO:2.6,Versión de Service Pack de SO:32-504.el6.x86_64 | H57: 5549943 MB | I57: Intel(R) Xeon(R) CPU E3-1240 v3 @ 3.40GHz | J57: ProLiant ML310e Gen8 v2 | K57: 7.703,11 MB | L57: LINUX | M57: Estación de trabajo | N57: SERVIDORES | P57: A01D48971688 | Q57: Desactivado
A58: BRC4064ELY | B58: alneilnx | C58: N/A | D58: 6/08/25 16:25:55 COT | E58: 192.168.150.64 | F58: HP | G58: Tipo de SO:Linux,Plataforma de SO:Workstation,Versión de SO:2.6,Versión de Service Pack de SO:32-754.el6.x86_64 | H58: 5629194 MB | I58: Intel(R) Xeon(R) CPU E3-1240 v3 @ 3.40GHz | J58: ProLiant ML310e Gen8 v2 | K58: 7.831,31 MB | L58: LINUX | M58: Estación de trabajo | N58: SERVIDORES | P58: 40A8F0C7AE74 | Q58: Desactivado
A59: BRC4064EN0 | B59: alpaslnx | C59: N/A | D59: 6/08/25 9:24:09 COT | E59: 192.168.175.64 | F59: HP | G59: Tipo de SO:Linux,Plataforma de SO:Workstation,Versión de SO:2.6,Versión de Service Pack de SO:32-754.el6.x86_64 | H59: 4842724 MB | I59: Intel(R) Xeon(R) CPU E3-1240 v3 @ 3.40GHz | J59: ProLiant ML310e Gen8 v2 | K59: 7.955,30 MB | L59: LINUX | M59: Estación de trabajo | N59: Linux Almacafe | P59: A01D489717EC | Q59: Desactivado
A60: BRC4064ERA | B60: ALPERLNX | C60: N/A | D60: 15/08/25 13:37:09 COT | E60: 192.168.135.64 | F60: HP | G60: Tipo de SO:Linux,Plataforma de SO:Workstation,Versión de SO:2.6,Versión de Service Pack de SO:32-754.el6.x86_64 | H60: 4034128 MB | I60: Intel(R) Xeon(R) CPU E3-1240 v3 @ 3.40GHz | J60: ProLiant ML310e Gen8 v2 | K60: 7.702,31 MB | L60: LINUX | M60: Estación de trabajo | N60: Linux Almacafe | P60: A0481CD6F3FC | Q60: Desactivado
A61: BRC4064EN8 | B61: alpoplnx | C61: N/A | D61: 4/09/25 10:55:20 COT | E61: 192.168.170.64 | F61: HP | G61: Tipo de SO:Linux,Plataforma de SO:Workstation,Versión de SO:2.6,Versión de Service Pack de SO:32-754.el6.x86_64 | H61: 4077469 MB | I61: Intel(R) Xeon(R) CPU E3-1240 v3 @ 3.40GHz | J61: ProLiant ML310e Gen8 v2 | K61: 7.702,31 MB | L61: LINUX | M61: Estación de trabajo | N61: Linux Almacafe | P61: A01D489705AC | Q61: Desactivado
A62: BRC4064ELL | B62: alsanlnx | C62: N/A | D62: 23/07/25 14:42:54 COT | E62: 192.168.180.64 | F62: HP | G62: Tipo de SO:Linux,Plataforma de SO:Workstation,Versión de SO:2.6,Versión de Service Pack de SO:32-754.el6.x86_64 | H62: 4833162 MB | I62: Intel(R) Xeon(R) CPU E3-1240 v3 @ 3.40GHz | J62: ProLiant ML310e Gen8 v2 | K62: 7.702,31 MB | L62: LINUX | M62: Estación de trabajo | N62: Linux Almacafe | P62: A0481CD6FB0C | Q62: Desactivado
A63: 8CN12500BV | B63: ANALISTAFINANCI | C63: User | D63: 19/12/25 8:53:10 COT | E63: 192.168.90.94 | F63: HP | G63: Tipo de SO:Windows 10,Plataforma de SO:Workstation,Versión de SO:10.0 | H63: 476298 MB | I63: Intel(R) Core(TM) i5-10500 CPU @ 3.10GHz | J63: HP ProOne 400 G6 20 All-in-One PC | K63: 7.967,22 MB | L63: Windows 10:10:0:0 | M63: Estación de trabajo | N63: Comite Santander | O63: 11.11.2.1172 | P63: 489EBDD59EDA | Q63: Desactivado
A64: MJ04PGVN | B64: ANALIZADOR | C64: analizador | D64: 23/12/25 12:16:33 COT | E64: 192.168.41.74 | F64: LENOVO | G64: Tipo de SO:Windows 10,Plataforma de SO:Workstation,Versión de SO:10.0 | H64: 952591 MB | I64: Intel(R) Xeon(R) CPU E3-1225 v5 @ 3.30GHz | J64: 30ASA0DN00 | K64: 8.082,21 MB | L64: Windows 10:10:0:0 | M64: Estación de trabajo | N64: Buencafe_Fabrica | O64: 11.9.100.182 | P64: 4CCC6A741023 | Q64: Desactivado
A65: NXVU2AL00123210F8B3400 | B65: ANDREAJFUYA | C65: N/A | D65: 17/12/25 17:29:52 COT | E65: 192.168.100.50 | F65: Acer | G65: Tipo de SO:Windows 11,Plataforma de SO:Workstation,Versión de SO:10.0 | H65: 487083 MB | I65: 11th Gen Intel(R) Core(TM) i5-1155G7 @ 2.50GHz | J65: TravelMate V15-51 | K65: 20.259,30 MB | L65: Windows 11:10:0:0 | M65: Estación de trabajo | N65: Comite Santander | O65: 11.11.2.1172 | P65: E0D045F47FF9 | Q65: Desactivado
A66: NXVU2AL00123300AEB3400 | B66: ANGELOGUERRERO | C66: giovany guerrero | D66: 18/12/25 16:29:18 COT | E66: 192.168.1.67 | F66: Acer | G66: Tipo de SO:Windows 11,Plataforma de SO:Workstation,Versión de SO:10.0 | H66: 487083 MB | I66: 11th Gen Intel(R) Core(TM) i5-1155G7 @ 2.50GHz | J66: TravelMate V15-51 | K66: 20.259,30 MB | L66: Windows 11:10:0:0 | M66: Estación de trabajo | N66: Comite Cauca | O66: 11.11.2.1172 | P66: E0D045F72DB7 | Q66: Desactivado
A67: MP15GMRT | B67: ANSERMA01 | C67: Comite | D67: 23/12/25 12:42:18 COT | E67: 10.11.0.111 | F67: LENOVO | G67: Tipo de SO:Windows 10,Plataforma de SO:Workstation,Versión de SO:10.0 | H67: 921258 MB | I67: Intel(R) Core(TM) i5-7400T CPU @ 2.40GHz | J67: F0CD00GNLD | K67: 8.103,46 MB | L67: Windows 10:10:0:0 | M67: Estación de trabajo | N67: Comite Caldas | O67: 11.11.2.1172 | P67: FC45967B9EDB | Q67: Desactivado
A68: NXVU2AL001233004FA3400 | B68: ANTONIODURAN | C68: antonio duran | D68: 22/12/25 17:53:47 COT | E68: 192.168.1.36 | F68: Acer | G68: Tipo de SO:Windows 11,Plataforma de SO:Workstation,Versión de SO:10.0 | H68: 487083 MB | I68: 11th Gen Intel(R) Core(TM) i5-1155G7 @ 2.50GHz | J68: TravelMate V15-51 | K68: 20.259,30 MB | L68: Windows 11:10:0:0 | M68: Estación de trabajo | N68: Comite Santander | O68: 11.11.2.1172 | P68: E0D045F47C48 | Q68: Desactivado
A69: 7M17XV3 | B69: ARACATACA | C69: Administrador1 | D69: 18/12/25 16:40:35 COT | E69: 192.168.0.104 | F69: Dell Inc. | G69: Tipo de SO:Windows 11,Plataforma de SO:Workstation,Versión de SO:10.0 | H69: 485371 MB | I69: 13th Gen Intel(R) Core(TM) i5-13500T | J69: OptiPlex Micro 7010 | K69: 16.072,73 MB | L69: Windows 11:10:0:0 | M69: Estación de trabajo | N69: Comite Magdalena | O69: 11.11.2.1172 | P69: 7497797FCA57 | Q69: Desactivado
A70: YL00DNB5 | B70: ARANZAZU01 | C70: Comite | D70: 20/12/25 15:29:14 COT | E70: 10.11.0.199 | F70: LENOVO | G70: Tipo de SO:Windows 10,Plataforma de SO:Workstation,Versión de SO:10.0 | H70: 921258 MB | I70: Intel(R) Core(TM) i5-8400 CPU @ 2.80GHz | J70: 10TY001DLS | K70: 8.076,28 MB | L70: Windows 10:10:0:0 | M70: Estación de trabajo | N70: Comite Caldas | O70: 11.11.2.1172 | P70: 1CA0B8773ABE | Q70: Desactivado
A71: YL00DN0L | B71: ARAUCA01 | C71: Alm. Cafe Arauca | D71: 23/12/25 12:55:43 COT | E71: ########## | F71: LENOVO | G71: Tipo de SO:Windows 10,Plataforma de SO:Workstation,Versión de SO:10.0 | H71: 476298 MB | I71: Intel(R) Core(TM) i5-8400 CPU @ 2.80GHz | J71: 10TY001DLS | K71: 8.079,96 MB | L71: Windows 10:10:0:0 | M71: Estación de trabajo | N71: Comite Caldas | O71: 11.11.2.1172 | P71: 250410000000000 | Q71: Desactivado
A72: 95DZ942 | B72: ARBOLEDA01 | C72: Comite | D72: 23/12/25 12:18:44 COT | E72: 192.168.218.71 | F72: Dell Inc. | G72: Tipo de SO:Windows 10,Plataforma de SO:Workstation,Versión de SO:10.0 | H72: 476342 MB | I72: Intel(R) Core(TM) i5-4590 CPU @ 3.30GHz | J72: OptiPlex 3020 | K72: 8.110,76 MB | L72: Windows 10:10:0:0 | M72: Estación de trabajo | N72: Comite Caldas | O72: 11.11.2.1172 | P72: 250410000000000 | Q72: Desactivado
A73: PK0C0PC | B73: AUDIOMETRO | C73: audiometro | D73: 22/12/25 16:43:49 COT | E73: 192.168.41.214 | F73: LENOVO | G73: Tipo de SO:Windows 10,Plataforma de SO:Workstation,Versión de SO:10.0 | H73: 223708 MB | I73: Intel(R) Core(TM) i7-3667U CPU @ 2.00GHz | J73: 3460AWS | K73: 8.010,86 MB | L73: Windows 10:10:0:0 | M73: Estación de trabajo | N73: Directory | P73: 843A4BCD9850 | Q73: Desactivado
A74: MJ0M0CQ6 | B74: BELALCAZAR01 | C74: Alm.Cafe Viterbo | D74: 23/12/25 12:12:34 COT | E74: 192.168.217.1 | F74: LENOVO | G74: Tipo de SO:Windows 11,Plataforma de SO:Workstation,Versión de SO:10.0 | H74: 486107 MB | I74: 13th Gen Intel(R) Core(TM) i5-13400T | J74: 12E4S8PL00 | K74: 16.023,07 MB | L74: Windows 11:10:0:0 | M74: Estación de trabajo | N74: Comite Caldas | O74: 11.11.2.1172 | P74: 250410000000000 | Q74: Desactivado
A75: MZ00RXX9 | B75: BOLIVIA01 | C75: Alm. Cafe Bolivia | D75: 23/12/25 12:02:09 COT | E75: 10.11.3.5 | F75: LENOVO | G75: Tipo de SO:Windows 11,Plataforma de SO:Workstation,Versión de SO:10.0 | H75: 486107 MB | I75: 13th Gen Intel(R) Core(TM) i5-13400T | J75: 12E4S8PL00 | K75: 16.015,09 MB | L75: Windows 11:10:0:0 | M75: Estación de trabajo | N75: Directory | P75: C4C6E6E5C2B2 | Q75: Desactivado
A76: MJ0L4328 | B76: BORSIG-123 | C76: refri1 | D76: 23/12/25 12:50:41 COT | E76: ########## | F76: LENOVO | G76: Tipo de SO:Windows 10,Plataforma de SO:Workstation,Versión de SO:10.0 | H76: 487723 MB | I76: 12th Gen Intel(R) Core(TM) i7-12700 | J76: 30FNSDMD00 | K76: 32.442,93 MB | L76: Windows 10:10:0:0 | M76: Estación de trabajo | N76: Buencafe_Fabrica | P76: 047C1699F09F | Q76: Desactivado
A77: J3N0CV038448107 | B77: BRAYANARIZA | C77: Brayan Ariza | D77: 17/12/25 16:24:00 COT | E77: 192.168.100.67 | F77: ASUSTeK COMPUTER INC. | G77: Tipo de SO:Windows 10,Plataforma de SO:Workstation,Versión de SO:10.0 | H77: 649157 MB | I77: Intel(R) Core(TM) i7-7500U CPU @ 2.70GHz | J77: X442UR | K77: 20.361,29 MB | L77: Windows 10:10:0:0 | M77: Estación de trabajo | N77: Directory | P77: 80C5F2795EC3 | Q77: Desactivado
A78: 5CG1488NNC | B78: BRAYAN-LEONARDO | C78: PC | D78: 23/12/25 12:43:35 COT | E78: 10.30.171.17 | F78: HP | G78: Tipo de SO:Windows 11,Plataforma de SO:Workstation,Versión de SO:10.0 | H78: 475129 MB | I78: 11th Gen Intel(R) Core(TM) i5-1135G7 @ 2.40GHz | J78: HP 240 G8 Notebook PC | K78: 7.859,27 MB | L78: Windows 11:10:0:0 | M78: Estación de trabajo | N78: Comite Santander | O78: 11.11.2.1172 | P78: AC74B14CB341 | Q78: Desactivado
A79: PF131G99 | B79: BYS02 | C79: secmat | D79: 23/12/25 12:39:57 COT | E79: ########## | F79: LENOVO | G79: Tipo de SO:Windows 11,Plataforma de SO:Workstation,Versión de SO:10.0 | H79: 242620 MB | I79: Intel(R) Core(TM) i7-8565U CPU @ 1.80GHz | J79: 20QES40F00 | K79: 16.156,29 MB | L79: Windows 11:10:0:0 | M79: Estación de trabajo | N79: Buencafe_Fabrica | O79: 11.9.100.182 | P79: 98FA9BD386C4 | Q79: Desactivado
A80: MJMVLZP | B80: BYS04 | C80: almacen2 | D80: 6/05/25 16:34:04 COT | E80: 192.168.41.184 | F80: LENOVO | G80: Tipo de SO:Windows 10,Plataforma de SO:Workstation,Versión de SO:10.0 | H80: 476292 MB | I80: Intel(R) Xeon(R) CPU E31225 @ 3.10GHz | J80: 782479S | K80: 12.112,33 MB | L80: Windows 10:10:0:0 | M80: Estación de trabajo | N80: Buencafe_Fabrica | O80: 11.9.100.182 | P80: 4437E6A0A9E6 | Q80: Desactivado
A81: MJ0C3R0V | B81: BYS06 | C81: almacen3 | D81: 23/12/25 12:52:48 COT | E81: 192.168.41.185 | F81: LENOVO | G81: Tipo de SO:Windows 11,Plataforma de SO:Workstation,Versión de SO:10.0 | H81: 243298 MB | I81: Intel(R) Xeon(R) E-2224G CPU @ 3.50GHz | J81: 30CYS08Y00 | K81: 16.224,09 MB | L81: Windows 11:10:0:0 | M81: Estación de trabajo | N81: Buencafe_Fabrica | O81: 11.9.100.182 | P81: 00D861F3304C | Q81: Desactivado
A82: MJ0303JN | B82: BYS07 | C82: almacen1 | D82: 23/12/25 12:23:31 COT | E82: 192.168.41.189 | F82: LENOVO | G82: Tipo de SO:Windows 10,Plataforma de SO:Workstation,Versión de SO:10.0 | H82: 214485 MB | I82: Intel(R) Xeon(R) CPU E3-1226 v3 @ 3.30GHz | J82: 30AGA00X00 | K82: 8.081,79 MB | L82: Windows 10:10:0:0 | M82: Estación de trabajo | N82: Buencafe_Fabrica | O82: 11.9.100.182 | P82: 6C0B844341AE | Q82: Desactivado
A83: MJ01LJ6V | B83: BYS08 | C83: reservas | D83: 23/12/25 12:35:24 COT | E83: 192.168.40.199 | F83: LENOVO | G83: Tipo de SO:Windows 10,Plataforma de SO:Workstation,Versión de SO:10.0 | H83: 939011 MB | I83: Intel(R) Xeon(R) CPU E3-1226 v3 @ 3.30GHz | J83: 30AJA04700 | K83: 8.081,51 MB | L83: Windows 10:10:0:0 | M83: Estación de trabajo | N83: Buencafe_Fabrica | O83: 11.9.100.182 | P83: 4439C454DD39 | Q83: Desactivado
A84: MJ01LJ6Y | B84: BYS09 | C84: secalm | D84: 22/12/25 21:59:15 COT | E84: 192.168.41.179 | F84: LENOVO | G84: Tipo de SO:Windows 10,Plataforma de SO:Workstation,Versión de SO:10.0 | H84: 939011 MB | I84: Intel(R) Xeon(R) CPU E3-1226 v3 @ 3.30GHz | J84: 30AJA04700 | K84: 8.081,91 MB | L84: Windows 10:10:0:0 | M84: Estación de trabajo | N84: Buencafe_Fabrica | O84: 11.9.100.182 | P84: 4439C454CDC8 | Q84: Desactivado
A85: PF4F12DX | B85: BYS10 | C85: NEON | D85: 23/12/25 12:11:44 COT | E85: ########## | F85: LENOVO | G85: Tipo de SO:Windows 11,Plataforma de SO:Workstation,Versión de SO:10.0 | H85: 486108 MB | I85: 12th Gen Intel(R) Core(TM) i7-1255U | J85: 21E40023LM | K85: 16.059,65 MB | L85: Windows 11:10:0:0 | M85: Estación de trabajo | N85: Excepcion USB | O85: 11.9.100.182 | P85: 745D2211907A | Q85: Desactivado
A86: MJ04DY4K | B86: BYS11 | C86: almacen2 | D86: 23/12/25 12:00:53 COT | E86: 192.168.41.187 | F86: LENOVO | G86: Tipo de SO:Windows 11,Plataforma de SO:Workstation,Versión de SO:10.0 | H86: 476051 MB | I86: Intel(R) Xeon(R) CPU E3-1225 v5 @ 3.30GHz | J86: 30ASA0DN00 | K86: 8.085,87 MB | L86: Windows 11:10:0:0 | M86: Estación de trabajo | N86: Buencafe_Fabrica | O86: 11.11.2.1172 | P86: 4CCC6A52A2FC | Q86: Desactivado
A87: MJ01LJ72 | B87: BYS16 | C87: b1empaque | D87: 23/12/25 12:46:09 COT | E87: 192.168.40.249 | F87: LENOVO | G87: Tipo de SO:Windows 10,Plataforma de SO:Workstation,Versión de SO:10.0 | H87: 137769 MB | I87: Intel(R) Xeon(R) CPU E3-1226 v3 @ 3.30GHz | J87: 30AJA04700 | K87: 16.273,51 MB | L87: Windows 10:10:0:0 | M87: Estación de trabajo | N87: Buencafe_Fabrica | O87: 11.9.100.182 | P87: 6C0B849883D1 | Q87: Desactivado
A88: R90H6DW5 | B88: BYS17 | C88: b1empaque | D88: 23/12/25 12:52:04 COT | E88: 192.168.40.247 | F88: LENOVO | G88: Tipo de SO:Windows 10,Plataforma de SO:Workstation,Versión de SO:10.0 | H88: 222739 MB | I88: Intel(R) Core(TM) i7-5500U CPU @ 2.40GHz | J88: 20BTS0BP00 | K88: 8.066,41 MB | L88: Windows 10:10:0:0 | M88: Estación de trabajo | N88: Buencafe_Fabrica | O88: 11.9.100.182 | P88: 94659C268CFC | Q88: Desactivado
A89: PF3WNYFY | B89: BYS19 | C89: AGIRALD140 | D89: 22/12/25 11:03:05 COT | E89: 192.168.80.234 | F89: LENOVO | G89: Tipo de SO:Windows 11,Plataforma de SO:Workstation,Versión de SO:10.0 | H89: 241920 MB | I89: 11th Gen Intel(R) Core(TM) i7-1165G7 @ 2.80GHz | J89: 20TBS10800 | K89: 16.082,11 MB | L89: Windows 11:10:0:0 | M89: Estación de trabajo | N89: Buencafe_Fabrica | O89: 11.9.100.182 | P89: C475ABD01ABA | Q89: Desactivado
... A112: MJ0C3R1E | B112: CALDERA5Y6 | C112: calderas | D112: 23/12/25 12:26:47 COT | E112: ########## | F112: LENOVO | G112: Tipo de SO:Windows 10,Plataforma de SO:Workstation,Versión de SO:10.0 | H112: 1196660 MB | I112: Intel(R) Xeon(R) E-2224G CPU @ 3.50GHz | J112: 30CYS08Y00 | K112: 16.224,09 MB | L112: Windows 10:10:0:0 | M112: Estación de trabajo | N112: Buencafe_Fabrica | O112: 11.9.100.182 | P112: 00D861F32D6E | Q112: Desactivado
A113: MJ06P74W | B113: CALDERAS3Y4R | C113: calderas | D113: 23/12/25 12:39:24 COT | E113: ########## | F113: LENOVO | G113: Tipo de SO:Windows 10,Plataforma de SO:Workstation,Versión de SO:10.0 | H113: 952590 MB | I113: Intel(R) Xeon(R) CPU E3-1225 v6 @ 3.30GHz | J113: 30BGA1HE00 | K113: 16.312,77 MB | L113: Windows 10:10:0:0 | M113: Estación de trabajo | N113: Buencafe_Fabrica | P113: 309C2352EF31 | Q113: Desactivado
A114: PF3Q60AQ | B114: CALI01 | C114: MNARANJ401 | D114: 20/12/25 23:17:28 COT | E114: 192.168.1.10 | F114: LENOVO | G114: Tipo de SO:Windows 11,Plataforma de SO:Workstation,Versión de SO:10.0 | H114: 975414 MB | I114: 11th Gen Intel(R) Core(TM) i7-1165G7 @ 2.80GHz | J114: 20XXSBD700 | K114: 16.103,05 MB | L114: Windows 11:10:0:0 | M114: Estación de trabajo | N114: Buencafe_Fabrica | O114: 11.9.100.182 | P114: 88D82E535FED | Q114: Desactivado
A115: PF2VHC9Y | B115: CALI03 | C115: bacteriologia | D115: 23/12/25 7:10:52 COT | E115: 192.168.40.188 | F115: LENOVO | G115: Tipo de SO:Windows 11,Plataforma de SO:Workstation,Versión de SO:10.0 | H115: 242715 MB | I115: Intel(R) Core(TM) i7-10510U CPU @ 1.80GHz | J115: 20UAS64A00 | K115: 16.134,84 MB | L115: Windows 11:10:0:0 | M115: Estación de trabajo | N115: Buencafe_Fabrica | O115: 11.9.100.182 | P115: F09E4AEBF67C | Q115: Desactivado
A116: MJOGSHVE | B116: CALI05 | C116: seccal | D116: 23/12/25 11:28:57 COT | E116: 192.168.41.164 | F116: LENOVO | G116: Tipo de SO:Windows 11,Plataforma de SO:Workstation,Versión de SO:10.0 | H116: 242920 MB | I116: Intel(R) Core(TM) i7-10700 CPU @ 2.90GHz | J116: 11CES2P400 | K116: 16.056,95 MB | L116: Windows 11:10:0:0 | M116: Estación de trabajo | N116: Buencafe_Fabrica | O116: 11.9.100.182 | P116: 083A886D66BB | Q116: Desactivado
A117: PF4F3BWC | B117: CALI07 | C117: aval | D117: 23/12/25 12:22:27 COT | E117: 192.168.40.65 | F117: LENOVO | G117: Tipo de SO:Windows 11,Plataforma de SO:Workstation,Versión de SO:10.0 | H117: 486108 MB | I117: 12th Gen Intel(R) Core(TM) i7-1255U | J117: 21E40023LM | K117: 16.059,65 MB | L117: Windows 11:10:0:0 | M117: Estación de trabajo | N117: Buencafe_Fabrica | O117: 11.9.100.182 | P117: B0DCEF8BEDE5 | Q117: Desactivado
A118: MP26TJPZ | B118: CALI08 | C118: labaguas | D118: 23/12/25 12:55:46 COT | E118: 192.168.207.53 | F118: LENOVO | G118: Tipo de SO:Windows 11,Plataforma de SO:Workstation,Versión de SO:10.0 | H118: 487108 MB | I118: Intel(R) Core(TM) i7-10700T CPU @ 2.00GHz | J118: 11FJ00FWLS | K118: 16.195,00 MB | L118: Windows 11:10:0:0 | M118: Estación de trabajo | N118: Buencafe_Fabrica | O118: 11.9.100.182 | P118: E4A8DFA0B7EF | Q118: Desactivado
A119: R90RG1LU | B119: CALI09 | C119: GQUI | D119: 23/12/25 12:06:19 COT | E119: 192.168.40.84 | F119: LENOVO | G119: Tipo de SO:Windows 11,Plataforma de SO:Workstation,Versión de SO:10.0 | H119: 487108 MB | I119: Intel(R) Core(TM) i7-8550U CPU @ 1.80GHz | J119: 20LEA01100 | K119: 16.234,49 MB | L119: Windows 11:10:0:0 | M119: Estación de trabajo | N119: Buencafe_Fabrica | O119: 11.9.100.182 | P119: 34E12D0F8B97 | Q119: Desactivado
A120: MJ04DY4R | B120: CALI10 | C120: AnalistaPE | D120: 23/12/25 12:38:35 COT | E120: 192.168.41.165 | F120: LENOVO | G120: Tipo de SO:Windows 10,Plataforma de SO:Workstation,Versión de SO:10.0 | H120: 952591 MB | I120: Intel(R) Xeon(R) CPU E3-1225 v5 @ 3.30GHz | J120: 30ASA0DN00 | K120: 16.277,87 MB | L120: Windows 10:10:0:0 | M120: Estación de trabajo | N120: Buencafe_Fabrica | O120: 11.9.100.182 | P120: 4CCC6A52A1FF | Q120: Desactivado
A121: MJ03X4NR | B121: CALI11 | C121: AnalistaME | D121: 23/12/25 12:38:27 COT | E121: 192.168.41.167 | F121: LENOVO | G121: Tipo de SO:Windows 10,Plataforma de SO:Workstation,Versión de SO:10.0 | H121: 303967 MB | I121: Intel(R) Xeon(R) CPU E3-1225 v5 @ 3.30GHz | J121: 30ASA0DN00 | K121: 8.082,21 MB | L121: Windows 10:10:0:0 | M121: Estación de trabajo | N121: Buencafe_Fabrica | O121: 11.9.100.182 | P121: 4CCC6A19D9DE | Q121: Desactivado
A122: PF15VVL7 | B122: CALI13 | C122: AFRANCO243 | D122: 17/06/25 0:33:48 COT | E122: 192.168.40.185 | F122: LENOVO | G122: Tipo de SO:Windows 11,Plataforma de SO:Workstation,Versión de SO:10.0 | H122: 242064 MB | I122: Intel(R) Core(TM) i7-8550U CPU @ 1.80GHz | J122: 20KGA03400 | K122: 8.041,94 MB | L122: Windows 11:10:0:0 | M122: Estación de trabajo | N122: Buencafe_Fabrica | O122: 11.9.100.182 | P122: 38BAF851D529 | Q122: Desactivado
A123: R90RG1LZ | B123: CALI14 | C123: APER | D123: 23/12/25 12:30:14 COT | E123: 192.168.40.85 | F123: LENOVO | G123: Tipo de SO:Windows 11,Plataforma de SO:Workstation,Versión de SO:10.0 | H123: 486886 MB | I123: Intel(R) Core(TM) i7-8550U CPU @ 1.80GHz | J123: 20LEA01100 | K123: 16.234,49 MB | L123: Windows 11:10:0:0 | M123: Estación de trabajo | N123: Buencafe_Fabrica | O123: 11.9.100.182 | P123: 34E12D0F8A34 | Q123: Desactivado
A124: MJ08D3FB | B124: CALI22 | C124: CafeVerde | D124: 23/12/25 12:07:30 COT | E124: ########## | F124: LENOVO | G124: Tipo de SO:Windows 11,Plataforma de SO:Workstation,Versión de SO:10.0 | H124: 952591 MB | I124: Intel(R) Xeon(R) E-2124G CPU @ 3.40GHz | J124: 30C6S0JB00 | K124: 16.224,09 MB | L124: Windows 11:10:0:0 | M124: Estación de trabajo | N124: Buencafe_Fabrica | O124: 11.9.100.182 | P124: 00D8614642FB | Q124: Desactivado
A125: PF4F45N5 | B125: CALI29 | C125: egar | D125: 23/12/25 12:24:19 COT | E125: 192.168.40.129 | F125: LENOVO | G125: Tipo de SO:Windows 11,Plataforma de SO:Workstation,Versión de SO:10.0 | H125: 486108 MB | I125: 12th Gen Intel(R) Core(TM) i7-1255U | J125: 21E40023LM | K125: 16.059,65 MB | L125: Windows 11:10:0:0 | M125: Estación de trabajo | N125: Buencafe_Fabrica | O125: 11.9.100.182 | P125: B0DCEF8C686A | Q125: Desactivado
... A132: HA0TEC1N | B132: CATACION3 | C132: N/A | D132: 26/05/25 11:50:55 COT | E132: 192.168.40.206 | F132: LENOVO | G132: Tipo de SO:Windows 10,Plataforma de SO:Workstation,Versión de SO:10.0 | H132: 58861 MB | I132: Intel(R) Atom(TM) x5-Z8550 CPU @ 1.44GHz | J132: Lenovo YB1-X91F | K132: 4.010,12 MB | L132: Windows 10:10:0:0 | M132: Estación de trabajo | N132: Buencafe_Fabrica | O132: 11.9.100.182 | P132: 64DB43E714DD | Q132: Desactivado
A133: 24464191253 | B133: CATACION5 | C133: N/A | D133: 27/10/25 14:19:36 COT | E133: 192.168.40.208 | F133: Microsoft Corporation | G133: Tipo de SO:Windows 11,Plataforma de SO:Workstation,Versión de SO:10.0 | H133: 973582 MB | I133: Intel(R) Core(TM) i7-8650U CPU @ 1.90GHz | J133: Surface Pro 6 | K133: 16.309,01 MB | L133: Windows 11:10:0:0 | M133: Estación de trabajo | N133: Excepcion USB | O133: 11.9.100.182 | P133: B831B589374D | Q133: Desactivado
A134: VMware-56 4d 17 ff 13 ae da f3-4d 12 d6 47 75 e0 cf b2 | B134: CCCAPLICACIONES | C134: administrador | D134: 23/12/25 12:33:23 COT | E134: 192.168.51.168 | F134: VMware, Inc. | G134: Tipo de SO:Windows Server 2019 Standard,Plataforma de SO:Server,Versión de SO:10.0 | H134: 10444101 MB | I134: Intel(R) Xeon(R) Silver 4208 CPU @ 2.10GHz | J134: VMware7,1 | K134: 15.359,03 MB | L134: Windows Server 2019 Standard:10:0:0 | M134: Servidor | N134: SERVIDORES | P134: 000C29E0CFB2 | Q134: Desactivado
A135: VMware-56 4d 45 86 23 22 56 cd-10 fb 88 7f 6e 5e c7 29 | B135: CCCDNS01 | C135: administrador | D135: 21/08/25 9:54:25 COT | E135: 192.168.51.66 | F135: VMware, Inc. | G135: Tipo de SO:Windows 2008 R2,Plataforma de SO:Server,Versión de SO:6.1,Versión de Service Pack de SO:Service Pack 1 | H135: 385972 MB | I135: Intel(R) Xeon(R) Silver 4208 CPU @ 2.10GHz | J135: VMware7,1 | K135: 10.239,03 MB | L135: Windows 2008 R2:6:1:1 | M135: Servidor | N135: SERVIDORES | P135: 000C295EC733 | Q135: Desactivado
A136: VMware-56 4d 74 4d dc bf 3c 1b-72 8d 20 bd 18 21 08 e3 | B136: CCCDOMINIO | C136: administrador | D136: 23/12/25 12:38:48 COT | E136: 192.168.51.167 | F136: VMware, Inc. | G136: Tipo de SO:Windows Server 2019 Standard,Plataforma de SO:Server,Versión de SO:10.0 | H136: 204183 MB | I136: Intel(R) Xeon(R) Silver 4208 CPU @ 2.10GHz | J136: VMware7,1 | K136: 5.119,03 MB | L136: Windows Server 2019 Standard:10:0:0 | M136: Servidor | N136: SERVIDORES | P136: 000C292108ED | Q136: Desactivado
A137: VMware-56 4d 21 22 de 7a c9 f2-72 3a 9f 1c c8 1e 61 f1 | B137: CCCWSUS | C137: N/A | D137: 23/12/25 12:38:12 COT | E137: 192.168.51.96 | F137: VMware, Inc. | G137: Tipo de SO:Windows Server 2019 Standard,Plataforma de SO:Server,Versión de SO:10.0 | H137: 1228165 MB | I137: Intel(R) Xeon(R) Silver 4208 CPU @ 2.10GHz | J137: VMware7,1 | K137: 12.287,03 MB | L137: Windows Server 2019 Standard:10:0:0 | M137: Servidor | N137: SERVIDORES | P137: 000C291E61F1 | Q137: Desactivado
B138: CCTLN01 | C138: fncctolsu2 | D138: 17/07/25 18:24:54 COT | E138: 192.168.75.38 | G138: Tipo de SO:Windows 2008,Plataforma de SO:Server,Versión de SO:6.0,Versión de Service Pack de SO:Service Pack 2 | H138: 2860429 MB | I138: Intel(R) Xeon(R) CPU E5504 @ 2.00GHz | K138: 4.085,30 MB | L138: WVSTS:6:0:2 | M138: Servidor | N138: SERVIDORES | P138: 00219b9ccb85 | Q138: Desactivado
B139: CCVLN01 | D139: 23/12/25 12:19:49 COT | E139: 192.168.70.38 | G139: Tipo de SO:Windows Server 2012 R2,Plataforma de SO:Server,Versión de SO:6.3 | H139: 3814827 MB | I139: Intel(R) Xeon(R) CPU E5-2609 v3 @ 1.90GHz | K139: 7.935,61 MB | L139: Windows Server 2012 R2:6:3:0 | M139: Servidor | N139: SERVIDORES | P139: A02BB831F631 | Q139: Activada
A140: MJ0K4WQA | B140: CHARALA01 | C140: ALMACEN CHARALA | D140: 21/12/25 11:05:43 COT | E140: 192.168.150.4 | F140: LENOVO | G140: Tipo de SO:Windows 11,Plataforma de SO:Workstation,Versión de SO:10.0 | H140: 486107 MB | I140: 12th Gen Intel(R) Core(TM) i7-12700T | J140: 11T4S75C00 | K140: 16.065,13 MB | L140: Windows 11:10:0:0 | M140: Estación de trabajo | N140: Comite Municipal Santander | O140: 11.11.2.1172 | P140: E880883F78DB | Q140: Desactivado
A141: MZ00RXVD | B141: CHEXPRESS01 | C141: Alm. Cafe Express | D141: 23/12/25 12:17:24 COT | E141: 192.168.217.22 | F141: LENOVO | G141: Tipo de SO:Windows 11,Plataforma de SO:Workstation,Versión de SO:10.0 | H141: 486107 MB | I141: 13th Gen Intel(R) Core(TM) i5-13400T | J141: 12E4S8PL00 | K141: 16.023,15 MB | L141: Windows 11:10:0:0 | M141: Estación de trabajo | N141: Directory | P141: 250410000000000 | Q141: Desactivado
A142: MJ0M0CME | B142: CHINCHINA01 | C142: CHINCHINA01 | D142: 23/12/25 12:34:57 COT | E142: 192.168.101.15 | F142: LENOVO | G142: Tipo de SO:Windows 11,Plataforma de SO:Workstation,Versión de SO:10.0 | H142: 486107 MB | I142: 13th Gen Intel(R) Core(TM) i5-13400T | J142: 12E4S8PL00 | K142: 16.023,16 MB | L142: Windows 11:10:0:0 | M142: Estación de trabajo | N142: Comite Norte Santander | O142: 11.11.2.1172 | P142: FC5CEE80735A | Q142: Desactivado
A143: MP15GQL9 | B143: CHINCHINA02 | C143: Alm. Chinchina 2 | D143: 23/12/25 12:31:31 COT | E143: 192.168.101.16 | F143: LENOVO | G143: Tipo de SO:Windows 10,Plataforma de SO:Workstation,Versión de SO:10.0 | H143: 921258 MB | I143: Intel(R) Core(TM) i5-7400T CPU @ 2.40GHz | J143: F0CD00GNLD | K143: 8.103,46 MB | L143: Windows 10:10:0:0 | M143: Estación de trabajo | N143: Comites Municipales Caldas | O143: 11.11.2.1172 | P143: FC45967BE446 | Q143: Desactivado
A144: MP15GMS1 | B144: CHINCHINA03 | C144: Alm. Cafe Chinchin 3 | D144: 23/12/25 12:36:48 COT | E144: 192.168.101.17 | F144: LENOVO | G144: Tipo de SO:Windows 10,Plataforma de SO:Workstation,Versión de SO:10.0 | H144: 921258 MB | I144: Intel(R) Core(TM) i5-7400T CPU @ 2.40GHz | J144: F0CD00GNLD | K144: 8.103,46 MB | L144: Windows 10:10:0:0 | M144: Estación de trabajo | N144: Comites Municipales Caldas | O144: 11.11.2.1172 | P144: FC45967BC8C2 | Q144: Desactivado
A145: 5WPH942 | B145: CHINCHINA04 | C145: Alm. Cafe Chinchina | D145: 23/12/25 12:32:57 COT | E145: 192.168.101.12 | F145: Dell Inc. | G145: Tipo de SO:Windows 10,Plataforma de SO:Workstation,Versión de SO:10.0 | H145: 476363 MB | I145: Intel(R) Core(TM) i5-4590 CPU @ 3.30GHz | J145: OptiPlex 3020 | K145: 8.110,44 MB | L145: Windows 10:10:0:0 | M145: Estación de trabajo | N145: Comites Municipales Caldas | O145: 11.11.2.1172 | P145: B083FE7AD8AE | Q145: Desactivado
A146: 5CG0379BMR | B146: CLAUDIAMONTAÑEZ | C146: Claudia Montañez | D146: 18/12/25 14:35:53 COT | E146: 192.168.1.21 | F146: HP | G146: Tipo de SO:Windows 11,Plataforma de SO:Workstation,Versión de SO:10.0 | H146: 951602 MB | I146: Intel(R) Core(TM) i5-1035G1 CPU @ 1.00GHz | J146: HP 240 G7 Notebook PC | K146: 11.976,70 MB | L146: Windows 11:10:0:0 | M146: Estación de trabajo | N146: Comite Santander | O146: 11.11.2.1172 | P146: 5C3A451F701B | Q146: Desactivado
A147: 22020472H | B147: CLAUDIA-SANCHEZ | C147: Sala Juntas | D147: 23/12/25 11:11:22 COT | E147: 192.168.91.28 | F147: Dynabook Inc. | G147: Tipo de SO:Windows 10,Plataforma de SO:Workstation,Versión de SO:10.0 | H147: 476756 MB | I147: Intel(R) Core(TM) i5-1035G1 CPU @ 1.00GHz | J147: Satellite Pro C40-H | K147: 16.127,98 MB | L147: Windows 10:10:0:0 | M147: Estación de trabajo | N147: Comite Santander | O147: 11.11.2.1172 | P147: 201E88C977EB | Q147: Desactivado
A148: MJ0G6RKV | B148: CLIE02 | C148: secscli | D148: 29/09/25 12:30:59 COT | E148: ########## | F148: LENOVO | G148: Tipo de SO:Windows 11,Plataforma de SO:Workstation,Versión de SO:10.0 | H148: 952678 MB | I148: Intel(R) Core(TM) i7-10700 CPU @ 2.90GHz | J148: 11CES0QN00 | K148: 7.864,93 MB | L148: Windows 11:10:0:0 | M148: Estación de trabajo | N148: Buencafe_Fabrica | O148: 11.9.100.182 | P148: 083A8869ACEB | Q148: Desactivado
A149: MJ04RYDX | B149: CNICAARCM | C149: AARCILA559 | D149: 18/12/25 10:13:22 COT | E149: 192.168.48.79 | F149: LENOVO | G149: Tipo de SO:Windows 10,Plataforma de SO:Workstation,Versión de SO:10.0 | H149: 961869 MB | I149: Intel(R) Core(TM) i7-6700T CPU @ 2.80GHz | J149: 10J0A0XV00 | K149: 32.657,40 MB | L149: Windows 10:10:0:0 | M149: Estación de trabajo | N149: Cenicafe | O149: 11.9.100.182 | P149: 6C0B84E08FDB | Q149: Desactivado
A150: PC0MVTBK | B150: CNICAARCMNTBK | C150: AARCILA559 | D150: 5/11/25 23:55:39 COT | E150: 192.168.79.122 | F150: LENOVO | G150: Tipo de SO:Windows 10,Plataforma de SO:Workstation,Versión de SO:10.0 | H150: 461372 MB | I150: Intel(R) Core(TM) i5-7200U CPU @ 2.50GHz | J150: 20HMS1AC00 | K150: 8.047,98 MB | L150: Windows 10:10:0:0 | M150: Estación de trabajo | N150: Cenicafe | P150: 250410000000000 | Q150: Desactivado
A151: VMware-42 35 b2 e8 0e e6 45 ec-25 e5 32 18 f9 fa 99 81 | B151: CNICADSLAVE | C151: administrator | D151: 28/06/25 22:20:20 COT | E151: 192.168.194.53 | F151: VMware, Inc. | G151: Tipo de SO:Windows Server 2019 Datacenter,Plataforma de SO:Server,Versión de SO:10.0 | H151: 81411 MB | I151: Intel(R) Xeon(R) CPU E5-2667 v4 @ 3.20GHz | J151: VMware Virtual Platform | K151: 12.287,55 MB | L151: Windows Server 2019 Datacenter:10:0:0 | M151: Servidor | N151: Cenicafe | P151: 005056B519B9 | Q151: Desactivado
A152: MJ04RYDD | B152: CNICAEPENM | C152: APENUEL640 | D152: 19/12/25 13:45:10 COT | E152: 192.168.49.160 | F152: LENOVO | G152: Tipo de SO:Windows 11,Plataforma de SO:Workstation,Versión de SO:10.0 | H152: 961194 MB | I152: Intel(R) Core(TM) i7-6700T CPU @ 2.80GHz | J152: 10J0A0XV00 | K152: 32.657,40 MB | L152: Windows 11:10:0:0 | M152: Estación de trabajo | N152: Cenicafe | O152: 11.9.100.182 | P152: 6C0B84E0EAFD | Q152: Desactivado
A153: R90QEGTG | B153: CNICAEPENMNTBK | C153: APENUEL640 | D153: 21/12/25 11:01:23 COT | E153: 192.168.1.8 | F153: LENOVO | G153: Tipo de SO:Windows 11,Plataforma de SO:Workstation,Versión de SO:10.0 | H153: 472818 MB | I153: Intel(R) Core(TM) i5-8250U CPU @ 1.60GHz | J153: 20M8S0D600 | K153: 16.234,13 MB | L153: Windows 11:10:0:0 | M153: Estación de trabajo | N153: Cenicafe | O153: 11.9.100.182 | P153: D46D6D6596EF | Q153: Desactivado
A154: PF2KH601 | B154: CNICAEPENMNTBK1 | C154: Cenicafe | D154: 9/12/25 10:53:55 COT | E154: 192.168.14.106 | F154: LENOVO | G154: Tipo de SO:Windows 11,Plataforma de SO:Workstation,Versión de SO:10.0 | H154: 461372 MB | I154: Intel(R) Core(TM) i5-10210U CPU @ 1.60GHz | J154: 20RBS1FE00 | K154: 16.157,63 MB | L154: Windows 11:10:0:0 | M154: Estación de trabajo | N154: Cenicafe | P154: 683E268B73C4 | Q154: Activada
...

Sheet Equipo en Estado Baja
A1: EMPRESA PROPIETARIO DEL EQUIPO | B1: DEPENDENCIA | C1: FUENTE DE RECURSO | D1: EMPRESA FUNCIONARIO | E1: CEDULA DEL FUNCIONARIO | F1: SHORTNAME | G1: NOMBRES Y APELLIDOS | H1: CARGO | I1: ÁREA | J1: UBICACIÓN Y PISO | K1: TIPO | L1: SERIAL | M1: PLACA | N1: MARCA | O1: MODELO | P1: NOMBRE DE EQUIPO | Q1: ESTADO OPERATIVO | R1: RAZÓN DEL ESTADO | S1: ADMINISTRADO/CONTROLADO | T1: PROCESADOR | U1: MEMORIA RAM | V1: TAMAÑO DISCO DURO | W1: SISTEMA OPERATIVO | X1: FECHA DE COMPRA | Y1: FIN DE GARANTIA | Z1: TIEMPO USO (AÑOS) | AA1: TIPO DE PROPIEDAD | AB1: CHEKLIST (RESPONSABLE TI) | AC1: ORDEN DE REMISIÓN

Sheet Listas De Validación Equipos 
A1: EMPRESA PROPIETARIO DEL EQUIPO | C1: DEPENDENCIA | E1: FUENTE DE RECURSO | G1: EMPRESA DE FUNCIONARIO | I1: TIPO | K1: ESTADO | L1: DESCRIPCIÓN DEL ESTADO | M1: RAZÓN DEL ESTADO | N1: DESCRIPCIÓN DEL RAZÓN DEL ESTADO | P1: ADMINISTRADO/CONTROLADO | R1: PROCESADOR | T1: MEMORIA RAM | V1: TAMAÑO DISCO DURO | X1: SISTEMA OPERATIVO
A2: ALMACAFÉ | C2: AGENCIA CUCUTA | E2: FON1 | G2: ALMACAFÉ | I2: EQUIPO ESCRITORIO | K2: ALMACENADO | L2: TODO ACTIVO QUE SE ENCUENTRA RESERVADO EN UNA BODEGA. | M2: DISPONIBLE | N2: TODO ACTIVO QUE SE ENCUENTRE DISPONIBLE NUEVO O USADO PARA ASIGNACIÓN A USUARIO FINAL. | P2: ADMINISTRADO | R2: 11TH GEN INTEL(R) CORE(TM) I3-1115G4 @ 3.00GHZ | T2: 12GB | V2: 120GB | X2: ANDROID
A3: FEDERACIÓN | C3: AGENCIA PASTO | E3: FON2 | G3: FEDERACIÓN | I3: EQUIPO PORTATIL | K3: TRÁNSITO | L3: TODO ACTIVO QUE SE ENCUENTRA EN CIRCULACIÓN. | M3: CUSTODIA | N3: TODO ACTIVO QUE INGRESE A BODEGA ESTARÁ ALMACENADO 15 DÍAS HÁBILES, DESPÚES DE ESTE TIEMPO SE REALIZARÁ EL CAMBIO DE ESTADO A DISPONIBLE PARA SU ASIGNACIÓN SEGÚN SE REQUIERA. | P3: CONTROLADO | R3: 11TH GEN INTEL(R) CORE(TM) I5-1135G7 @ 2.40GHZ | T3: 16GB | V3: 128GB | X3: IOS
A4: BANCOLOMBIA | C4: AGENCIA POPAYAN | E4: FEPC | G4: TIVIT | I4: EQUIPO TODO EN UNO | K4: EN OPERACIÓN | L4: TODO ACTIVO QUE SE ENCUENTRA EN USO POR PARTE DE UN COLABORADOR. | M4: ALISTAMIENTO / SOPORTE | N4: TODOS AQUELLOS ACTIVOS QUE SE ENCUENTREN EN PROCESO DE ALISTAMIENTO, MANTENIMIENTO, SOPORTE O GARANTÍA | R4: 11TH GEN INTEL(R) CORE(TM) I5-11400 @ 2.60GHZ | T4: 1GB | V4: 16GB | X4: LINUX
A5: CAFECERT | C5: BUENCAFÉ | E5: ALMACAFÉ | G5: SAMTEL | I5: IMPRESORA | K5: BAJA | L5: TODO ACTIVO QUE SE ENCUENTRA EN PROCESO PARA DISPOCISIÓN FINAL. | M5: RENOVACIÓN | N5: TODO ACTIVO NUEVO QUE INGRESA A BODEGA CON LA FINALIDAD DE REALIZAR LA ACTUALIZACIÓN DE LOS MISMOS. | R5: 11TH GEN INTEL(R) CORE(TM) I5-11400T @ 1.30GHZ | T5: 20GB | V5: 180GB | X5: MACOS BIG SUR
M6: PROCESAR BAJA | N6: TODO ACTIVO QUE SE ENCUENTRA EN PEL PROCESO DE BAJA. | R6: No Aplica | T6: No Aplica | V6: No Aplica | X6: No Aplica
A7: FONDO NACIONAL | C7: CENICAFÉ | G7: TECNOFILE | I7: TABLETA | K7: HURTO | L7: TODO ACTIVO HURTADO. | M7: DESPACHO | N7: TODO ACTIVO QUE SE ENCUENTRA EN MOVIMIENTO O TRASLADO DESDE LA OFICINA BOGOTÁ PARA LAS SEDES, COMITES E INSPECCIONES A NIVEL NACIONAL. | R7: 11TH GEN INTEL(R) CORE(TM) I5-1145G7 @ 2.60GHZ | T7: 24GB | V7: 1TB | X7: MACOS CATALINA
C8: COMITÉ ANTIOQUIA | I8: ESANER | M8: RETORNO | N8: TODO ACTIVO QUE SE ENCUENTRA EN MOVIMIENTO O TRASLADO DESDE SEDES,COMITÉS Ó INSPECCIONES A NIVEL NACIONAL QUE SEAN ENVIADOS A LA OFICINA BOGOTÁ. | R8: 11TH GEN INTEL(R) CORE(TM) I5-1155G7 @ 2.50GHZ | T8: 2GB | V8: 1TB + 500GB | X8: MACOS MONTEREY
C9: COMITÉ BOYACÁ | I9: MONITOR | M9: ASIGNACIÓN RESPONSABLE | N9: TODO ACTIVO QUE SE ENCUENTRE SIENDO UTILIZADO POR USUARIO CUYO CARGO CORRESPONDAN A (APRENDICES O TERCEROS), SERÁN ASIGNADOS A UN USUARIO RESPONSABLE. | R9: 11TH GEN INTEL(R) CORE(TM) I7-11370H @ 3.30GHZ | T9: 32GB | V9: 240GB | X9: MACOS SEQUOIA
C10: COMITÉ CALDAS | M10: PRÉSTAMO | N10: TODO ACTIVO QUE SE ENCEUNTRE ASIGNADO EN CALIDAD DE PRÉSTAMO POR UN TIEMPO NO MAYOR A 15 DÍAS CALENDARIO | R10: 11TH GEN INTEL(R) CORE(TM) I7-1165G7 @ 2.80GHZ | T10: 4GB | V10: 250GB | X10: MACOS SONOMA
C11: COMITÉ CAUCA | M11: HURTO / PERDIDA | N11: TODO ACTIVO QUE SE ENCUENTRE EXTRAVIADO / HURTADO, EL CUAL DEBE CONTAR CON SU SOPORTE CORRESPONDIENTE (DENUNCIA). | R11: 11TH GEN INTEL(R) CORE(TM) I7-11700 @ 2.50GHZ | T11: 512 MB | V11: 256GB | X11: MACOS VENTURA
C12: COMITÉ CESAR GUAJIRA | M12: DEVUELTO A PROVEEDOR | N12: TODO ACTIVO QUE SE ENCUENTRA EN PROCESO DE DEVOLUCIÓN AL PROVEEDOR POR CONCEPTOS DE RENTA Y/O LEASING | R12: 11TH GEN INTEL(R) CORE(TM) I7-11700T @ 1.40GHZ | T12: 6GB | V12: 300GB
C13: COMITÉ CUNDINAMARCA | M13: DONACIÓN | N13: EQUIPO DADO EN DONACIÓN POR PARTE DE FNC O ALM | R13: 11TH GEN INTEL(R) CORE(TM) I7-11800H @ 2.30GHZ | T13: 8GB | V13: 320GB | X13: WINDOWS 10 PRO
C14: COMITÉ HUILA | M14: BAJA | N14: TODO ACTIVO EL CUAL SE LE REALIZA BAJA POR OBSOLECENSIA O DAÑO. | R14: 12TH GEN INTEL(R) CORE(TM) I5-1235U | V14: 4 TB | X14: WINDOWS 11 PRO
C15: COMITÉ MAGDALENA | R15: 12TH GEN INTEL(R) CORE(TM) I5-1240P | V15: 480GB | X15: WINDOWS 7
C16: COMITÉ NARIÑO | R16: 12TH GEN INTEL(R) CORE(TM) I5-12450H | V16: 500GB | X16: WINDOWS 8
C17: COMITÉ NTE SANTANDER | R17: 12TH GEN INTEL(R) CORE(TM) I5-12500 | V17: 512GB | X17: WINDOWS 8.1
C18: COMITÉ QUINDIO | R18: 12TH GEN INTEL(R) CORE(TM) I7-1250U | V18: 5TB | X18: WINDOWS VISTA
C19: COMITÉ RISARALDA | R19: 12TH GEN INTEL(R) CORE(TM) I7-1255U | V19: 600GB | X19: WINDOWS XP
C20: COMITÉ SANTANDER | R20: 12TH GEN INTEL(R) CORE(TM) I7-1260P | V20: 720GB | X20: WINDOWS 11 HOME
C21: COMITÉ TOLIMA | R21: 12TH GEN INTEL(R) CORE(TM) I7-1260U | V21: 750GB | X21: WINDOWS 10 HOME
C22: COMITÉ VALLE | R22: 12TH GEN INTEL(R) CORE(TM) I7-1265U | V22: 64GB
C23: INSPECCION CAFETERA BUENAVENTURA | R23: 12TH GEN INTEL(R) CORE(TM) I7-12700 | V23: SSD 256GB
C24: INSPECCION CAFETERA CARTAGENA | R24: 12TH GEN INTEL(R) CORE(TM) I7-12700H
C25: INSPECCION CAFETERA SANTA MARTA | R25: 12TH GEN INTEL(R) CORE(TM) I7-12700T
C26: OFICINA BUENAVENTURA | R26: 12TH GEN INTEL(R) CORE(TM) I7-1280P
C27: OFICINA CARTAGENA | R27: 13TH GEN INTEL(R) CORE(TM) I5-1335U
C28: OFICINAS COORDINADORAS Y OTROS TERRITORIOS | R28: 13TH GEN INTEL(R) CORE(TM) I5-13400T
C29: PLANTA TORREFACTORA | R29: 13TH GEN INTEL(R) CORE(TM) I5-13420H
C30: SEDE BOGOTÁ | R30: 13TH GEN INTEL(R) CORE(TM) I5-13500
C31: SUCURSAL ARMENIA | R31: 13TH GEN INTEL(R) CORE(TM) I5-13500T
C32: SUCURSAL BOGOTA (SOACHA) | R32: 13TH GEN INTEL(R) CORE(TM) I7-1355U
C33: SUCURSAL BUCARAMANGA | R33: 13TH GEN INTEL(R) CORE(TM) I7-1360P
C34: SUCURSAL BUGA | R34: 13TH GEN INTEL(R) CORE(TM) I7-1365U
C35: SUCURSAL CELTA | R35: 13TH GEN INTEL(R) CORE(TM) I7-13700
... C41: SUCURSAL SANTA MARTA | R41: AMD E2-7110 APU WITH AMD RADEON R2 GRAPHICS
R42: AMD RYZEN 3 2200U WITH RADEON VEGA MOBILE GFX
R43: AMD RYZEN 3 3200U WITH RADEON VEGA MOBILE GFX
R44: AMD RYZEN 3 5300U WITH RADEON GRAPHICS
R45: AMD RYZEN 5 3450U WITH RADEON VEGA MOBILE GFX
R46: AMD RYZEN 5 3500U WITH RADEON VEGA MOBILE GFX
R47: AMD RYZEN 5 5500U WITH RADEON GRAPHICS
R48: AMD RYZEN 5 5600H WITH RADEON GRAPHICS
R49: AMD RYZEN 5 7520U WITH RADEON GRAPHICS
R50: AMD RYZEN 5 PRO 7530U WITH RADEON GRAPHICS
R51: AMD RYZEN 7 5700G WITH RADEON GRAPHICS
R52: AMD RYZEN 7 5700U WITH RADEON GRAPHICS
R53: AMD RYZEN 7 7735U WITH RADEON GRAPHICS
... R254: Exynos 9810 de ocho núcleos a 2 GHz + 1,7 GHz

Sheet Información Licencias
A1: EMPRESA | B1: DEPENDENCIA | C1: FUENTE DE RECURSO | D1: LÍNEA | E1: TIPO DE SOFTWARE | F1: TIPO DE LICENCIA | G1: FABRICANTE | H1: PROVEEDOR | I1: VALOR | J1: NOMBRE DEL PRODUCTO | K1: DESCRIPCIÓN DEL PRODUCTO | L1: PLATAFORMA S.O | M1: ESTADO DE LICENCIA | N1: CANTIDAD LICENCIAS CONTRATADAS | O1: CANTIDAD DE LICENCIAS INSTALADAS/ASIGNADAS | P1: TOTAL LICENCIAS DISPONIBLES | Q1: FECHA DE COMPRA | R1: FECHA VENCIMIENTO | S1: EVIDENCIA FACTURA | T1: OBSERVACIONES

Sheet Asignación Licencias
A1: NOMBRE DEL PRODUCTO | B1: SERIAL EQUIPO INSTALADO | C1: PLACA EQUIPO INSTALADO | D1: CEDULA DEL FUNCIONARIO | E1: SHORTNAME | F1: NOMBRES Y APELLIDOS | G1: CARGO | H1: ÁREA

Sheet Listas De Validación Licencias
A1: EMPRESA | C1: DEPENDENCIA | E1: FUENTE DE RECURSO | G1: LINEA | I1: TIPO DE SOFTWARE | K1: TIPO DE LICENCIA
A2: ALMACAFÉ | C2: AGENCIA CUCUTA | E2: FON1 | G2: INFRAESTRUCTURA | I2: SOFTWARE DE SISTEMA | K2: CÓDIGO ABIERTO
A3: FEDERACIÓN | C3: AGENCIA PASTO | E3: FON2 | G3: APLICACIONES | I3: SOFTWARE DE APLICACIÓN | K3: FREEWARE
A4: CAFECERT | C4: AGENCIA POPAYAN | E4: FEPC | G4: OFIMÁTICA | I4: SOFTWARE DE DESARROLLO | K4: SHAREWARE
C5: BUENCAFÉ | E5: ALMACAFÉ | K5: SAAS (SOFTWARE COMO SERVICIO)
C6: CENICAFÉ | K6: SUSCRIPCIÓN
C7: COMITÉ ANTIOQUIA | K7: PERPETUAS
C8: COMITÉ BOYACÁ | K8: FLOTANTES/CONCURRENTES
C9: COMITÉ CALDAS
C10: COMITÉ CAUCA
C11: COMITÉ CESAR GUAJIRA
C12: COMITÉ CUNDINAMARCA
C13: COMITÉ HUILA
C14: COMITÉ MAGDALENA
C15: COMITÉ NARIÑO
C16: COMITÉ NTE SANTANDER
C17: COMITÉ QUINDIO
C18: COMITÉ RISARALDA
C19: COMITÉ SANTANDER
C20: COMITÉ TOLIMA
... C40: SUCURSAL SANTA MARTA
